Workbook

Sheet Top 300
A1: In scope | B1: Leveranciersnummer | C1: Leveranciersnaam | D1: Totaal # artikelen | E1: pdf | F1: tekst in mail | G1: via link in mail | H1: Nota
A2: X | B2: 3001044 | C2: ABENA BV | D2: 36 | F2: x
A3: X | B3: 3000096 | C3: ADDED PHARMA BV | D3: 22 | E3: x
A4: X | B4: 3000002 | C4: AKB GROOTVERBRUIK B.V. | D4: 20 | E4: x
A5: X | B5: 3000190 | C5: ALCON NEDERLAND BV | D5: 24 | F5: x
A6: X | B6: 3000395 | C6: ALCON NV | D6: 16 | F6: x
A7: X | B7: 3000431 | C7: ALPHEIOS | D7: 24 | E7: x
A8: X | B8: 3000132 | C8: ALPHEIOS BV | D8: 48 | E8: x
A9: X | B9: 3000019 | C9: AMBU BV | D9: 15 | E9: x
A10: X | B10: 3002833 | C10: AMBU BV Belgie | D10: 18 | E10: x
A11: X | B11: 3003735 | C11: APPLIED MEDICAL BELGIUM BV | D11: 7 | E11: x
A12: X | B12: 3000239 | C12: APPLIED MEDICAL BV | D12: 68 | E12: x
A13: X | B13: 3000003 | C13: ARGUS ETIKETTEN BV | D13: 24 | E13: x
A14: X | B14: 3001279 | C14: ARJO BELGIUM NV | D14: 6 | E14: x
A15: X | B15: 3000939 | C15: ARJO NEDERLAND BV | D15: 16 | E15: x
A16: X | B16: 3004411 | C16: ARSEUS MEDICAL GROUP BV | D16: 1 | E16: x
A17: X | B17: 3000687 | C17: ARSEUS MEDICAL GROUP NV | D17: 2 | E17: x
A18: X | B18: 3004318 | C18: ARSEUS MEDICAL GROUP NV AZ DIMPNA | D18: 7 | E18: x
... A24: X | B24: 3004338 | C24: ARSEUS MEDICAL GROUP NV WZC | D24: 6 | E24: x
A25: X | B25: 3002156 | C25: ARTHREX BVBA | D25: 14
A26: X | B26: 3001236 | C26: ARTHREX NEDERLAND BV | D26: 26
A27: X | B27: 3004380 | C27: AT MEDICALS BVBA AZ ST DIMPNA GEEL | D27: 3 | E27: x
A28: X | B28: 3004382 | C28: AT MEDICALS BVBA EMMAUS | D28: 2 | E28: x
A29: X | B29: 3004383 | C29: AT MEDICALS BVBA IMELDA | D29: 7 | E29: x
A30: X | B30: 3004381 | C30: AT MEDICALS BVBA SAL | D30: 16 | E30: x
A31: X | B31: 3000005 | C31: B. BRAUN MEDICAL BV | D31: 360 | E31: x | H31: AFW: bruto naar netto prijs
A32: X | B32: 3000465 | C32: B.BRAUN MEDICAL N.V. | D32: 186 | E32: x
A33: X | B33: 3002134 | C33: BAUSCH & LOMB BVBA | D33: 1 | F33: x
A34: X | B34: 3000966 | C34: BAUSCH EN LOMB SURGICAL | D34: 21 | F34: x
A35: X | B35: 3004257 | C35: BAXTER BE BVBA AZ ST DIMPNA | D35: 4 | F35: x
A36: X | B36: 3004260 | C36: BAXTER BE BVBA AZH | D36: 5 | F36: x
A37: X | B37: 3004256 | C37: BAXTER BE BVBA CHC | D37: 5 | F37: x
A38: X | B38: 3004255 | C38: BAXTER BE BVBA EMMAUS | D38: 1 | F38: x
A39: X | B39: 3004259 | C39: BAXTER BE BVBA IMELDA | D39: 8 | F39: x
A40: X | B40: 3004258 | C40: BAXTER BE BVBA SAL | D40: 4 | F40: x
A41: X | B41: 3000263 | C41: BAXTER BV | D41: 132 | F41: x
A42: X | B42: 3000952 | C42: BAYER HEALTHCARE | D42: 24 | F42: x
A43: X | B43: 3000008 | C43: BECTON DICKINSON BV | D43: 515 | E43: x | G43: x | H43: OB => alleen van art met LT?
A44: X | B44: 3003861 | C44: BECTON DICKINSON BV EU NL1033064313 | D44: 3 | E44: x | G44: x
A45: X | B45: 3000374 | C45: BECTON DICKINSON NV | D45: 316 | E45: x | G45: x
A46: X | B46: 3000134 | C46: BELDICO BV | D46: 39 | E46: x
A47: X | B47: 3003864 | C47: BELDICO BV EUROFINS NL1033067738 | D47: 1 | E47: x
A48: X | B48: 3001391 | C48: BOMA NEDERLAND BV | D48: 11 | F48: x
A49: X | B49: 3004629 | C49: BOMA NV AZH | D49: 1 | F49: x
A50: X | B50: 3004312 | C50: BOMA NV CHC | D50: 2 | F50: x
A51: X | B51: 3004193 | C51: BOMA NV EMMAUS | D51: 19 | F51: x
A52: X | B52: 3004194 | C52: BOMA NV IMELDA | D52: 32 | F52: x
A53: X | B53: 3004195 | C53: BOMA NV SAL | D53: 18 | F53: x
A54: X | B54: 3004196 | C54: BOMA NV WZC | D54: 93 | F54: x | H54: AFW: LT niet op artikelniveau
A55: X | B55: 3001867 | C55: BOSTON SCIENTIFIC BENELUX NV | D55: 19
A56: X | B56: 3000135 | C56: BOSTON SCIENTIFIC NEDERLAND BV | D56: 58
A57: X | B57: 3004464 | C57: Bracco Imaging Europe | D57: 5 | E57: x
A58: X | B58: 3000021 | C58: BRACCO IMAGING EUROPE BV | D58: 16 | E58: x
A59: X | B59: 3001270 | C59: BRIDEA MEDICAL BV | D59: 20
A60: X | B60: 3000009 | C60: BROCACEF ZORGLOGISTIEK BV | D60: 262 | E60: x | H60: AFW: OB per klant, ook update over artikel besteld op andere PO
A61: X | B61: 3003116 | C61: BUROFORM NV | D61: 33
A62: X | B62: 3000884 | C62: CAIR BELGIUM | D62: 54
A63: X | B63: 3003869 | C63: CaptureTech | D63: 52 | E63: x
A64: X | B64: 3004156 | C64: CARDINAL HEALTH BE AZ ST D | D64: 7 | E64: x
A65: X | B65: 3004155 | C65: CARDINAL HEALTH BE AZH | D65: 22 | E65: x
A66: X | B66: 3004307 | C66: CARDINAL HEALTH BE CHC | D66: 44 | E66: x
A67: X | B67: 3004157 | C67: CARDINAL HEALTH BE EMMAUS | D67: 17 | E67: x
A68: X | B68: 3004158 | C68: CARDINAL HEALTH BE IMELDA | D68: 20 | E68: x | H68: AFW: er wordt nooit LT vermeld
A69: X | B69: 3004159 | C69: CARDINAL HEALTH BE SAL | D69: 47 | E69: x
A70: X | B70: 3001922 | C70: CARDINAL HEALTH NETHERLANDS 502 BV | D70: 132 | E70: x
A71: X | B71: 3002496 | C71: CAREL LURVINK | D71: 28 | E71: x
A72: X | B72: 3000231 | C72: CAZANDER MEDICAL BV | D72: 22 | E72: x
A73: X | B73: 3000563 | C73: COCA-COLA BEVERAGES (1991) N.V | D73: 32 | E73: x
A74: X | B74: 3000011 | C74: CODAN BV | D74: 136
A75: X | B75: 3003978 | C75: CODAN GHZ | D75: 10
A76: X | B76: 3003977 | C76: CODAN PMC | D76: 28
A77: X | B77: 3000012 | C77: COLOPLAST BV | D77: 96
A78: X | B78: 3004422 | C78: COLOPLAST NV AZ ST DIMPNA | D78: 5
A79: X | B79: 3004421 | C79: COLOPLAST NV AZH | D79: 7
A80: X | B80: 3004418 | C80: COLOPLAST NV CHC | D80: 35
A81: X | B81: 3004423 | C81: COLOPLAST NV EMMAUS | D81: 11
A82: X | B82: 3004424 | C82: COLOPLAST NV IMELDA | D82: 47
A83: X | B83: 3004425 | C83: COLOPLAST NV SAL | D83: 22
A84: X | B84: 3000896 | C84: CONVATEC BELGIUM BVBA | D84: 7 | E84: x
A85: X | B85: 3000014 | C85: CONVATEC BV | D85: 30 | E85: x
A86: X | B86: 3000600 | C86: COOK BELGIUM NV | D86: 28 | E86: x
A87: X | B87: 3001262 | C87: COOK NEDERLAND BV | D87: 37 | E87: x
A88: X | B88: 3003839 | C88: CORDIS BELGIUM IMELDA | D88: 23 | F88: x
A89: X | B89: 3003840 | C89: CORDIS NETHERLANDS | D89: 16 | F89: x
A90: X | B90: 3003100 | C90: DAILY FRESH FOOD BV | D90: 112
A91: X | B91: 3000050 | C91: DAKLAPACK EUROPE BV | D91: 43 | E91: x
A92: X | B92: 3003862 | C92: DAKLAPACK EUROPE BV EU NL1033067753 | D92: 1 | E92: x
A93: X | B93: 3001622 | C93: DANONE BELUX NV | D93: 59
A94: X | B94: 3004631 | C94: De Bondt Grafimedia Communicatie BV | D94: 28
A95: X | B95: 3002940 | C95: DEFORCE MEDICAL BVBA | D95: 31 | E95: x
A96: X | B96: 3000835 | C96: DEMUYNCK-VERRAX NV | D96: 30
A97: X | B97: 3004092 | C97: DIALEX BIOMEDICA NV AZ ST DIMPNA | D97: 8
A98: X | B98: 3004094 | C98: DIALEX BIOMEDICA NV AZH | D98: 3
A99: X | B99: 3004302 | C99: DIALEX BIOMEDICA NV CHC | D99: 2
A100: X | B100: 3004093 | C100: DIALEX BIOMEDICA NV EMMAUS | D100: 5
A101: X | B101: 3004090 | C101: DIALEX BIOMEDICA NV IMELDA | D101: 16
A102: X | B102: 3004095 | C102: DIALEX BIOMEDICA NV OPZ | D102: 4
A103: X | B103: 3004091 | C103: DIALEX BIOMEDICA NV SAL | D103: 20
A104: X | B104: 3004452 | C104: DIALEX BIOMEDICA NV WZC | D104: 1
A105: X | B105: 3001329 | C105: DIVERSEY B.V. | D105: 35 | E105: x
...

Sheet Analyse HL 2 (3)
E1: Classification | F1: Standard
E2: GPT-5 Nano | F2: GPT-5 Mini | G2: Hoover te voorzien
N3: Nuttig veld? | R3: Nuttig veld?
E4: =COUNTA(Table326[File Name]) -> 99 | F4: =COUNTIF(Table326[Recognised doc type],"extracted") -> 77 | G4: =SUM(Table326['# Missing fields]) -> 69 | H4: =AVERAGE(Table326[PO nr]) -> 0.95652174 | I4: =AVERAGE(Table326[Supplier Order Nr]) -> 0.91304348 | J4: =AVERAGE(Table326[Order Date]) -> 0.95652174 | K4: =AVERAGE(Table326[Supplier Name]) -> 0.95652174 | L4: =AVERAGE(Table326[Customer name]) -> 0.95652174 | M4: =AVERAGE(Table326[Currency]) -> 0.84782609 | N4: =AVERAGE(Table326[Line nr]) -> 0.91304348 | O4: =AVERAGE(Table326[Article Number]) -> 0.95652174 | P4: =AVERAGE(Table326[Description]) -> 0.93478261 | Q4: =AVERAGE(Table326[Quantity]) -> 0.95652174 | R4: =AVERAGE(Table326[UoM]) -> 0.80434783 | S4: =AVERAGE(Table326[Unit Price]) -> 0.7826087 | T4: =AVERAGE(Table326[Delivery Date]) -> 0.65217391 | U4: =AVERAGE(H4:T4) -> 0.89130435
H5: Confirmation Lines
D6: Customer | E6: File Name | F6: Recognised doc type | G6: # Missing fields | H6: PO nr | I6: Supplier Order Nr | J6: Order Date | K6: Supplier Name | L6: Customer name | M6: Currency | N6: Line nr | O6: Article Number | P6: Description | Q6: Quantity | R6: UoM | S6: Unit Price | T6: Delivery Date | U6: Avg | V6: Comments | W6: Vraag HL | X6: Acties | Y6: Beslissing | Z6: Flexso
C7: =_xlfn.XLOOKUP(Table326[[#This Row],[Customer]],'Top 300'!C:C,'Top 300'!A:A,"0",2,1) -> 0 | D7: =_xlfn.XLOOKUP(Table326[[#This Row],[File Name]],'Analyse 2 Detail 02-03'!A:A,'Analyse 2 Detail 02-03'!R:R,"Not Found",0,1) -> Mölnlycke Health Care NV | E7: _ Orderbevestiging 1501037327.pdf | F7: extracted | G7: 0 | U7: =AVERAGE(Table326[[#This Row],[PO nr]:[Delivery Date]]) -> #DIV/0!
C8: =_xlfn.XLOOKUP(Table326[[#This Row],[Customer]],'Top 300'!C:C,'Top 300'!A:A,"0",2,1) -> 0 | D8: =_xlfn.XLOOKUP(Table326[[#This Row],[File Name]],'Analyse 2 Detail 02-03'!A:A,'Analyse 2 Detail 02-03'!R:R,"Not Found",0,1) -> Mölnlycke Health Care B.V. | E8: _ Orderbevestiging 1504026582.pdf | F8: extracted | G8: 0 | U8: =AVERAGE(Table326[[#This Row],[PO nr]:[Delivery Date]]) -> #DIV/0!
C9: =_xlfn.XLOOKUP(Table326[[#This Row],[Customer]],'Top 300'!C:C,'Top 300'!A:A,"0",2,1) -> 0 | D9: =_xlfn.XLOOKUP(Table326[[#This Row],[File Name]],'Analyse 2 Detail 02-03'!A:A,'Analyse 2 Detail 02-03'!R:R,"Not Found",0,1) -> Mölnlycke Health Care B.V. | E9: _ Orderbevestiging 1505040022.pdf | F9: extracted | G9: 0 | U9: =AVERAGE(Table326[[#This Row],[PO nr]:[Delivery Date]]) -> #DIV/0!
C10: =_xlfn.XLOOKUP(Table326[[#This Row],[Customer]],'Top 300'!C:C,'Top 300'!A:A,"0",2,1) -> 0 | D10: =_xlfn.XLOOKUP(Table326[[#This Row],[File Name]],'Analyse 2 Detail 02-03'!A:A,'Analyse 2 Detail 02-03'!R:R,"Not Found",0,1) -> Mölnlycke Health Care B.V. | E10: _ Orderbevestiging 3504015911.pdf | F10: extracted | G10: 0 | U10: =AVERAGE(Table326[[#This Row],[PO nr]:[Delivery Date]]) -> #DIV/0!
C11: =_xlfn.XLOOKUP(Table326[[#This Row],[Customer]],'Top 300'!C:C,'Top 300'!A:A,"0",2,1) -> 0 | D11: =_xlfn.XLOOKUP(Table326[[#This Row],[File Name]],'Analyse 2 Detail 02-03'!A:A,'Analyse 2 Detail 02-03'!R:R,"Not Found",0,1) -> Mölnlycke Health Care B.V. | E11: _ Orderbevestiging 3505026677.pdf | F11: extracted | G11: 0 | U11: =AVERAGE(Table326[[#This Row],[PO nr]:[Delivery Date]]) -> #DIV/0!
C12: =_xlfn.XLOOKUP(Table326[[#This Row],[Customer]],'Top 300'!C:C,'Top 300'!A:A,"0",2,1) -> 0 | D12: =_xlfn.XLOOKUP(Table326[[#This Row],[File Name]],'Analyse 2 Detail 02-03'!A:A,'Analyse 2 Detail 02-03'!R:R,"Not Found",0,1) -> 0 | E12: 100142673 HL WZC Herinnering Sligro [#KM-6720322] [#RL-144746].pdf | F12: unclassified | G12: 0 | H12: N/A | I12: N/A | J12: N/A | K12: N/A | L12: N/A | M12: N/A | N12: N/A | O12: N/A | P12: N/A | Q12: N/A | R12: N/A | S12: N/A | T12: N/A | U12: =AVERAGE(Table326[[#This Row],[PO nr]:[Delivery Date]]) -> #DIV/0! | V12: Niet extracted want geen OB - Betalingsherinnering | W12: Deze proberen weren van OB mailbox
C13: =_xlfn.XLOOKUP(Table326[[#This Row],[Customer]],'Top 300'!C:C,'Top 300'!A:A,"0",2,1) -> X | D13: =_xlfn.XLOOKUP(Table326[[#This Row],[File Name]],'Analyse 2 Detail 02-03'!A:A,'Analyse 2 Detail 02-03'!R:R,"Not Found",0,1) -> Essity Belgium NV | E13: 2501209992 ESSITY Orderbevestiging.pdf | F13: extracted | G13: 0 | U13: =AVERAGE(Table326[[#This Row],[PO nr]:[Delivery Date]]) -> #DIV/0!
C14: =_xlfn.XLOOKUP(Table326[[#This Row],[Customer]],'Top 300'!C:C,'Top 300'!A:A,"0",2,1) -> X | D14: =_xlfn.XLOOKUP(Table326[[#This Row],[File Name]],'Analyse 2 Detail 02-03'!A:A,'Analyse 2 Detail 02-03'!R:R,"Not Found",0,1) -> Essity Belgium NV | E14: 2501209992 ESSITY Orderbevestiging.pdf | F14: extracted | G14: 0 | U14: =AVERAGE(Table326[[#This Row],[PO nr]:[Delivery Date]]) -> #DIV/0!
C15: =_xlfn.XLOOKUP(Table326[[#This Row],[Customer]],'Top 300'!C:C,'Top 300'!A:A,"0",2,1) -> 0 | D15: =_xlfn.XLOOKUP(Table326[[#This Row],[File Name]],'Analyse 2 Detail 02-03'!A:A,'Analyse 2 Detail 02-03'!R:R,"Not Found",0,1) -> Essity Netherlands B.V. | E15: 2505040799 ESSITY Order Ontvangstbevestiging.pdf | F15: extracted | G15: 1 | H15: 1 | I15: 1 | J15: 1 | K15: 1 | L15: 1 | M15: 1 | N15: 1 | O15: 1 | P15: 1 | Q15: 1 | R15: 1 | S15: 1 | T15: 0.5 | U15: =AVERAGE(Table326[[#This Row],[PO nr]:[Delivery Date]]) -> 0.96153846 | V15: Order ontvangst bevestiging =/= OB - Geen leverdatum | W15: Wat gaan we doen met order ontvangst bevestigingen?
C16: =_xlfn.XLOOKUP(Table326[[#This Row],[Customer]],'Top 300'!C:C,'Top 300'!A:A,"0",2,1) -> 0 | D16: =_xlfn.XLOOKUP(Table326[[#This Row],[File Name]],'Analyse 2 Detail 02-03'!A:A,'Analyse 2 Detail 02-03'!R:R,"Not Found",0,1) -> Essity Netherlands B.V. | E16: 2507017044 ESSITY Order Ontvangstbevestiging.pdf | F16: extracted | G16: 2 | H16: 1 | I16: 1 | J16: 1 | K16: 1 | L16: 1 | M16: 1 | N16: 1 | O16: 1 | P16: 1 | Q16: 1 | R16: 1 | S16: 1 | T16: 0.5 | U16: =AVERAGE(Table326[[#This Row],[PO nr]:[Delivery Date]]) -> 0.96153846 | V16: Order ontvangst bevestiging =/= OB - Geen leverdatum | W16: Wat gaan we doen met order ontvangst bevestigingen?
C17: =_xlfn.XLOOKUP(Table326[[#This Row],[Customer]],'Top 300'!C:C,'Top 300'!A:A,"0",2,1) -> X | D17: =_xlfn.XLOOKUP(Table326[[#This Row],[File Name]],'Analyse 2 Detail 02-03'!A:A,'Analyse 2 Detail 02-03'!R:R,"Not Found",0,1) -> Essity Belgium NV | E17: 2508010179 ESSITY Orderbevestiging.pdf | F17: extracted | G17: 4 | H17: 1 | I17: 1 | J17: 1 | K17: 1 | L17: 1 | M17: 1 | N17: 1 | O17: 1 | P17: 1 | Q17: 1 | R17: 1 | S17: 0.5 | T17: 0.5 | U17: =AVERAGE(Table326[[#This Row],[PO nr]:[Delivery Date]]) -> 0.92307692 | V17: Geen unit price op OB - Line 1: geen confirmed del date | W17: Wat willen we doen in geval niet confirmed? | X17: Te confirmeren indien geen delivery date veld leeg of altijd +1 dag tegenover bevestigingsdatum
C18: =_xlfn.XLOOKUP(Table326[[#This Row],[Customer]],'Top 300'!C:C,'Top 300'!A:A,"0",2,1) -> X | D18: =_xlfn.XLOOKUP(Table326[[#This Row],[File Name]],'Analyse 2 Detail 02-03'!A:A,'Analyse 2 Detail 02-03'!R:R,"Not Found",0,1) -> Essity Belgium NV | E18: 2508010179 ESSITY Orderbevestiging.pdf | F18: extracted | G18: 1 | H18: 1 | I18: 1 | J18: 1 | K18: 1 | L18: 1 | M18: 1 | N18: 1 | O18: 1 | P18: 1 | Q18: 1 | R18: 1 | S18: 1 | T18: 0.5 | U18: =AVERAGE(Table326[[#This Row],[PO nr]:[Delivery Date]]) -> 0.96153846 | V18: Zelfde OB als lijn 17 maar met prijzen - Line 1: geen confirmed del date | W18: Wat willen we doen in geval niet confirmed? | X18: Te confirmeren indien geen delivery date veld leeg of altijd +1 dag tegenover bevestigingsdatum
C19: =_xlfn.XLOOKUP(Table326[[#This Row],[Customer]],'Top 300'!C:C,'Top 300'!A:A,"0",2,1) -> 0 | D19: =_xlfn.XLOOKUP(Table326[[#This Row],[File Name]],'Analyse 2 Detail 02-03'!A:A,'Analyse 2 Detail 02-03'!R:R,"Not Found",0,1) -> Essity Netherlands B.V. Health & Medical | E19: 3505026639 ESSITY Orderbevestiging.pdf | F19: extracted | G19: 0 | U19: =AVERAGE(Table326[[#This Row],[PO nr]:[Delivery Date]]) -> #DIV/0!
C20: =_xlfn.XLOOKUP(Table326[[#This Row],[Customer]],'Top 300'!C:C,'Top 300'!A:A,"0",2,1) -> 0 | D20: =_xlfn.XLOOKUP(Table326[[#This Row],[File Name]],'Analyse 2 Detail 02-03'!A:A,'Analyse 2 Detail 02-03'!R:R,"Not Found",0,1) -> Essity Netherlands B.V. | E20: 3505026670 ESSITY Orderbevestiging.pdf | F20: extracted | G20: 0 | U20: =AVERAGE(Table326[[#This Row],[PO nr]:[Delivery Date]]) -> #DIV/0!
C21: =_xlfn.XLOOKUP(Table326[[#This Row],[Customer]],'Top 300'!C:C,'Top 300'!A:A,"0",2,1) -> 0 | D21: =_xlfn.XLOOKUP(Table326[[#This Row],[File Name]],'Analyse 2 Detail 02-03'!A:A,'Analyse 2 Detail 02-03'!R:R,"Not Found",0,1) -> Essity Netherlands B.V. | E21: 3505026678 ESSITY Orderbevestiging.pdf | F21: extracted | G21: 0 | U21: =AVERAGE(Table326[[#This Row],[PO nr]:[Delivery Date]]) -> #DIV/0!
C22: =_xlfn.XLOOKUP(Table326[[#This Row],[Customer]],'Top 300'!C:C,'Top 300'!A:A,"0",2,1) -> 0 | D22: =_xlfn.XLOOKUP(Table326[[#This Row],[File Name]],'Analyse 2 Detail 02-03'!A:A,'Analyse 2 Detail 02-03'!R:R,"Not Found",0,1) -> Essity Netherlands B.V. | E22: 6507004827 ESSITY Order Ontvangstbevestiging.pdf | F22: extracted | G22: 1 | H22: 1 | I22: 1 | J22: 1 | K22: 1 | L22: 1 | M22: 1 | N22: 1 | O22: 1 | P22: 1 | Q22: 1 | R22: 1 | S22: 1 | T22: 0.5 | U22: =AVERAGE(Table326[[#This Row],[PO nr]:[Delivery Date]]) -> 0.96153846 | V22: Order ontvangst bevestiging =/= OB - Geen leverdatum | W22: Wat gaan we doen met order ontvangst bevestigingen?
C23: =_xlfn.XLOOKUP(Table326[[#This Row],[Customer]],'Top 300'!C:C,'Top 300'!A:A,"0",2,1) -> 0 | D23: =_xlfn.XLOOKUP(Table326[[#This Row],[File Name]],'Analyse 2 Detail 02-03'!A:A,'Analyse 2 Detail 02-03'!R:R,"Not Found",0,1) -> Essity Netherlands B.V. | E23: 6507004831 ESSITY Order Ontvangstbevestiging.pdf | F23: extracted | G23: 1 | H23: 1 | I23: 1 | J23: 1 | K23: 1 | L23: 1 | M23: 1 | N23: 1 | O23: 1 | P23: 1 | Q23: 1 | R23: 1 | S23: 1 | T23: 0.5 | U23: =AVERAGE(Table326[[#This Row],[PO nr]:[Delivery Date]]) -> 0.96153846 | V23: Order ontvangst bevestiging =/= OB - Geen leverdatum | W23: Wat gaan we doen met order ontvangst bevestigingen?
C24: =_xlfn.XLOOKUP(Table326[[#This Row],[Customer]],'Top 300'!C:C,'Top 300'!A:A,"0",2,1) -> 0 | D24: =_xlfn.XLOOKUP(Table326[[#This Row],[File Name]],'Analyse 2 Detail 02-03'!A:A,'Analyse 2 Detail 02-03'!R:R,"Not Found",0,1) -> Essity Netherlands B.V. | E24: 6507004833 ESSITY Order Ontvangstbevestiging.pdf | F24: extracted | G24: 1 | H24: 1 | I24: 1 | J24: 1 | K24: 1 | L24: 1 | M24: 1 | N24: 1 | O24: 1 | P24: 1 | Q24: 1 | R24: 1 | S24: 1 | T24: 0.5 | U24: =AVERAGE(Table326[[#This Row],[PO nr]:[Delivery Date]]) -> 0.96153846 | V24: Order ontvangst bevestiging =/= OB - Geen leverdatum | W24: Wat gaan we doen met order ontvangst bevestigingen?
C25: =_xlfn.XLOOKUP(Table326[[#This Row],[Customer]],'Top 300'!C:C,'Top 300'!A:A,"0",2,1) -> X | D25: =_xlfn.XLOOKUP(Table326[[#This Row],[File Name]],'Analyse 2 Detail 02-03'!A:A,'Analyse 2 Detail 02-03'!R:R,"Not Found",0,1) -> Becton Dickinson BV | E25: BD Order Acknowledgement for your purchase order with reference 1505040027.pdf | F25: extracted | G25: 0 | U25: =AVERAGE(Table326[[#This Row],[PO nr]:[Delivery Date]]) -> #DIV/0!
C26: =_xlfn.XLOOKUP(Table326[[#This Row],[Customer]],'Top 300'!C:C,'Top 300'!A:A,"0",2,1) -> X | D26: =_xlfn.XLOOKUP(Table326[[#This Row],[File Name]],'Analyse 2 Detail 02-03'!A:A,'Analyse 2 Detail 02-03'!R:R,"Not Found",0,1) -> Becton Dickinson BV | E26: BD Order Acknowledgement for your purchase order with reference 3504015923.pdf | F26: extracted | G26: 0 | U26: =AVERAGE(Table326[[#This Row],[PO nr]:[Delivery Date]]) -> #DIV/0!
C27: =_xlfn.XLOOKUP(Table326[[#This Row],[Customer]],'Top 300'!C:C,'Top 300'!A:A,"0",2,1) -> X | D27: =_xlfn.XLOOKUP(Table326[[#This Row],[File Name]],'Analyse 2 Detail 02-03'!A:A,'Analyse 2 Detail 02-03'!R:R,"Not Found",0,1) -> Becton Dickinson BV | E27: BD Order Acknowledgement for your purchase order with reference 3507009726.pdf | F27: extracted | G27: 2 | H27: 1 | I27: 1 | J27: 1 | K27: 1 | L27: 1 | M27: 1 | N27: 1 | O27: 1 | P27: 1 | Q27: 1 | R27: 0.5 | S27: 1 | T27: 1 | U27: =AVERAGE(Table326[[#This Row],[PO nr]:[Delivery Date]]) -> 0.96153846 | V27: Geen UoM op OB | W27: Confirmeren op UoM in PO? To Check? | X27: Te confirmeren indien geen UOM maar quantity matcht - UOM van PO overnemen of to check?
C28: =_xlfn.XLOOKUP(Table326[[#This Row],[Customer]],'Top 300'!C:C,'Top 300'!A:A,"0",2,1) -> 0 | D28: =_xlfn.XLOOKUP(Table326[[#This Row],[File Name]],'Analyse 2 Detail 02-03'!A:A,'Analyse 2 Detail 02-03'!R:R,"Not Found",0,1) -> Medline Int'l Belgium BV | E28: BE356233 Order Hospital Logistics 1501037350.pdf | F28: extracted | G28: 2 | H28: 1 | I28: 1 | J28: 1 | K28: 1 | L28: 1 | M28: 1 | N28: 1 | O28: 1 | P28: 0.5 | Q28: 1 | R28: 0.5 | S28: 1 | T28: 1 | U28: =AVERAGE(Table326[[#This Row],[PO nr]:[Delivery Date]]) -> 0.92307692 | V28: Geen description & UoM op OB | W28: Wat willen we hiermee doen? | X28: Te confirmeren indien geen UOM maar quantity matcht - UOM van PO overnemen of to check? Te confirmeren indien geen description maar lev. Art. Nr matcht - Description van PO overnemen of to check?
C29: =_xlfn.XLOOKUP(Table326[[#This Row],[Customer]],'Top 300'!C:C,'Top 300'!A:A,"0",2,1) -> 0 | D29: =_xlfn.XLOOKUP(Table326[[#This Row],[File Name]],'Analyse 2 Detail 02-03'!A:A,'Analyse 2 Detail 02-03'!R:R,"Not Found",0,1) -> VYGON NEDERLAND B.V. | E29: Betreft_ Overzicht van nog te leveren Vygon producten.pdf | F29: unclassified | G29: 0 | U29: =AVERAGE(Table326[[#This Row],[PO nr]:[Delivery Date]]) -> #DIV/0!
C30: =_xlfn.XLOOKUP(Table326[[#This Row],[Customer]],'Top 300'!C:C,'Top 300'!A:A,"0",2,1) -> 0 | D30: =_xlfn.XLOOKUP(Table326[[#This Row],[File Name]],'Analyse 2 Detail 02-03'!A:A,'Analyse 2 Detail 02-03'!R:R,"Not Found",0,1) -> VYGON NEDERLAND B.V. | E30: Betreft_ Overzicht van nog te leveren Vygon producten.pdf | F30: unclassified | G30: 0 | U30: =AVERAGE(Table326[[#This Row],[PO nr]:[Delivery Date]]) -> #DIV/0!
C31: =_xlfn.XLOOKUP(Table326[[#This Row],[Customer]],'Top 300'!C:C,'Top 300'!A:A,"0",2,1) -> 0 | D31: =_xlfn.XLOOKUP(Table326[[#This Row],[File Name]],'Analyse 2 Detail 02-03'!A:A,'Analyse 2 Detail 02-03'!R:R,"Not Found",0,1) -> VYGON NEDERLAND B.V. | E31: Betreft_ Overzicht van nog te leveren Vygon producten.pdf | F31: extracted | G31: 3 | H31: 1 | I31: 1 | J31: 1 | K31: 1 | L31: 1 | M31: 0.5 | N31: 1 | O31: 1 | P31: 1 | Q31: 1 | R31: 0.5 | S31: 0.5 | T31: 1 | U31: =AVERAGE(Table326[[#This Row],[PO nr]:[Delivery Date]]) -> 0.88461538 | V31: Backorder overzicht - Geen currency, UoM of Unit Price op vermeld | W31: Wat doen we met deze bestanden? | X31: Te confirmeren indien geen unit price --> To check of overnemen van PO? Te confirmeren indien geen currency --> To check of overnemen van PO?
C32: =_xlfn.XLOOKUP(Table326[[#This Row],[Customer]],'Top 300'!C:C,'Top 300'!A:A,"0",2,1) -> 0 | D32: =_xlfn.XLOOKUP(Table326[[#This Row],[File Name]],'Analyse 2 Detail 02-03'!A:A,'Analyse 2 Detail 02-03'!R:R,"Not Found",0,1) -> King Belgium SA/NV | E32: Bevestiging bestelling S09313425-1.pdf | F32: extracted | G32: 0 | U32: =AVERAGE(Table326[[#This Row],[PO nr]:[Delivery Date]]) -> #DIV/0!
C33: =_xlfn.XLOOKUP(Table326[[#This Row],[Customer]],'Top 300'!C:C,'Top 300'!A:A,"0",2,1) -> 0 | D33: =_xlfn.XLOOKUP(Table326[[#This Row],[File Name]],'Analyse 2 Detail 02-03'!A:A,'Analyse 2 Detail 02-03'!R:R,"Not Found",0,1) -> King Belgium SA/NV | E33: Bevestiging bestelling S09313437-1.pdf | F33: extracted | G33: 0 | U33: =AVERAGE(Table326[[#This Row],[PO nr]:[Delivery Date]]) -> #DIV/0!
C34: =_xlfn.XLOOKUP(Table326[[#This Row],[Customer]],'Top 300'!C:C,'Top 300'!A:A,"0",2,1) -> 0 | D34: =_xlfn.XLOOKUP(Table326[[#This Row],[File Name]],'Analyse 2 Detail 02-03'!A:A,'Analyse 2 Detail 02-03'!R:R,"Not Found",0,1) -> King Belgium SA/NV | E34: Bevestiging bestelling S09313444-1.pdf | F34: extracted | G34: 0 | U34: =AVERAGE(Table326[[#This Row],[PO nr]:[Delivery Date]]) -> #DIV/0!
C35: =_xlfn.XLOOKUP(Table326[[#This Row],[Customer]],'Top 300'!C:C,'Top 300'!A:A,"0",2,1) -> 0 | D35: =_xlfn.XLOOKUP(Table326[[#This Row],[File Name]],'Analyse 2 Detail 02-03'!A:A,'Analyse 2 Detail 02-03'!R:R,"Not Found",0,1) -> King Belgium SA/NV | E35: Bevestiging bestelling S09313481-1.pdf | F35: extracted | G35: 0 | U35: =AVERAGE(Table326[[#This Row],[PO nr]:[Delivery Date]]) -> #DIV/0!
C36: =_xlfn.XLOOKUP(Table326[[#This Row],[Customer]],'Top 300'!C:C,'Top 300'!A:A,"0",2,1) -> 0 | D36: =_xlfn.XLOOKUP(Table326[[#This Row],[File Name]],'Analyse 2 Detail 02-03'!A:A,'Analyse 2 Detail 02-03'!R:R,"Not Found",0,1) -> King Belgium SA/NV | E36: Bevestiging bestelling S09313926-1.pdf | F36: extracted | G36: 1 | H36: 1 | I36: 1 | J36: 1 | K36: 1 | L36: 1 | M36: 1 | N36: 0 | O36: 1 | P36: 1 | Q36: 1 | R36: 1 | S36: 1 | T36: 1 | U36: =AVERAGE(Table326[[#This Row],[PO nr]:[Delivery Date]]) -> 0.92307692 | V36: KM heffing niet opgenomen in confirmation lines | X36: Te confirmeren dat we de KM-heffing negeren
C37: =_xlfn.XLOOKUP(Table326[[#This Row],[Customer]],'Top 300'!C:C,'Top 300'!A:A,"0",2,1) -> 0 | D37: =_xlfn.XLOOKUP(Table326[[#This Row],[File Name]],'Analyse 2 Detail 02-03'!A:A,'Analyse 2 Detail 02-03'!R:R,"Not Found",0,1) -> King Belgium SA/NV | E37: Bevestiging bestelling S09313928-1.pdf | F37: extracted | G37: 0 | U37: =AVERAGE(Table326[[#This Row],[PO nr]:[Delivery Date]]) -> #DIV/0!
C38: =_xlfn.XLOOKUP(Table326[[#This Row],[Customer]],'Top 300'!C:C,'Top 300'!A:A,"0",2,1) -> 0 | D38: =_xlfn.XLOOKUP(Table326[[#This Row],[File Name]],'Analyse 2 Detail 02-03'!A:A,'Analyse 2 Detail 02-03'!R:R,"Not Found",0,1) -> Duomed Belgium NV/SA | E38: Confirmation C007-S2607613-1.pdf | F38: extracted | G38: 0 | U38: =AVERAGE(Table326[[#This Row],[PO nr]:[Delivery Date]]) -> #DIV/0!
C39: =_xlfn.XLOOKUP(Table326[[#This Row],[Customer]],'Top 300'!C:C,'Top 300'!A:A,"0",2,1) -> 0 | D39: =_xlfn.XLOOKUP(Table326[[#This Row],[File Name]],'Analyse 2 Detail 02-03'!A:A,'Analyse 2 Detail 02-03'!R:R,"Not Found",0,1) -> King Belgium SA/NV | E39: Confirmation Commande S09313483-1.pdf | F39: extracted | G39: 0 | U39: =AVERAGE(Table326[[#This Row],[PO nr]:[Delivery Date]]) -> #DIV/0!
C40: =_xlfn.XLOOKUP(Table326[[#This Row],[Customer]],'Top 300'!C:C,'Top 300'!A:A,"0",2,1) -> 0 | D40: =_xlfn.XLOOKUP(Table326[[#This Row],[File Name]],'Analyse 2 Detail 02-03'!A:A,'Analyse 2 Detail 02-03'!R:R,"Not Found",0,1) -> 0 | E40: Embal.bon_100726_Sligro_5061_klant_000142470.pdf | F40: unclassified | G40: 0 | H40: N/A | I40: N/A | J40: N/A | K40: N/A | L40: N/A | M40: N/A | N40: N/A | O40: N/A | P40: N/A | Q40: N/A | R40: N/A | S40: N/A | T40: N/A | U40: =AVERAGE(Table326[[#This Row],[PO nr]:[Delivery Date]]) -> #DIV/0! | V40: Niet extracted want geen OB - Volgoed- en emballagebon | W40: Deze proberen weren van OB mailbox
C41: =_xlfn.XLOOKUP(Table326[[#This Row],[Customer]],'Top 300'!C:C,'Top 300'!A:A,"0",2,1) -> 0 | D41: =_xlfn.XLOOKUP(Table326[[#This Row],[File Name]],'Analyse 2 Detail 02-03'!A:A,'Analyse 2 Detail 02-03'!R:R,"Not Found",0,1) -> Medline International Netherlands B.V. | E41: FW_ ORDERBEVESTIGING NL327171, Deb.nr. 110890HE, Uw order_ 3507009725.pdf | F41: extracted | G41: 1 | H41: 1 | I41: 1 | J41: 1 | K41: 1 | L41: 1 | M41: 1 | N41: 1 | O41: 1 | P41: 1 | Q41: 1 | R41: 1 | S41: 1 | T41: 1 | U41: =AVERAGE(Table326[[#This Row],[PO nr]:[Delivery Date]]) -> 1 | Z41: Missing field staat 1 maar geen missing field te zien
C42: =_xlfn.XLOOKUP(Table326[[#This Row],[Customer]],'Top 300'!C:C,'Top 300'!A:A,"0",2,1) -> 0 | D42: =_xlfn.XLOOKUP(Table326[[#This Row],[File Name]],'Analyse 2 Detail 02-03'!A:A,'Analyse 2 Detail 02-03'!R:R,"Not Found",0,1) -> N.V. PAUL HARTMANN S.A. | E42: Hartmann _ Order bevestiging.pdf | F42: extracted | G42: 0 | U42: =AVERAGE(Table326[[#This Row],[PO nr]:[Delivery Date]]) -> #DIV/0!
C43: =_xlfn.XLOOKUP(Table326[[#This Row],[Customer]],'Top 300'!C:C,'Top 300'!A:A,"0",2,1) -> 0 | D43: =_xlfn.XLOOKUP(Table326[[#This Row],[File Name]],'Analyse 2 Detail 02-03'!A:A,'Analyse 2 Detail 02-03'!R:R,"Not Found",0,1) -> N.V. PAUL HARTMANN S.A. | E43: Hartmann _ Order bevestiging.pdf | F43: extracted | G43: 0 | U43: =AVERAGE(Table326[[#This Row],[PO nr]:[Delivery Date]]) -> #DIV/0!
C44: =_xlfn.XLOOKUP(Table326[[#This Row],[Customer]],'Top 300'!C:C,'Top 300'!A:A,"0",2,1) -> 0 | D44: =_xlfn.XLOOKUP(Table326[[#This Row],[File Name]],'Analyse 2 Detail 02-03'!A:A,'Analyse 2 Detail 02-03'!R:R,"Not Found",0,1) -> N.V. PAUL HARTMANN S.A. | E44: Hartmann _ Order bevestiging.pdf | F44: extracted | G44: 0 | U44: =AVERAGE(Table326[[#This Row],[PO nr]:[Delivery Date]]) -> #DIV/0!
C45: =_xlfn.XLOOKUP(Table326[[#This Row],[Customer]],'Top 300'!C:C,'Top 300'!A:A,"0",2,1) -> 0 | D45: =_xlfn.XLOOKUP(Table326[[#This Row],[File Name]],'Analyse 2 Detail 02-03'!A:A,'Analyse 2 Detail 02-03'!R:R,"Not Found",0,1) -> N.V. PAUL HARTMANN S.A. | E45: Hartmann _ Order bevestiging.pdf | F45: extracted | G45: 0 | U45: =AVERAGE(Table326[[#This Row],[PO nr]:[Delivery Date]]) -> #DIV/0!
C46: =_xlfn.XLOOKUP(Table326[[#This Row],[Customer]],'Top 300'!C:C,'Top 300'!A:A,"0",2,1) -> 0 | D46: =_xlfn.XLOOKUP(Table326[[#This Row],[File Name]],'Analyse 2 Detail 02-03'!A:A,'Analyse 2 Detail 02-03'!R:R,"Not Found",0,1) -> Paul Hartmann B.V. | E46: HARTMANN_ ORDERBEVESTIGING0021752283.pdf | F46: extracted | G46: 0 | U46: =AVERAGE(Table326[[#This Row],[PO nr]:[Delivery Date]]) -> #DIV/0!
C47: =_xlfn.XLOOKUP(Table326[[#This Row],[Customer]],'Top 300'!C:C,'Top 300'!A:A,"0",2,1) -> 0 | D47: =_xlfn.XLOOKUP(Table326[[#This Row],[File Name]],'Analyse 2 Detail 02-03'!A:A,'Analyse 2 Detail 02-03'!R:R,"Not Found",0,1) -> Paul Hartmann B.V. | E47: HARTMANN_ ORDERBEVESTIGING0021752292.pdf | F47: extracted | G47: 0 | U47: =AVERAGE(Table326[[#This Row],[PO nr]:[Delivery Date]]) -> #DIV/0!
C48: =_xlfn.XLOOKUP(Table326[[#This Row],[Customer]],'Top 300'!C:C,'Top 300'!A:A,"0",2,1) -> 0 | D48: =_xlfn.XLOOKUP(Table326[[#This Row],[File Name]],'Analyse 2 Detail 02-03'!A:A,'Analyse 2 Detail 02-03'!R:R,"Not Found",0,1) -> Paul Hartmann B.V. | E48: HARTMANN_ ORDERBEVESTIGING0021752293.pdf | F48: extracted | G48: 0 | U48: =AVERAGE(Table326[[#This Row],[PO nr]:[Delivery Date]]) -> #DIV/0!
C49: =_xlfn.XLOOKUP(Table326[[#This Row],[Customer]],'Top 300'!C:C,'Top 300'!A:A,"0",2,1) -> 0 | D49: =_xlfn.XLOOKUP(Table326[[#This Row],[File Name]],'Analyse 2 Detail 02-03'!A:A,'Analyse 2 Detail 02-03'!R:R,"Not Found",0,1) -> 0 | E49: Informatie betreffende een JAVA levering.pdf | F49: unclassified | G49: 0 | H49: N/A | I49: N/A | J49: N/A | K49: N/A | L49: N/A | M49: N/A | N49: N/A | O49: N/A | P49: N/A | Q49: N/A | R49: N/A | S49: N/A | T49: N/A | U49: =AVERAGE(Table326[[#This Row],[PO nr]:[Delivery Date]]) -> #DIV/0! | V49: Niet extracted want geen OB - Afleverbon | W49: Deze proberen weren van OB mailbox
C50: =_xlfn.XLOOKUP(Table326[[#This Row],[Customer]],'Top 300'!C:C,'Top 300'!A:A,"0",2,1) -> 0 | D50: =_xlfn.XLOOKUP(Table326[[#This Row],[File Name]],'Analyse 2 Detail 02-03'!A:A,'Analyse 2 Detail 02-03'!R:R,"Not Found",0,1) -> 0 | E50: Informatie betreffende een JAVA levering.pdf | F50: unclassified | G50: 0 | H50: N/A | I50: N/A | J50: N/A | K50: N/A | L50: N/A | M50: N/A | N50: N/A | O50: N/A | P50: N/A | Q50: N/A | R50: N/A | S50: N/A | T50: N/A | U50: =AVERAGE(Table326[[#This Row],[PO nr]:[Delivery Date]]) -> #DIV/0! | V50: Niet extracted want geen OB - Afleverbon | W50: Deze proberen weren van OB mailbox
C51: =_xlfn.XLOOKUP(Table326[[#This Row],[Customer]],'Top 300'!C:C,'Top 300'!A:A,"0",2,1) -> 0 | D51: =_xlfn.XLOOKUP(Table326[[#This Row],[File Name]],'Analyse 2 Detail 02-03'!A:A,'Analyse 2 Detail 02-03'!R:R,"Not Found",0,1) -> 0 | E51: Informatie betreffende een JAVA levering.pdf | F51: unclassified | G51: 0 | H51: N/A | I51: N/A | J51: N/A | K51: N/A | L51: N/A | M51: N/A | N51: N/A | O51: N/A | P51: N/A | Q51: N/A | R51: N/A | S51: N/A | T51: N/A | U51: =AVERAGE(Table326[[#This Row],[PO nr]:[Delivery Date]]) -> #DIV/0! | V51: Niet extracted want geen OB - Afleverbon | W51: Deze proberen weren van OB mailbox
C52: =_xlfn.XLOOKUP(Table326[[#This Row],[Customer]],'Top 300'!C:C,'Top 300'!A:A,"0",2,1) -> 0 | D52: =_xlfn.XLOOKUP(Table326[[#This Row],[File Name]],'Analyse 2 Detail 02-03'!A:A,'Analyse 2 Detail 02-03'!R:R,"Not Found",0,1) -> 0 | E52: JAVA leveringsinformatie.pdf | F52: unclassified | G52: 0 | H52: N/A | I52: N/A | J52: N/A | K52: N/A | L52: N/A | M52: N/A | N52: N/A | O52: N/A | P52: N/A | Q52: N/A | R52: N/A | S52: N/A | T52: N/A | U52: =AVERAGE(Table326[[#This Row],[PO nr]:[Delivery Date]]) -> #DIV/0! | V52: Niet extracted want geen OB - Leveringsinformatie | W52: Deze proberen weren van OB mailbox
C53: =_xlfn.XLOOKUP(Table326[[#This Row],[Customer]],'Top 300'!C:C,'Top 300'!A:A,"0",2,1) -> 0 | D53: =_xlfn.XLOOKUP(Table326[[#This Row],[File Name]],'Analyse 2 Detail 02-03'!A:A,'Analyse 2 Detail 02-03'!R:R,"Not Found",0,1) -> 0 | E53: JAVA leveringsinformatie.pdf | F53: unclassified | G53: 0 | H53: N/A | I53: N/A | J53: N/A | K53: N/A | L53: N/A | M53: N/A | N53: N/A | O53: N/A | P53: N/A | Q53: N/A | R53: N/A | S53: N/A | T53: N/A | U53: =AVERAGE(Table326[[#This Row],[PO nr]:[Delivery Date]]) -> #DIV/0! | V53: Niet extracted want geen OB - Leveringsinformatie | W53: Deze proberen weren van OB mailbox
C54: =_xlfn.XLOOKUP(Table326[[#This Row],[Customer]],'Top 300'!C:C,'Top 300'!A:A,"0",2,1) -> 0 | D54: =_xlfn.XLOOKUP(Table326[[#This Row],[File Name]],'Analyse 2 Detail 02-03'!A:A,'Analyse 2 Detail 02-03'!R:R,"Not Found",0,1) -> 0 | E54: Jouw Lyreco bestelling 1178683275 - 2505040761 is onderweg!.pdf | F54: extracted | G54: 0 | H54: 0 | I54: 0 | J54: 0 | K54: 0 | L54: 0 | M54: 0 | N54: 0 | O54: 0 | P54: 0 | Q54: 0 | R54: 0 | S54: 0 | T54: 0 | U54: =AVERAGE(Table326[[#This Row],[PO nr]:[Delivery Date]]) -> 0 | V54: Geen OB - Verzendbevestiging fout geëxtract als OB | W54: Deze proberen weren van OB mailbox
C55: =_xlfn.XLOOKUP(Table326[[#This Row],[Customer]],'Top 300'!C:C,'Top 300'!A:A,"0",2,1) -> 0 | D55: =_xlfn.XLOOKUP(Table326[[#This Row],[File Name]],'Analyse 2 Detail 02-03'!A:A,'Analyse 2 Detail 02-03'!R:R,"Not Found",0,1) -> Lyreco Belgium SA/NV | E55: Lyreco orderbevestiging 167912161-16022026-0006.pdf | F55: extracted | G55: 2 | H55: 1 | I55: 1 | J55: 1 | K55: 1 | L55: 1 | M55: 1 | N55: 1 | O55: 1 | P55: 1 | Q55: 1 | R55: 0.5 | S55: 1 | T55: 0.5 | U55: =AVERAGE(Table326[[#This Row],[PO nr]:[Delivery Date]]) -> 0.92307692 | V55: Geen UoM en delivery date op OB
C56: =_xlfn.XLOOKUP(Table326[[#This Row],[Customer]],'Top 300'!C:C,'Top 300'!A:A,"0",2,1) -> 0 | D56: =_xlfn.XLOOKUP(Table326[[#This Row],[File Name]],'Analyse 2 Detail 02-03'!A:A,'Analyse 2 Detail 02-03'!R:R,"Not Found",0,1) -> Lyreco Belgium SA/NV | E56: Lyreco orderbevestiging 167913009-16022026-0006.pdf | F56: extracted | G56: 2 | H56: 1 | I56: 1 | J56: 1 | K56: 1 | L56: 1 | M56: 1 | N56: 1 | O56: 1 | P56: 1 | Q56: 1 | R56: 0.5 | S56: 1 | T56: 0.5 | U56: =AVERAGE(Table326[[#This Row],[PO nr]:[Delivery Date]]) -> 0.92307692 | V56: Geen UoM en delivery date op OB
C57: =_xlfn.XLOOKUP(Table326[[#This Row],[Customer]],'Top 300'!C:C,'Top 300'!A:A,"0",2,1) -> 0 | D57: =_xlfn.XLOOKUP(Table326[[#This Row],[File Name]],'Analyse 2 Detail 02-03'!A:A,'Analyse 2 Detail 02-03'!R:R,"Not Found",0,1) -> Lyreco Belgium SA/NV | E57: Lyreco orderbevestiging 167924591-16022026-0006.pdf | F57: extracted | G57: 2 | H57: 1 | I57: 1 | J57: 1 | K57: 1 | L57: 1 | M57: 1 | N57: 1 | O57: 1 | P57: 1 | Q57: 1 | R57: 0.5 | S57: 1 | T57: 0.5 | U57: =AVERAGE(Table326[[#This Row],[PO nr]:[Delivery Date]]) -> 0.92307692 | V57: Geen UoM en delivery date op OB
C58: =_xlfn.XLOOKUP(Table326[[#This Row],[Customer]],'Top 300'!C:C,'Top 300'!A:A,"0",2,1) -> 0 | D58: =_xlfn.XLOOKUP(Table326[[#This Row],[File Name]],'Analyse 2 Detail 02-03'!A:A,'Analyse 2 Detail 02-03'!R:R,"Not Found",0,1) -> Mediq Nederland B.V. | E58: Mediq orderbevestiging_ 1507018696.pdf | F58: extracted | G58: 0 | U58: =AVERAGE(Table326[[#This Row],[PO nr]:[Delivery Date]]) -> #DIV/0!
C59: =_xlfn.XLOOKUP(Table326[[#This Row],[Customer]],'Top 300'!C:C,'Top 300'!A:A,"0",2,1) -> 0 | D59: =_xlfn.XLOOKUP(Table326[[#This Row],[File Name]],'Analyse 2 Detail 02-03'!A:A,'Analyse 2 Detail 02-03'!R:R,"Not Found",0,1) -> Mediq Nederland B.V. | E59: Mediq orderbevestiging_ 3507009731.pdf | F59: extracted | G59: 0 | U59: =AVERAGE(Table326[[#This Row],[PO nr]:[Delivery Date]]) -> #DIV/0!
C60: =_xlfn.XLOOKUP(Table326[[#This Row],[Customer]],'Top 300'!C:C,'Top 300'!A:A,"0",2,1) -> 0 | D60: =_xlfn.XLOOKUP(Table326[[#This Row],[File Name]],'Analyse 2 Detail 02-03'!A:A,'Analyse 2 Detail 02-03'!R:R,"Not Found",0,1) -> 0 | E60: Medtronic - backorder report - Hospital Logistics.pdf | F60: unclassified | G60: 0 | U60: =AVERAGE(Table326[[#This Row],[PO nr]:[Delivery Date]]) -> #DIV/0!
C61: =_xlfn.XLOOKUP(Table326[[#This Row],[Customer]],'Top 300'!C:C,'Top 300'!A:A,"0",2,1) -> 0 | D61: =_xlfn.XLOOKUP(Table326[[#This Row],[File Name]],'Analyse 2 Detail 02-03'!A:A,'Analyse 2 Detail 02-03'!R:R,"Not Found",0,1) -> Medtronic Trading NL BV | E61: Order bevestiging 26-02818.pdf | F61: extracted | G61: 2 | H61: N/A | I61: N/A | J61: N/A | K61: N/A | L61: N/A | M61: N/A | N61: N/A | O61: N/A | P61: N/A | Q61: N/A | R61: N/A | S61: N/A | T61: N/A | U61: =AVERAGE(Table326[[#This Row],[PO nr]:[Delivery Date]]) -> #DIV/0! | V61: OB niet voor HL maar klant | W61: Wat gaan we doen met deze OB's?
C62: =_xlfn.XLOOKUP(Table326[[#This Row],[Customer]],'Top 300'!C:C,'Top 300'!A:A,"0",2,1) -> 0 | D62: =_xlfn.XLOOKUP(Table326[[#This Row],[File Name]],'Analyse 2 Detail 02-03'!A:A,'Analyse 2 Detail 02-03'!R:R,"Not Found",0,1) -> Medtronic Trading NL BV | E62: Order bevestiging 26-02818.pdf | F62: extracted | G62: 2 | H62: N/A | I62: N/A | J62: N/A | K62: N/A | L62: N/A | M62: N/A | N62: N/A | O62: N/A | P62: N/A | Q62: N/A | R62: N/A | S62: N/A | T62: N/A | U62: =AVERAGE(Table326[[#This Row],[PO nr]:[Delivery Date]]) -> #DIV/0! | V62: OB niet voor HL maar klant | W62: Wat gaan we doen met deze OB's?
C63: =_xlfn.XLOOKUP(Table326[[#This Row],[Customer]],'Top 300'!C:C,'Top 300'!A:A,"0",2,1) -> 0 | D63: =_xlfn.XLOOKUP(Table326[[#This Row],[File Name]],'Analyse 2 Detail 02-03'!A:A,'Analyse 2 Detail 02-03'!R:R,"Not Found",0,1) -> Medtronic Trading NL BV | E63: Order bevestiging 26-02855.pdf | F63: extracted | G63: 7 | H63: N/A | I63: N/A | J63: N/A | K63: N/A | L63: N/A | M63: N/A | N63: N/A | O63: N/A | P63: N/A | Q63: N/A | R63: N/A | S63: N/A | T63: N/A | U63: =AVERAGE(Table326[[#This Row],[PO nr]:[Delivery Date]]) -> #DIV/0! | V63: OB niet voor HL maar klant | W63: Wat gaan we doen met deze OB's?
C64: =_xlfn.XLOOKUP(Table326[[#This Row],[Customer]],'Top 300'!C:C,'Top 300'!A:A,"0",2,1) -> 0 | D64: =_xlfn.XLOOKUP(Table326[[#This Row],[File Name]],'Analyse 2 Detail 02-03'!A:A,'Analyse 2 Detail 02-03'!R:R,"Not Found",0,1) -> Medtronic Trading NL BV | E64: Order bevestiging 26-02889.pdf | F64: extracted | G64: 1 | H64: N/A | I64: N/A | J64: N/A | K64: N/A | L64: N/A | M64: N/A | N64: N/A | O64: N/A | P64: N/A | Q64: N/A | R64: N/A | S64: N/A | T64: N/A | U64: =AVERAGE(Table326[[#This Row],[PO nr]:[Delivery Date]]) -> #DIV/0! | V64: OB niet voor HL maar klant | W64: Wat gaan we doen met deze OB's?
C65: =_xlfn.XLOOKUP(Table326[[#This Row],[Customer]],'Top 300'!C:C,'Top 300'!A:A,"0",2,1) -> 0 | D65: =_xlfn.XLOOKUP(Table326[[#This Row],[File Name]],'Analyse 2 Detail 02-03'!A:A,'Analyse 2 Detail 02-03'!R:R,"Not Found",0,1) -> Fresenius Kabi nv/sa | E65: ORDERBEVESTIGING 2364064918.pdf | F65: extracted | G65: 0 | U65: =AVERAGE(Table326[[#This Row],[PO nr]:[Delivery Date]]) -> #DIV/0!
C66: =_xlfn.XLOOKUP(Table326[[#This Row],[Customer]],'Top 300'!C:C,'Top 300'!A:A,"0",2,1) -> 0 | D66: =_xlfn.XLOOKUP(Table326[[#This Row],[File Name]],'Analyse 2 Detail 02-03'!A:A,'Analyse 2 Detail 02-03'!R:R,"Not Found",0,1) -> Fresenius Kabi Nederland B.V. | E66: ORDERBEVESTIGING 2364067490.pdf | F66: extracted | G66: 0 | U66: =AVERAGE(Table326[[#This Row],[PO nr]:[Delivery Date]]) -> #DIV/0!
C67: =_xlfn.XLOOKUP(Table326[[#This Row],[Customer]],'Top 300'!C:C,'Top 300'!A:A,"0",2,1) -> 0 | D67: =_xlfn.XLOOKUP(Table326[[#This Row],[File Name]],'Analyse 2 Detail 02-03'!A:A,'Analyse 2 Detail 02-03'!R:R,"Not Found",0,1) -> Fresenius Kabi Nederland B.V. | E67: ORDERBEVESTIGING 2364067490.pdf | F67: extracted | G67: 0 | U67: =AVERAGE(Table326[[#This Row],[PO nr]:[Delivery Date]]) -> #DIV/0!
C68: =_xlfn.XLOOKUP(Table326[[#This Row],[Customer]],'Top 300'!C:C,'Top 300'!A:A,"0",2,1) -> 0 | D68: =_xlfn.XLOOKUP(Table326[[#This Row],[File Name]],'Analyse 2 Detail 02-03'!A:A,'Analyse 2 Detail 02-03'!R:R,"Not Found",0,1) -> Duomed Belgium NV/SA | E68: Orderbevestiging C007-S2607585-1.pdf | F68: extracted | G68: 0 | U68: =AVERAGE(Table326[[#This Row],[PO nr]:[Delivery Date]]) -> #DIV/0!
C69: =_xlfn.XLOOKUP(Table326[[#This Row],[Customer]],'Top 300'!C:C,'Top 300'!A:A,"0",2,1) -> 0 | D69: =_xlfn.XLOOKUP(Table326[[#This Row],[File Name]],'Analyse 2 Detail 02-03'!A:A,'Analyse 2 Detail 02-03'!R:R,"Not Found",0,1) -> Duomed Belgium NV/SA | E69: Orderbevestiging C007-S2607598-1.pdf | F69: extracted | G69: 0 | U69: =AVERAGE(Table326[[#This Row],[PO nr]:[Delivery Date]]) -> #DIV/0!
C70: =_xlfn.XLOOKUP(Table326[[#This Row],[Customer]],'Top 300'!C:C,'Top 300'!A:A,"0",2,1) -> 0 | D70: =_xlfn.XLOOKUP(Table326[[#This Row],[File Name]],'Analyse 2 Detail 02-03'!A:A,'Analyse 2 Detail 02-03'!R:R,"Not Found",0,1) -> Duomed Belgium NV/SA | E70: Orderbevestiging C007-S2607619-1.pdf | F70: extracted | G70: 0 | U70: =AVERAGE(Table326[[#This Row],[PO nr]:[Delivery Date]]) -> #DIV/0!
C71: =_xlfn.XLOOKUP(Table326[[#This Row],[Customer]],'Top 300'!C:C,'Top 300'!A:A,"0",2,1) -> 0 | D71: =_xlfn.XLOOKUP(Table326[[#This Row],[File Name]],'Analyse 2 Detail 02-03'!A:A,'Analyse 2 Detail 02-03'!R:R,"Not Found",0,1) -> Duomed Belgium NV/SA | E71: Orderbevestiging C007-S2607622-1.pdf | F71: extracted | G71: 0 | U71: =AVERAGE(Table326[[#This Row],[PO nr]:[Delivery Date]]) -> #DIV/0!
C72: =_xlfn.XLOOKUP(Table326[[#This Row],[Customer]],'Top 300'!C:C,'Top 300'!A:A,"0",2,1) -> 0 | D72: =_xlfn.XLOOKUP(Table326[[#This Row],[File Name]],'Analyse 2 Detail 02-03'!A:A,'Analyse 2 Detail 02-03'!R:R,"Not Found",0,1) -> Duomed Belgium NV/SA | E72: Orderbevestiging C007-S2607623-1.pdf | F72: extracted | G72: 0 | U72: =AVERAGE(Table326[[#This Row],[PO nr]:[Delivery Date]]) -> #DIV/0!
C73: =_xlfn.XLOOKUP(Table326[[#This Row],[Customer]],'Top 300'!C:C,'Top 300'!A:A,"0",2,1) -> 0 | D73: =_xlfn.XLOOKUP(Table326[[#This Row],[File Name]],'Analyse 2 Detail 02-03'!A:A,'Analyse 2 Detail 02-03'!R:R,"Not Found",0,1) -> Duomed Belgium NV/SA | E73: Orderbevestiging C007-S2607720-1.pdf | F73: extracted | G73: 0 | U73: =AVERAGE(Table326[[#This Row],[PO nr]:[Delivery Date]]) -> #DIV/0!
C74: =_xlfn.XLOOKUP(Table326[[#This Row],[Customer]],'Top 300'!C:C,'Top 300'!A:A,"0",2,1) -> 0 | D74: =_xlfn.XLOOKUP(Table326[[#This Row],[File Name]],'Analyse 2 Detail 02-03'!A:A,'Analyse 2 Detail 02-03'!R:R,"Not Found",0,1) -> 0 | E74: Orderbevestiging C007-S2607726-1.pdf | F74: extracted | G74: 0 | U74: =AVERAGE(Table326[[#This Row],[PO nr]:[Delivery Date]]) -> #DIV/0!
C75: =_xlfn.XLOOKUP(Table326[[#This Row],[Customer]],'Top 300'!C:C,'Top 300'!A:A,"0",2,1) -> 0 | D75: =_xlfn.XLOOKUP(Table326[[#This Row],[File Name]],'Analyse 2 Detail 02-03'!A:A,'Analyse 2 Detail 02-03'!R:R,"Not Found",0,1) -> Medica Europe B.V. | E75: Orderbevestiging_Orderacknowledgement_ 3505026688.pdf | F75: extracted | G75: 0 | U75: =AVERAGE(Table326[[#This Row],[PO nr]:[Delivery Date]]) -> #DIV/0!
C76: =_xlfn.XLOOKUP(Table326[[#This Row],[Customer]],'Top 300'!C:C,'Top 300'!A:A,"0",2,1) -> 0 | D76: =_xlfn.XLOOKUP(Table326[[#This Row],[File Name]],'Analyse 2 Detail 02-03'!A:A,'Analyse 2 Detail 02-03'!R:R,"Not Found",0,1) -> Medica Europe B.V. | E76: Orderbevestiging_Orderacknowledgement_ 3505026688.pdf | F76: extracted | G76: 0 | U76: =AVERAGE(Table326[[#This Row],[PO nr]:[Delivery Date]]) -> #DIV/0!
C77: =_xlfn.XLOOKUP(Table326[[#This Row],[Customer]],'Top 300'!C:C,'Top 300'!A:A,"0",2,1) -> 0 | D77: =_xlfn.XLOOKUP(Table326[[#This Row],[File Name]],'Analyse 2 Detail 02-03'!A:A,'Analyse 2 Detail 02-03'!R:R,"Not Found",0,1) -> Fresenius Medical Care Nederland BV | E77: Re_ [EXTERNAL EMAIL] Order Hospital Logistics 1507018691.pdf | F77: extracted | G77: 5 | H77: 1 | I77: 1 | J77: 1 | K77: 1 | L77: 1 | M77: 1 | N77: 1 | O77: 1 | P77: 1 | Q77: 1 | R77: 1 | S77: 0.5 | T77: 0.5 | U77: =AVERAGE(Table326[[#This Row],[PO nr]:[Delivery Date]]) -> 0.92307692 | V77: Voor artikel 3 is geen prijs meegegeven - Aantal lijnen zonder leverdatum | W77: Wat indien geen prijs?
C78: =_xlfn.XLOOKUP(Table326[[#This Row],[Customer]],'Top 300'!C:C,'Top 300'!A:A,"0",2,1) -> 0 | D78: =_xlfn.XLOOKUP(Table326[[#This Row],[File Name]],'Analyse 2 Detail 02-03'!A:A,'Analyse 2 Detail 02-03'!R:R,"Not Found",0,1) -> 0 | E78: Re_ [EXTERNAL EMAIL] Order Hospital Logistics 1508015191.pdf | F78: extracted | G78: 0 | U78: =AVERAGE(Table326[[#This Row],[PO nr]:[Delivery Date]]) -> #DIV/0!
C79: =_xlfn.XLOOKUP(Table326[[#This Row],[Customer]],'Top 300'!C:C,'Top 300'!A:A,"0",2,1) -> 0 | D79: =_xlfn.XLOOKUP(Table326[[#This Row],[File Name]],'Analyse 2 Detail 02-03'!A:A,'Analyse 2 Detail 02-03'!R:R,"Not Found",0,1) -> Fresenius Medical Care Nederland BV | E79: Re_ [EXTERNAL EMAIL] Order Hospital Logistics 3504015924.pdf | F79: extracted | G79: 3 | H79: 1 | I79: 1 | J79: 1 | K79: 1 | L79: 1 | M79: 1 | N79: 1 | O79: 1 | P79: 1 | Q79: 1 | R79: 1 | S79: 1 | T79: 0.5 | U79: =AVERAGE(Table326[[#This Row],[PO nr]:[Delivery Date]]) -> 0.96153846 | V79: Geen leverdatum meegedeeld
C80: =_xlfn.XLOOKUP(Table326[[#This Row],[Customer]],'Top 300'!C:C,'Top 300'!A:A,"0",2,1) -> 0 | D80: =_xlfn.XLOOKUP(Table326[[#This Row],[File Name]],'Analyse 2 Detail 02-03'!A:A,'Analyse 2 Detail 02-03'!R:R,"Not Found",0,1) -> Fresenius Medical Care Nederland BV | E80: Re_ [EXTERNAL EMAIL] Order Hospital Logistics 3505026679.pdf | F80: extracted | G80: 1 | H80: 1 | I80: 1 | J80: 1 | K80: 1 | L80: 1 | M80: 1 | N80: 1 | O80: 1 | P80: 1 | Q80: 1 | R80: 1 | S80: 0.5 | T80: 0.5 | U80: =AVERAGE(Table326[[#This Row],[PO nr]:[Delivery Date]]) -> 0.92307692 | V80: Voor aantal artikels is geen prijs meegegeven - Aantal lijnen zonder leverdatum | W80: Wat indien geen prijs?
C81: =_xlfn.XLOOKUP(Table326[[#This Row],[Customer]],'Top 300'!C:C,'Top 300'!A:A,"0",2,1) -> 0 | D81: =_xlfn.XLOOKUP(Table326[[#This Row],[File Name]],'Analyse 2 Detail 02-03'!A:A,'Analyse 2 Detail 02-03'!R:R,"Not Found",0,1) -> 0 | E81: RE_ FW_ Opvolging openstaande orders.pdf | F81: unclassified | G81: 0 | U81: =AVERAGE(Table326[[#This Row],[PO nr]:[Delivery Date]]) -> #DIV/0!
C82: =_xlfn.XLOOKUP(Table326[[#This Row],[Customer]],'Top 300'!C:C,'Top 300'!A:A,"0",2,1) -> 0 | D82: =_xlfn.XLOOKUP(Table326[[#This Row],[File Name]],'Analyse 2 Detail 02-03'!A:A,'Analyse 2 Detail 02-03'!R:R,"Not Found",0,1) -> 0 | E82: RE_ Opvolging openstaande orders.pdf | F82: unclassified | G82: 0 | U82: =AVERAGE(Table326[[#This Row],[PO nr]:[Delivery Date]]) -> #DIV/0!
C83: =_xlfn.XLOOKUP(Table326[[#This Row],[Customer]],'Top 300'!C:C,'Top 300'!A:A,"0",2,1) -> 0 | D83: =_xlfn.XLOOKUP(Table326[[#This Row],[File Name]],'Analyse 2 Detail 02-03'!A:A,'Analyse 2 Detail 02-03'!R:R,"Not Found",0,1) -> 0 | E83: RE_ order 1501037263.pdf | F83: unclassified | G83: 0 | U83: =AVERAGE(Table326[[#This Row],[PO nr]:[Delivery Date]]) -> #DIV/0!
C84: =_xlfn.XLOOKUP(Table326[[#This Row],[Customer]],'Top 300'!C:C,'Top 300'!A:A,"0",2,1) -> 0 | D84: =_xlfn.XLOOKUP(Table326[[#This Row],[File Name]],'Analyse 2 Detail 02-03'!A:A,'Analyse 2 Detail 02-03'!R:R,"Not Found",0,1) -> 0 | E84: RE_ RE_ Teleflex Orderbevestiging 1504025864 and 13995843.pdf | F84: unclassified | G84: 0 | U84: =AVERAGE(Table326[[#This Row],[PO nr]:[Delivery Date]]) -> #DIV/0!
C85: =_xlfn.XLOOKUP(Table326[[#This Row],[Customer]],'Top 300'!C:C,'Top 300'!A:A,"0",2,1) -> 0 | D85: =_xlfn.XLOOKUP(Table326[[#This Row],[File Name]],'Analyse 2 Detail 02-03'!A:A,'Analyse 2 Detail 02-03'!R:R,"Not Found",0,1) -> 0 | E85: RE_ Verwachte leverdatum.pdf | F85: unclassified | G85: 0 | U85: =AVERAGE(Table326[[#This Row],[PO nr]:[Delivery Date]]) -> #DIV/0!
C86: =_xlfn.XLOOKUP(Table326[[#This Row],[Customer]],'Top 300'!C:C,'Top 300'!A:A,"0",2,1) -> 0 | D86: =_xlfn.XLOOKUP(Table326[[#This Row],[File Name]],'Analyse 2 Detail 02-03'!A:A,'Analyse 2 Detail 02-03'!R:R,"Not Found",0,1) -> 0 | E86: RE_ Verwachte LT.pdf | F86: unclassified | G86: 0 | U86: =AVERAGE(Table326[[#This Row],[PO nr]:[Delivery Date]]) -> #DIV/0!
C87: =_xlfn.XLOOKUP(Table326[[#This Row],[Customer]],'Top 300'!C:C,'Top 300'!A:A,"0",2,1) -> 0 | D87: =_xlfn.XLOOKUP(Table326[[#This Row],[File Name]],'Analyse 2 Detail 02-03'!A:A,'Analyse 2 Detail 02-03'!R:R,"Not Found",0,1) -> 0 | E87: RE_ Verwachte LT.pdf | F87: unclassified | G87: 0 | U87: =AVERAGE(Table326[[#This Row],[PO nr]:[Delivery Date]]) -> #DIV/0!
C88: =_xlfn.XLOOKUP(Table326[[#This Row],[Customer]],'Top 300'!C:C,'Top 300'!A:A,"0",2,1) -> 0 | D88: =_xlfn.XLOOKUP(Table326[[#This Row],[File Name]],'Analyse 2 Detail 02-03'!A:A,'Analyse 2 Detail 02-03'!R:R,"Not Found",0,1) -> 0 | E88: Teleflex Verzendnotificatie 8015531328.pdf | F88: unclassified | G88: 0 | U88: =AVERAGE(Table326[[#This Row],[PO nr]:[Delivery Date]]) -> #DIV/0!
C89: =_xlfn.XLOOKUP(Table326[[#This Row],[Customer]],'Top 300'!C:C,'Top 300'!A:A,"0",2,1) -> 0 | D89: =_xlfn.XLOOKUP(Table326[[#This Row],[File Name]],'Analyse 2 Detail 02-03'!A:A,'Analyse 2 Detail 02-03'!R:R,"Not Found",0,1) -> 0 | E89: Teleflex Verzendnotificatie 8015532636.pdf | F89: unclassified | G89: 0 | U89: =AVERAGE(Table326[[#This Row],[PO nr]:[Delivery Date]]) -> #DIV/0!
C90: =_xlfn.XLOOKUP(Table326[[#This Row],[Customer]],'Top 300'!C:C,'Top 300'!A:A,"0",2,1) -> X | D90: =_xlfn.XLOOKUP(Table326[[#This Row],[File Name]],'Analyse 2 Detail 02-03'!A:A,'Analyse 2 Detail 02-03'!R:R,"Not Found",0,1) -> QRS Healthcare BV | E90: Uw orderbevestiging 60392040.pdf | F90: extracted | G90: 0 | U90: =AVERAGE(Table326[[#This Row],[PO nr]:[Delivery Date]]) -> #DIV/0!
C91: =_xlfn.XLOOKUP(Table326[[#This Row],[Customer]],'Top 300'!C:C,'Top 300'!A:A,"0",2,1) -> 0 | D91: =_xlfn.XLOOKUP(Table326[[#This Row],[File Name]],'Analyse 2 Detail 02-03'!A:A,'Analyse 2 Detail 02-03'!R:R,"Not Found",0,1) -> Brocacef BV | E91: Uw orderinformatie (uw referentie_ 1504026606, Brocacef Ordernr_ TPV72539).pdf | F91: extracted | G91: 11 | H91: 1 | I91: 1 | J91: 1 | K91: 1 | L91: 1 | M91: 0.5 | N91: 1 | O91: 1 | P91: 1 | Q91: 1 | R91: 1 | S91: 0.5 | T91: 0.5 | U91: =AVERAGE(Table326[[#This Row],[PO nr]:[Delivery Date]]) -> 0.88461538 | V91: OB met backorderoverzicht wordt per PO gesplitst op de lijnen - Geen currency, geen Unit price en niet overal planned delivery date
C92: =_xlfn.XLOOKUP(Table326[[#This Row],[Customer]],'Top 300'!C:C,'Top 300'!A:A,"0",2,1) -> 0 | D92: =_xlfn.XLOOKUP(Table326[[#This Row],[File Name]],'Analyse 2 Detail 02-03'!A:A,'Analyse 2 Detail 02-03'!R:R,"Not Found",0,1) -> Brocacef | E92: Uw orderinformatie (uw referentie_ 2505040801, Brocacef Ordernr_ TPV72495).pdf | F92: extracted | G92: 2 | H92: 1 | I92: 1 | J92: 1 | K92: 1 | L92: 1 | M92: 0.5 | N92: 1 | O92: 1 | P92: 1 | Q92: 1 | R92: 1 | S92: 0.5 | T92: 1 | U92: =AVERAGE(Table326[[#This Row],[PO nr]:[Delivery Date]]) -> 0.92307692 | V92: Geen currency en geen Unit price
C93: =_xlfn.XLOOKUP(Table326[[#This Row],[Customer]],'Top 300'!C:C,'Top 300'!A:A,"0",2,1) -> 0 | D93: =_xlfn.XLOOKUP(Table326[[#This Row],[File Name]],'Analyse 2 Detail 02-03'!A:A,'Analyse 2 Detail 02-03'!R:R,"Not Found",0,1) -> Van Hoeckel | E93: Van Hoeckel leveringsinformatie.pdf | F93: extracted | G93: 2 | H93: N/A | I93: N/A | J93: N/A | K93: N/A | L93: N/A | M93: N/A | N93: N/A | O93: N/A | P93: N/A | Q93: N/A | R93: N/A | S93: N/A | T93: N/A | U93: =AVERAGE(Table326[[#This Row],[PO nr]:[Delivery Date]]) -> #DIV/0! | V93: Leveringsinformatie =/= OB | W93: Wat gaan we hiermee doen?
C94: =_xlfn.XLOOKUP(Table326[[#This Row],[Customer]],'Top 300'!C:C,'Top 300'!A:A,"0",2,1) -> 0 | D94: =_xlfn.XLOOKUP(Table326[[#This Row],[File Name]],'Analyse 2 Detail 02-03'!A:A,'Analyse 2 Detail 02-03'!R:R,"Not Found",0,1) -> Van Hoeckel | E94: Van Hoeckel order ontvangstbevestiging.pdf | F94: extracted | G94: 3 | H94: 1 | I94: 0.5 | J94: 1 | K94: 1 | L94: 1 | M94: 0.5 | N94: 1 | O94: 1 | P94: 1 | Q94: 1 | R94: 1 | S94: 0.5 | T94: 1 | U94: =AVERAGE(Table326[[#This Row],[PO nr]:[Delivery Date]]) -> 0.88461538 | V94: Order ontvangst bevestiging =/= OB | W94: Wat gaan we hiermee doen?
C95: =_xlfn.XLOOKUP(Table326[[#This Row],[Customer]],'Top 300'!C:C,'Top 300'!A:A,"0",2,1) -> 0 | D95: =_xlfn.XLOOKUP(Table326[[#This Row],[File Name]],'Analyse 2 Detail 02-03'!A:A,'Analyse 2 Detail 02-03'!R:R,"Not Found",0,1) -> Van Hoeckel | E95: Van Hoeckel orderinformatie.pdf | F95: extracted | G95: 4 | H95: 1 | I95: 0.5 | J95: 1 | K95: 1 | L95: 1 | M95: 0.5 | N95: 1 | O95: 1 | P95: 1 | Q95: 1 | R95: 0.5 | S95: 0.5 | T95: 1 | U95: =AVERAGE(Table326[[#This Row],[PO nr]:[Delivery Date]]) -> 0.84615385 | V95: Orderinformatie =/= OB | W95: Wat gaan we hiermee doen?
C96: =_xlfn.XLOOKUP(Table326[[#This Row],[Customer]],'Top 300'!C:C,'Top 300'!A:A,"0",2,1) -> 0 | D96: =_xlfn.XLOOKUP(Table326[[#This Row],[File Name]],'Analyse 2 Detail 02-03'!A:A,'Analyse 2 Detail 02-03'!R:R,"Not Found",0,1) -> G3 Medical B.V. | E96: Verkooporder SO00454616 _ 3505026682.pdf | F96: extracted | G96: 0 | U96: =AVERAGE(Table326[[#This Row],[PO nr]:[Delivery Date]]) -> #DIV/0!
C97: =_xlfn.XLOOKUP(Table326[[#This Row],[Customer]],'Top 300'!C:C,'Top 300'!A:A,"0",2,1) -> 0 | D97: =_xlfn.XLOOKUP(Table326[[#This Row],[File Name]],'Analyse 2 Detail 02-03'!A:A,'Analyse 2 Detail 02-03'!R:R,"Not Found",0,1) -> G3 Medical B.V. | E97: Verkooporder SO00454632 _ 3505026682.pdf | F97: extracted | G97: 0 | U97: =AVERAGE(Table326[[#This Row],[PO nr]:[Delivery Date]]) -> #DIV/0!
C98: =_xlfn.XLOOKUP(Table326[[#This Row],[Customer]],'Top 300'!C:C,'Top 300'!A:A,"0",2,1) -> 0 | D98: =_xlfn.XLOOKUP(Table326[[#This Row],[File Name]],'Analyse 2 Detail 02-03'!A:A,'Analyse 2 Detail 02-03'!R:R,"Not Found",0,1) -> 0 | E98: Verkooporder SO00454638 _ 3505026682.pdf | F98: unclassified | G98: 0 | U98: =AVERAGE(Table326[[#This Row],[PO nr]:[Delivery Date]]) -> #DIV/0!
C99: =_xlfn.XLOOKUP(Table326[[#This Row],[Customer]],'Top 300'!C:C,'Top 300'!A:A,"0",2,1) -> 0 | D99: =_xlfn.XLOOKUP(Table326[[#This Row],[File Name]],'Analyse 2 Detail 02-03'!A:A,'Analyse 2 Detail 02-03'!R:R,"Not Found",0,1) -> G3 Medical B.V. | E99: Verkooporder SO00454639 _ 3505026682.pdf | F99: extracted | G99: 0 | U99: =AVERAGE(Table326[[#This Row],[PO nr]:[Delivery Date]]) -> #DIV/0!
C100: =_xlfn.XLOOKUP(Table326[[#This Row],[Customer]],'Top 300'!C:C,'Top 300'!A:A,"0",2,1) -> 0 | D100: =_xlfn.XLOOKUP(Table326[[#This Row],[File Name]],'Analyse 2 Detail 02-03'!A:A,'Analyse 2 Detail 02-03'!R:R,"Not Found",0,1) -> G3 Medical B.V. | E100: Verkooporder SO00454641 _ 3505026682.pdf | F100: extracted | G100: 0 | U100: =AVERAGE(Table326[[#This Row],[PO nr]:[Delivery Date]]) -> #DIV/0!
...

Sheet SAPUI5 Export
A1: File Name | B1: Document Type | C1: Type Confidence | D1: Status | E1: Uploaded (UTC) | F1: File Size | G1: File Type | H1: Missing Fields | I1: Low Confidence Fields
A2: G3 Medical - per klant (Gelre) - 3504015927.pdf | C2: 88 | D2: extracted | E2: 46071.665 | F2: 111303 | G2: application/pdf | H2: 0 | I2: 0
A3: Essity BE - eerst ontvangstbevestiging - 2508010179.pdf | C3: 85 | D3: extracted | E3: 46071.665 | F3: 140250 | G3: application/pdf | H3: 6 | I3: 0
A4: Lyreco NL - nooit LT vermeld.pdf | C4: 85 | D4: extracted | E4: 46071.665 | F4: 16242 | G4: application/pdf | H4: 14 | I4: 0
A5: Medtronic NL - OB niet voor HL - rechtstreeks voor klant.PDF | C5: 92 | D5: extracted | E5: 46071.665 | F5: 22869 | G5: application/pdf | H5: 1 | I5: 0
A6: Essity BE - OB met prijzen - 2508010179.pdf | C6: 85 | D6: extracted | E6: 46071.665 | F6: 142035 | G6: application/pdf | H6: 1 | I6: 0
A7: Brocacef - per klant (Isala) - info update artikel besteld op andere PO - 3504015919.PDF | C7: 92 | D7: extracted | E7: 46071.665 | F7: 80430 | G7: application/pdf | H7: 30 | I7: 0
A8: Brocacef - per klant (Gelre) - info update artikel besteld op andere PO_3504015919.PDF | C8: 88 | D8: extracted | E8: 46071.665 | F8: 78681 | G8: application/pdf | H8: 12 | I8: 0
A9: Essity BE - OB zonder prijzen - 2508010179.pdf | C9: 90 | D9: extracted | E9: 46071.665 | F9: 140505 | G9: application/pdf | H9: 4 | I9: 0
A10: Cardinal Health BE - nooit LT vermeld.PDF | C10: 85 | D10: extracted | E10: 46071.665 | F10: 21165 | G10: application/pdf | H10: 0 | I10: 0
A11: G3 Medical - per klant (Isala) met afwijkende LT - 3504015927.pdf | C11: 85 | D11: extracted | E11: 46071.665 | F11: 112647 | G11: application/pdf | H11: 0 | I11: 0
A12: Essity NL - art lev niet exact - 2507016986.pdf | C12: 88 | D12: extracted | E12: 46071.665 | F12: 141015 | G12: application/pdf | H12: 0 | I12: 0
A13: B. Braun NL - bruto naar netto prijs.pdf | C13: 90 | D13: extracted | E13: 46071.665 | F13: 68516 | G13: application/pdf | H13: 0 | I13: 0
... A22: QRS - op klant - leverweek Isala - 3504015936.pdf | C22: 85 | D22: extracted | E22: 46071.647 | F22: 314184 | G22: application/pdf | H22: 1 | I22: 0

Sheet Analyse 1 Documents 27-02
A1: File Name | B1: Document Type | C1: Type Confidence | D1: Status | E1: Uploaded (UTC) | F1: File Size | G1: File Type | H1: Missing Fields | I1: Low Confidence Fields
A2: _ Orderbevestiging 1501037327.pdf | C2: 88 | D2: extracted | E2: 46080.531 | F2: 35061 | G2: application/pdf | H2: 0 | I2: 13
A3: _ Orderbevestiging 1504026582.pdf | C3: 82 | D3: extracted | E3: 46080.531 | F3: 34837 | G3: application/pdf | H3: 0 | I3: 0
A4: _ Orderbevestiging 1505040022.pdf | C4: 90 | D4: extracted | E4: 46080.531 | F4: 35265 | G4: application/pdf | H4: 0 | I4: 0
A5: _ Orderbevestiging 3504015911.pdf | C5: 85 | D5: extracted | E5: 46080.531 | F5: 58986 | G5: application/pdf | H5: 0 | I5: 255
A6: _ Orderbevestiging 3505026677.pdf | C6: 92 | D6: extracted | E6: 46080.531 | F6: 35794 | G6: application/pdf | H6: 0 | I6: 0
A7: 100142673 HL WZC Herinnering Sligro [#KM-6720322] [#RL-144746].pdf | C7: 28 | D7: unclassified | E7: 46080.531 | F7: 105937 | G7: application/pdf | H7: 0 | I7: 0
A8: 2501209992 ESSITY Orderbevestiging.pdf | C8: 92 | D8: extracted | E8: 46080.531 | F8: 138975 | G8: application/pdf | H8: 0 | I8: 12
A9: 2501209992 ESSITY Orderbevestiging.pdf | C9: 92 | D9: extracted | E9: 46080.531 | F9: 139995 | G9: application/pdf | H9: 0 | I9: 0
A10: 2505040799 ESSITY Order Ontvangstbevestiging.pdf | C10: 88 | D10: extracted | E10: 46080.531 | F10: 139995 | G10: application/pdf | H10: 1 | I10: 0
A11: 2507017044 ESSITY Order Ontvangstbevestiging.pdf | C11: 88 | D11: extracted | E11: 46080.531 | F11: 140760 | G11: application/pdf | H11: 2 | I11: 0
A12: 2508010179 ESSITY Orderbevestiging.pdf | C12: 92 | D12: extracted | E12: 46080.531 | F12: 140505 | G12: application/pdf | H12: 4 | I12: 0
A13: 2508010179 ESSITY Orderbevestiging.pdf | C13: 85 | D13: extracted | E13: 46080.531 | F13: 142035 | G13: application/pdf | H13: 1 | I13: 0
... A100: Verkooporder SO00454663 _ 3504015927.pdf | C100: 85 | D100: extracted | E100: 46080.531 | F100: 372936 | G100: application/pdf | H100: 0 | I100: 60

Sheet Analyse 2 Detail 02-03
E1: =AVERAGE(E3:E495) -> 73.435233 | G1: =AVERAGE(G3:G495) -> 0.5010142 | M1: =AVERAGE(M3:M126) -> 61.080645 | O1: =AVERAGE(O3:O126) -> 62.822581 | Q1: =AVERAGE(Q3:Q126) -> 63.129032 | S1: =AVERAGE(S3:S126) -> 62.879032 | U1: =AVERAGE(U3:U126) -> 62.185484 | W1: =AVERAGE(W3:W126) -> 62.685484 | Y1: =AVERAGE(Y3:Y126) -> 62.975806 | AA1: =AVERAGE(AA3:AA126) -> 62.403226 | AC1: =AVERAGE(AC3:AC126) -> 61.209677 | AE1: =AVERAGE(AE3:AE126) -> 63.016129 | AG1: =AVERAGE(AG3:AG126) -> 61.153226 | AI1: =AVERAGE(AI3:AI126) -> 61 | AK1: =AVERAGE(AK3:AK33) -> 70.903226
A2: File Name | B2: Document Type | C2: Status | D2: Uploaded (UTC) | E2: Extraction Score | F2: Total Fields | G2: Missing Fields | H2: Reviewed By | I2: Source | J2: Language | K2: Line Item # | L2: Purchase Order Number | M2: Purchase Order Number (Confidence %) | N2: Supplier Order Number | O2: Supplier Order Number (Confidence %) | P2: Order Date | Q2: Order Date (Confidence %) | R2: Supplier Name | S2: Supplier Name (Confidence %) | T2: Customer Name | U2: Customer Name (Confidence %) | V2: Currency | W2: Currency (Confidence %) | X2: Line Number | Y2: Line Number (Confidence %) | Z2: Article Number | AA2: Article Number (Confidence %) | AB2: Item Description | AC2: Item Description (Confidence %) | AD2: Quantity | AE2: Quantity (Confidence %) | AF2: Unit of Measure | AG2: Unit of Measure (Confidence %) | AH2: Unit Price | AI2: Unit Price (Confidence %) | AJ2: Item Planned Delivery Date | AK2: Item Planned Delivery Date (Confidence %)
A3: Uw orderbevestiging 60392040.pdf | B3: Purchase Order Confirmation | C3: extracted | D3: 46080.56 | E3: 93.8 | F3: 13 | G3: 0 | I3: mail - noreply@qrs.nl — Uw orderbevestiging 60392040 | J3: Dutch | K3: 1 | L3: 1505040024 | M3: 95 | N3: 60392040 | O3: 90 | P3: 16/02/2026 | Q3: 98 | R3: QRS Healthcare BV | S3: 92 | T3: Hospital Logistics Nederland BV (Bernhoven) | U3: 94 | V3: EUR | W3: 96 | X3: 1 | Y3: 90 | Z3: 54758 | AA3: 98 | AB3: Dispo Medical Cystoscopie enkel (50 stuks) | AC3: 96 | AD3: 5 | AE3: 98 | AF3: DS | AG3: 92 | AH3: EUR 166,21 | AI3: 95 | AJ3: 20/02/2026 | AK3: 92
A4: Verkooporder SO00454632 _ 3505026682.pdf | B4: Purchase Order Confirmation | C4: extracted | D4: 46080.56 | E4: 90.83 | F4: 104 | G4: 0 | I4: mail - info@g3-medical.nl — Verkooporder SO00454632 / 3505026682 | J4: Dutch | K4: 1 | L4: 3505026682 | M4: 98 | N4: SO00454632 | O4: 95 | P4: 16/02/2026 | Q4: 95 | R4: G3 Medical B.V. | S4: 95 | T4: Hospital Logistics Nederland B.V. | U4: 92 | V4: EUR | W4: 95 | X4: 1 | Y4: 95 | Z4: BP30F | AA4: 95 | AB4: Kai biopsie punch, disposable, steriel, 3,0mm, 20x1st/ds | AC4: 92 | AD4: 5 | AE4: 95 | AF4: Dozen | AG4: 92 | AH4: 25,15 | AI4: 92 | AJ4: 19/02/2026 | AK4: 90
A5: Verkooporder SO00454632 _ 3505026682.pdf | B5: Purchase Order Confirmation | C5: extracted | D5: 46080.56 | E5: 90.83 | F5: 104 | G5: 0 | I5: mail - info@g3-medical.nl — Verkooporder SO00454632 / 3505026682 | J5: Dutch | K5: 2 | L5: 3505026682 | M5: 98 | N5: SO00454632 | O5: 95 | P5: 16/02/2026 | Q5: 95 | R5: G3 Medical B.V. | S5: 95 | T5: Hospital Logistics Nederland B.V. | U5: 92 | V5: EUR | W5: 95 | X5: 2 | Y5: 95 | Z5: MK407 | AA5: 95 | AB5: Kai ring curette, disposable, steriel, 7,0mm, 20x1st/ds | AC5: 90 | AD5: 3 | AE5: 95 | AF5: Dozen | AG5: 92 | AH5: 33,31 | AI5: 92 | AJ5: 19/02/2026 | AK5: 90
A6: Verkooporder SO00454632 _ 3505026682.pdf | B6: Purchase Order Confirmation | C6: extracted | D6: 46080.56 | E6: 90.83 | F6: 104 | G6: 0 | I6: mail - info@g3-medical.nl — Verkooporder SO00454632 / 3505026682 | J6: Dutch | K6: 3 | L6: 3505026682 | M6: 98 | N6: SO00454632 | O6: 95 | P6: 16/02/2026 | Q6: 95 | R6: G3 Medical B.V. | S6: 95 | T6: Hospital Logistics Nederland B.V. | U6: 92 | V6: EUR | W6: 95 | X6: 3 | Y6: 95 | Z6: BP50F | AA6: 95 | AB6: Kai biopsie punch, disposable, steriel, 5,0mm, 20x1st/ds | AC6: 90 | AD6: 1 | AE6: 95 | AF6: Dozen | AG6: 92 | AH6: 26,07 | AI6: 92 | AJ6: 19/02/2026 | AK6: 90
A7: Verkooporder SO00454632 _ 3505026682.pdf | B7: Purchase Order Confirmation | C7: extracted | D7: 46080.56 | E7: 90.83 | F7: 104 | G7: 0 | I7: mail - info@g3-medical.nl — Verkooporder SO00454632 / 3505026682 | J7: Dutch | K7: 4 | L7: 3505026682 | M7: 98 | N7: SO00454632 | O7: 95 | P7: 16/02/2026 | Q7: 95 | R7: G3 Medical B.V. | S7: 95 | T7: Hospital Logistics Nederland B.V. | U7: 92 | V7: EUR | W7: 95 | X7: 4 | Y7: 95 | Z7: 700635 | AA7: 95 | AB7: Medicijnbeker 30ml, disposable, transparant, 100st/ds | AC7: 88 | AD7: 3 | AE7: 95 | AF7: Dozen | AG7: 90 | AH7: 30,79 | AI7: 92 | AJ7: 19/02/2026 | AK7: 90
A8: Verkooporder SO00454632 _ 3505026682.pdf | B8: Purchase Order Confirmation | C8: extracted | D8: 46080.56 | E8: 90.83 | F8: 104 | G8: 0 | I8: mail - info@g3-medical.nl — Verkooporder SO00454632 / 3505026682 | J8: Dutch | K8: 5 | L8: 3505026682 | M8: 98 | N8: SO00454632 | O8: 95 | P8: 16/02/2026 | Q8: 95 | R8: G3 Medical B.V. | S8: 95 | T8: Hospital Logistics Nederland B.V. | U8: 92 | V8: EUR | W8: 95 | X8: 5 | Y8: 95 | Z8: 300205 | AA8: 95 | AB8: CMT Identificatie foambandje, baby, disposable, X-Large, wit, 24st/doos | AC8: 92 | AD8: 4 | AE8: 95 | AF8: Dozen | AG8: 92 | AH8: 53,08 | AI8: 92 | AJ8: 19/02/2026 | AK8: 90
A9: Verkooporder SO00454632 _ 3505026682.pdf | B9: Purchase Order Confirmation | C9: extracted | D9: 46080.56 | E9: 90.83 | F9: 104 | G9: 0 | I9: mail - info@g3-medical.nl — Verkooporder SO00454632 / 3505026682 | J9: Dutch | K9: 6 | L9: 3505026682 | M9: 98 | N9: SO00454632 | O9: 95 | P9: 16/02/2026 | Q9: 95 | R9: G3 Medical B.V. | S9: 95 | T9: Hospital Logistics Nederland B.V. | U9: 92 | V9: EUR | W9: 95 | X9: 6 | Y9: 95 | Z9: 700747 | AA9: 95 | AB9: Medi-inn scheermesje, dubbel-edged, disposable, blauw, 100st/doos | AC9: 90 | AD9: 2 | AE9: 95 | AF9: Dozen | AG9: 92 | AH9: 9,13 | AI9: 92 | AJ9: 19/02/2026 | AK9: 90
A10: Verkooporder SO00454632 _ 3505026682.pdf | B10: Purchase Order Confirmation | C10: extracted | D10: 46080.56 | E10: 90.83 | F10: 104 | G10: 0 | I10: mail - info@g3-medical.nl — Verkooporder SO00454632 / 3505026682 | J10: Dutch | K10: 7 | L10: 3505026682 | M10: 98 | N10: SO00454632 | O10: 95 | P10: 16/02/2026 | Q10: 95 | R10: G3 Medical B.V. | S10: 95 | T10: Hospital Logistics Nederland B.V. | U10: 92 | V10: EUR | W10: 95 | X10: 7 | Y10: 95 | Z10: 700555 | AA10: 95 | AB10: Waca drinkbeker, PP, 250ml, semi-transparent, p/st | AC10: 88 | AD10: 2 | AE10: 95 | AF10: Stuks | AG10: 90 | AH10: 1,09 | AI10: 92 | AJ10: 19/02/2026 | AK10: 90
A11: Verkooporder SO00454632 _ 3505026682.pdf | B11: Purchase Order Confirmation | C11: extracted | D11: 46080.56 | E11: 90.83 | F11: 104 | G11: 0 | I11: mail - info@g3-medical.nl — Verkooporder SO00454632 / 3505026682 | J11: Dutch | K11: 8 | L11: 3505026682 | M11: 98 | N11: SO00454632 | O11: 95 | P11: 16/02/2026 | Q11: 95 | R11: G3 Medical B.V. | S11: 95 | T11: Hospital Logistics Nederland B.V. | U11: 92 | V11: EUR | W11: 95 | X11: 8 | Y11: 95 | Z11: 704400 | AA11: 95 | AB11: CMT Telemetrie draagtasjes, disposable, 21x16,5cm, PP/PE met lintfreeband, wit,100st/doos | AC11: 90 | AD11: 4 | AE11: 95 | AF11: Dozen | AG11: 92 | AH11: 52,08 | AI11: 92 | AJ11: 19/02/2026 | AK11: 90
A12: Verkooporder SO00454616 _ 3505026682.pdf | B12: Purchase Order Confirmation | C12: extracted | D12: 46080.56 | E12: 88.48 | F12: 143 | G12: 0 | I12: mail - info@g3-medical.nl — Verkooporder SO00454616 / 3505026682 | J12: Dutch | K12: 1 | L12: 3505026682 | M12: 98 | N12: SO00454616 | O12: 98 | P12: 16/02/2026 | Q12: 98 | R12: G3 Medical B.V. | S12: 95 | T12: Hospital Logistics Nederland B.V./Groene Hart Ziekenhuis | U12: 92 | V12: EUR | W12: 98 | X12: 1 | Y12: 98 | Z12: 700124 | AA12: 92 | AB12: Navelstrengklem, disposable, dubbele sluiting, blauw, steriel, 100x1st/ds | AC12: 88 | AD12: 3 | AE12: 96 | AF12: Dozen | AG12: 92 | AH12: 41,28 | AI12: 92 | AJ12: 19/02/2026 | AK12: 85
A13: Verkooporder SO00454616 _ 3505026682.pdf | B13: Purchase Order Confirmation | C13: extracted | D13: 46080.56 | E13: 88.48 | F13: 143 | G13: 0 | I13: mail - info@g3-medical.nl — Verkooporder SO00454616 / 3505026682 | J13: Dutch | K13: 2 | L13: 3505026682 | M13: 98 | N13: SO00454616 | O13: 98 | P13: 16/02/2026 | Q13: 98 | R13: G3 Medical B.V. | S13: 95 | T13: Hospital Logistics Nederland B.V./Groene Hart Ziekenhuis | U13: 92 | V13: EUR | W13: 98 | X13: 2 | Y13: 98 | Z13: 550269 | AA13: 90 | AB13: Noba 263106-1 gynaecologische tampon, 5mtr/6cm, steriel, 4x1st/ds | AC13: 86 | AD13: 8 | AE13: 96 | AF13: Dozen | AG13: 92 | AH13: 8,42 | AI13: 92 | AJ13: 19/02/2026 | AK13: 85
A14: Verkooporder SO00454616 _ 3505026682.pdf | B14: Purchase Order Confirmation | C14: extracted | D14: 46080.56 | E14: 88.48 | F14: 143 | G14: 0 | I14: mail - info@g3-medical.nl — Verkooporder SO00454616 / 3505026682 | J14: Dutch | K14: 3 | L14: 3505026682 | M14: 98 | N14: SO00454616 | O14: 98 | P14: 16/02/2026 | Q14: 98 | R14: G3 Medical B.V. | S14: 95 | T14: Hospital Logistics Nederland B.V./Groene Hart Ziekenhuis | U14: 92 | V14: EUR | W14: 98 | X14: 3 | Y14: 98 | Z14: 880421 | AA14: 90 | AB14: Swann Morton 0421, stitchcutter, 110mm, steriel, disposable, carbonstaal, per stuk, 100st/ds | AC14: 86 | AD14: 3 | AE14: 96 | AF14: Dozen | AG14: 92 | AH14: 30,83 | AI14: 90 | AJ14: 19/02/2026 | AK14: 85
... A22: Verkooporder SO00454616 _ 3505026682.pdf | B22: Purchase Order Confirmation | C22: extracted | D22: 46080.56 | E22: 88.48 | F22: 143 | G22: 0 | I22: mail - info@g3-medical.nl — Verkooporder SO00454616 / 3505026682 | J22: Dutch | K22: 11 | L22: 3505026682 | M22: 98 | N22: SO00454616 | O22: 98 | P22: 16/02/2026 | Q22: 98 | R22: G3 Medical B.V. | S22: 95 | T22: Hospital Logistics Nederland B.V./Groene Hart Ziekenhuis | U22: 92 | V22: EUR | W22: 98 | X22: 11 | Y22: 98 | Z22: MKKSS | AA22: 90 | AB22: HP MKK-SS Polsband met enkele bevestigingsband, 30 cm, p/pr | AC22: 88 | AD22: 7 | AE22: 96 | AF22: Paar | AG22: 92 | AH22: 9,90 | AI22: 90 | AJ22: 26/02/2026 | AK22: 96
A23: Re_ [EXTERNAL EMAIL] Order Hospital Logistics 1507018691.pdf | B23: Purchase Order Confirmation | C23: extracted | D23: 46080.559 | E23: 88.54 | F23: 78 | G23: 5 | I23: mail - orders.NL@freseniusmedicalcare.com — Re: [EXTERNAL EMAIL] Order Hospital Logistics 1507018691 | J23: Dutch | K23: 1 | L23: 1507018691 | M23: 98 | N23: 2364062865 | O23: 96 | P23: 16/02/2026 | Q23: 92 | R23: Fresenius Medical Care Nederland BV | S23: 92 | T23: Hospital Logistics, Medisch Centrum Leeuwarden | U23: 88 | V23: EUR | W23: 96 | X23: 10 | Y23: 95 | Z23: 5092030 | AA23: 95 | AB23: Prijs per behandeling BTW Laag | AC23: 90 | AD23: 240 | AE23: 94 | AF23: ST | AG23: 92 | AH23: 27,77 | AI23: 94 | AK23: 20
A24: Re_ [EXTERNAL EMAIL] Order Hospital Logistics 1507018691.pdf | B24: Purchase Order Confirmation | C24: extracted | D24: 46080.559 | E24: 88.54 | F24: 78 | G24: 5 | I24: mail - orders.NL@freseniusmedicalcare.com — Re: [EXTERNAL EMAIL] Order Hospital Logistics 1507018691 | J24: Dutch | K24: 2 | L24: 1507018691 | M24: 98 | N24: 2364062865 | O24: 96 | P24: 16/02/2026 | Q24: 92 | R24: Fresenius Medical Care Nederland BV | S24: 92 | T24: Hospital Logistics, Medisch Centrum Leeuwarden | U24: 88 | V24: EUR | W24: 96 | X24: 210 | Y24: 95 | Z24: 5060781 | AA24: 95 | AB24: BIBAG 650g 5008 | AC24: 92 | AD24: 240 | AE24: 94 | AF24: ST | AG24: 92 | AH24: 27,77 | AI24: 95 | AJ24: 17/02/2026 | AK24: 95
A25: Re_ [EXTERNAL EMAIL] Order Hospital Logistics 1507018691.pdf | B25: Purchase Order Confirmation | C25: extracted | D25: 46080.559 | E25: 88.54 | F25: 78 | G25: 5 | I25: mail - orders.NL@freseniusmedicalcare.com — Re: [EXTERNAL EMAIL] Order Hospital Logistics 1507018691 | J25: Dutch | K25: 3 | L25: 1507018691 | M25: 98 | N25: 2364062865 | O25: 96 | P25: 16/02/2026 | Q25: 92 | R25: Fresenius Medical Care Nederland BV | S25: 92 | T25: Hospital Logistics, Medisch Centrum Leeuwarden | U25: 88 | V25: EUR | W25: 96 | X25: 440 | Y25: 95 | Z25: F00001591 | AA25: 95 | AB25: FX CorDiax 80 | AC25: 90 | AD25: 240 | AE25: 90 | AF25: ST | AG25: 88 | AI25: 30 | AJ25: 17/02/2026 | AK25: 95
A26: Re_ [EXTERNAL EMAIL] Order Hospital Logistics 1507018691.pdf | B26: Purchase Order Confirmation | C26: extracted | D26: 46080.559 | E26: 88.54 | F26: 78 | G26: 5 | I26: mail - orders.NL@freseniusmedicalcare.com — Re: [EXTERNAL EMAIL] Order Hospital Logistics 1507018691 | J26: Dutch | K26: 4 | L26: 1507018691 | M26: 98 | N26: 2364062865 | O26: 96 | P26: 16/02/2026 | Q26: 92 | R26: Fresenius Medical Care Nederland BV | S26: 92 | T26: Hospital Logistics, Medisch Centrum Leeuwarden | U26: 88 | V26: EUR | W26: 96 | X26: 660 | Y26: 95 | Z26: 5092030ID | AA26: 95 | AB26: Prijs per behandeling BTW Hoog | AC26: 92 | AD26: 240 | AE26: 94 | AF26: ST | AG26: 92 | AH26: 4,34 | AI26: 95 | AK26: 25
A27: Re_ [EXTERNAL EMAIL] Order Hospital Logistics 1507018691.pdf | B27: Purchase Order Confirmation | C27: extracted | D27: 46080.559 | E27: 88.54 | F27: 78 | G27: 5 | I27: mail - orders.NL@freseniusmedicalcare.com — Re: [EXTERNAL EMAIL] Order Hospital Logistics 1507018691 | J27: Dutch | K27: 5 | L27: 1507018691 | M27: 98 | N27: 2364062865 | O27: 96 | P27: 16/02/2026 | Q27: 92 | R27: Fresenius Medical Care Nederland BV | S27: 92 | T27: Hospital Logistics, Medisch Centrum Leeuwarden | U27: 88 | V27: EUR | W27: 96 | X27: 730 | Y27: 95 | Z27: F00006822 | AA27: 95 | AB27: FX CorAL 80 | AC27: 92 | AD27: 72 | AE27: 94 | AF27: ST | AG27: 92 | AH27: 5,38 | AI27: 95 | AK27: 25
A28: Re_ [EXTERNAL EMAIL] Order Hospital Logistics 1507018691.pdf | B28: Purchase Order Confirmation | C28: extracted | D28: 46080.559 | E28: 88.54 | F28: 78 | G28: 5 | I28: mail - orders.NL@freseniusmedicalcare.com — Re: [EXTERNAL EMAIL] Order Hospital Logistics 1507018691 | J28: Dutch | K28: 6 | L28: 1507018691 | M28: 98 | N28: 2364062865 | O28: 96 | P28: 16/02/2026 | Q28: 92 | R28: Fresenius Medical Care Nederland BV | S28: 92 | T28: Hospital Logistics, Medisch Centrum Leeuwarden | U28: 88 | V28: EUR | W28: 96 | X28: 810 | Y28: 95 | Z28: F00001595 | AA28: 95 | AB28: FX CorDiax 1000 | AC28: 92 | AD28: 168 | AE28: 94 | AF28: ST | AG28: 92 | AH28: 1,28 | AI28: 95 | AK28: 20
A29: Re_ [EXTERNAL EMAIL] Order Hospital Logistics 3504015924.pdf | B29: Purchase Order Confirmation | C29: extracted | D29: 46080.559 | E29: 89.42 | F29: 39 | G29: 3 | I29: mail - orders.NL@freseniusmedicalcare.com — Re: [EXTERNAL EMAIL] Order Hospital Logistics 3504015924 | J29: Dutch | K29: 1 | L29: 3504015924 | M29: 95 | N29: 2364063103 | O29: 90 | P29: 16/02/2026 | Q29: 95 | R29: Fresenius Medical Care Nederland BV | S29: 95 | T29: Hospital Logistics Nederland | U29: 95 | V29: EUR | W29: 100 | X29: 10 | Y29: 95 | Z29: 5060781 | AA29: 95 | AB29: BIBAG 650g 5008 | AC29: 90 | AD29: 128 | AE29: 95 | AF29: ST | AG29: 90 | AH29: 2,89 | AI29: 95 | AK29: 20
A30: Re_ [EXTERNAL EMAIL] Order Hospital Logistics 3504015924.pdf | B30: Purchase Order Confirmation | C30: extracted | D30: 46080.559 | E30: 89.42 | F30: 39 | G30: 3 | I30: mail - orders.NL@freseniusmedicalcare.com — Re: [EXTERNAL EMAIL] Order Hospital Logistics 3504015924 | J30: Dutch | K30: 2 | L30: 3504015924 | M30: 95 | N30: 2364063103 | O30: 90 | P30: 16/02/2026 | Q30: 95 | R30: Fresenius Medical Care Nederland BV | S30: 95 | T30: Hospital Logistics Nederland | U30: 95 | V30: EUR | W30: 100 | X30: 20 | Y30: 95 | Z30: F00002387 | AA30: 95 | AB30: FX 80 classix | AC30: 90 | AD30: 48 | AE30: 95 | AF30: ST | AG30: 90 | AH30: 8,48 | AI30: 95 | AK30: 20
A31: Re_ [EXTERNAL EMAIL] Order Hospital Logistics 3504015924.pdf | B31: Purchase Order Confirmation | C31: extracted | D31: 46080.559 | E31: 89.42 | F31: 39 | G31: 3 | I31: mail - orders.NL@freseniusmedicalcare.com — Re: [EXTERNAL EMAIL] Order Hospital Logistics 3504015924 | J31: Dutch | K31: 3 | L31: 3504015924 | M31: 95 | N31: 2364063103 | O31: 90 | P31: 16/02/2026 | Q31: 95 | R31: Fresenius Medical Care Nederland BV | S31: 95 | T31: Hospital Logistics Nederland | U31: 95 | V31: EUR | W31: 100 | X31: 30 | Y31: 95 | Z31: 5060801 | AA31: 95 | AB31: BIBAG 900g 5008 | AC31: 90 | AD31: 84 | AE31: 95 | AF31: ST | AG31: 90 | AH31: 3,95 | AI31: 95 | AK31: 20
A32: 3505026639 ESSITY Orderbevestiging.pdf | B32: Purchase Order Confirmation | C32: extracted | D32: 46080.559 | E32: 64.8 | F32: 1140 | G32: 0 | I32: mail - tena.medical.cs.nl@essity.com — 3505026639 ESSITY Orderbevestiging | J32: Dutch | K32: 1 | L32: 3505026639 | M32: 50 | N32: 3004524437 | O32: 50 | P32: 11/02/2026 | Q32: 50 | R32: Essity Netherlands B.V. Health & Medical | S32: 50 | T32: Hospital Logistics Nederland b.v. | U32: 50 | V32: EUR | W32: 50 | X32: 10 | Y32: 50 | Z32: 7238101 | AA32: 50 | AB32: Leukomed T 8 x 10cm - P50 | AC32: 50 | AD32: 4 | AE32: 50 | AF32: PC | AG32: 50 | AH32: 18,77 / 1 PC | AI32: 50 | AJ32: 18/02/2026 | AK32: 50
A33: 3505026639 ESSITY Orderbevestiging.pdf | B33: Purchase Order Confirmation | C33: extracted | D33: 46080.559 | E33: 64.8 | F33: 1140 | G33: 0 | I33: mail - tena.medical.cs.nl@essity.com — 3505026639 ESSITY Orderbevestiging | J33: Dutch | K33: 2 | L33: 3505026639 | M33: 50 | N33: 3004524437 | O33: 50 | P33: 11/02/2026 | Q33: 50 | R33: Essity Netherlands B.V. Health & Medical | S33: 50 | T33: Hospital Logistics Nederland b.v. | U33: 50 | V33: EUR | W33: 50 | X33: 20 | Y33: 50 | Z33: 7268000 | AA33: 50 | AB33: Cuticell Contact 5 x 7,5cm - P5 | AC33: 50 | AD33: 60 | AE33: 50 | AF33: PC | AG33: 50 | AH33: 4,41 / 1 PC | AI33: 50 | AJ33: 18/02/2026 | AK33: 50
A34: 3505026639 ESSITY Orderbevestiging.pdf | B34: Purchase Order Confirmation | C34: extracted | D34: 46080.559 | E34: 64.8 | F34: 1140 | G34: 0 | I34: mail - tena.medical.cs.nl@essity.com — 3505026639 ESSITY Orderbevestiging | J34: Dutch | K34: 3 | L34: 3505026639 | M34: 50 | N34: 3004524437 | O34: 50 | P34: 11/02/2026 | Q34: 50 | R34: Essity Netherlands B.V. Health & Medical | S34: 50 | T34: Hospital Logistics Nederland b.v. | U34: 50 | V34: EUR | W34: 50 | X34: 30 | Y34: 50 | Z34: 7123718 | AA34: 50 | AB34: LP comp cot gauze ST 10x20cm 12PLY - P50x1 | AC34: 50 | AD34: 3 | AE34: 50 | AF34: PC | AG34: 50 | AH34: 8,71 / 1 PC | AI34: 50
A35: 3505026639 ESSITY Orderbevestiging.pdf | B35: Purchase Order Confirmation | C35: extracted | D35: 46080.559 | E35: 64.8 | F35: 1140 | G35: 0 | I35: mail - tena.medical.cs.nl@essity.com — 3505026639 ESSITY Orderbevestiging | J35: Dutch | K35: 4 | L35: 3505026639 | M35: 50 | N35: 3004524437 | O35: 50 | P35: 11/02/2026 | Q35: 50 | R35: Essity Netherlands B.V. Health & Medical | S35: 50 | T35: Hospital Logistics Nederland b.v. | U35: 50 | V35: EUR | W35: 50 | X35: 40 | Y35: 50 | Z35: 7274007 | AA35: 50 | AB35: LP WCS ST natural 6x75mm - P50x3 strips | AC35: 50 | AD35: 2 | AE35: 50 | AF35: PC | AG35: 50 | AH35: 26,35 / 1 PC | AI35: 50 | AJ35: 18/02/2026 | AK35: 50
A36: 3505026639 ESSITY Orderbevestiging.pdf | B36: Purchase Order Confirmation | C36: extracted | D36: 46080.559 | E36: 64.8 | F36: 1140 | G36: 0 | I36: mail - tena.medical.cs.nl@essity.com — 3505026639 ESSITY Orderbevestiging | J36: Dutch | K36: 5 | L36: 3505026639 | M36: 50 | N36: 3004524437 | O36: 50 | P36: 11/02/2026 | Q36: 50 | R36: Essity Netherlands B.V. Health & Medical | S36: 50 | T36: Hospital Logistics Nederland b.v. | U36: 50 | V36: EUR | W36: 50 | X36: 50 | Y36: 50 | Z36: 7274006 | AA36: 50 | AB36: LP WCS ST natural 6x38mm - P50x6 strips | AC36: 50 | AD36: 2 | AE36: 50 | AF36: PC | AG36: 50 | AH36: 28,19 / 1 PC | AI36: 50 | AJ36: 18/02/2026 | AK36: 50
A37: 3505026639 ESSITY Orderbevestiging.pdf | B37: Purchase Order Confirmation | C37: extracted | D37: 46080.559 | E37: 64.8 | F37: 1140 | G37: 0 | I37: mail - tena.medical.cs.nl@essity.com — 3505026639 ESSITY Orderbevestiging | J37: Dutch | K37: 6 | L37: 3505026639 | M37: 50 | N37: 3004524437 | O37: 50 | P37: 11/02/2026 | Q37: 50 | R37: Essity Netherlands B.V. Health & Medical | S37: 50 | T37: Hospital Logistics Nederland b.v. | U37: 50 | V37: EUR | W37: 50 | X37: 60 | Y37: 50 | Z37: 7274008 | AA37: 50 | AB37: LP WCS ST natural 12x100mm - P50x6 strips | AC37: 50 | AD37: 2 | AE37: 50 | AF37: PC | AG37: 50 | AH37: 36,16 / 1 PC | AI37: 50 | AJ37: 18/02/2026 | AK37: 50
A38: 3505026639 ESSITY Orderbevestiging.pdf | B38: Purchase Order Confirmation | C38: extracted | D38: 46080.559 | E38: 64.8 | F38: 1140 | G38: 0 | I38: mail - tena.medical.cs.nl@essity.com — 3505026639 ESSITY Orderbevestiging | J38: Dutch | K38: 7 | L38: 3505026639 | M38: 50 | N38: 3004524437 | O38: 50 | P38: 11/02/2026 | Q38: 50 | R38: Essity Netherlands B.V. Health & Medical | S38: 50 | T38: Hospital Logistics Nederland b.v. | U38: 50 | V38: EUR | W38: 50 | X38: 70 | Y38: 50 | Z38: 7128201 | AA38: 50 | AB38: LP comp abs protect ST 20 x 40cm - P25x1 | AC38: 50 | AD38: 7 | AE38: 50 | AF38: PC | AG38: 50 | AH38: 14,28 / 1 PC | AI38: 50 | AJ38: 18/02/2026 | AK38: 50
A39: 3505026639 ESSITY Orderbevestiging.pdf | B39: Purchase Order Confirmation | C39: extracted | D39: 46080.559 | E39: 64.8 | F39: 1140 | G39: 0 | I39: mail - tena.medical.cs.nl@essity.com — 3505026639 ESSITY Orderbevestiging | J39: Dutch | K39: 8 | L39: 3505026639 | M39: 50 | N39: 3004524437 | O39: 50 | P39: 11/02/2026 | Q39: 50 | R39: Essity Netherlands B.V. Health & Medical | S39: 50 | T39: Hospital Logistics Nederland b.v. | U39: 50 | V39: EUR | W39: 50 | X39: 80 | Y39: 50 | Z39: 7128203 | AA39: 50 | AB39: LP comp abs protect ST 10 x 20cm - P50x1 | AC39: 50 | AD39: 24 | AE39: 50 | AF39: PC | AG39: 50 | AH39: 9,29 / 1 PC | AI39: 50 | AJ39: 18/02/2026 | AK39: 50
A40: 3505026639 ESSITY Orderbevestiging.pdf | B40: Purchase Order Confirmation | C40: extracted | D40: 46080.559 | E40: 64.8 | F40: 1140 | G40: 0 | I40: mail - tena.medical.cs.nl@essity.com — 3505026639 ESSITY Orderbevestiging | J40: Dutch | K40: 9 | L40: 3505026639 | M40: 50 | N40: 3004524437 | O40: 50 | P40: 11/02/2026 | Q40: 50 | R40: Essity Netherlands B.V. Health & Medical | S40: 50 | T40: Hospital Logistics Nederland b.v. | U40: 50 | V40: EUR | W40: 50 | X40: 90 | Y40: 50 | Z40: 7128814 | AA40: 50 | AB40: LP comp non-wov ST 10x10cm 4PLY - P25x10 | AC40: 50 | AD40: 15 | AE40: 50 | AF40: PC | AG40: 50 | AH40: 5,95 / 1 PC | AI40: 50 | AJ40: 18/02/2026 | AK40: 50
A41: 3505026639 ESSITY Orderbevestiging.pdf | B41: Purchase Order Confirmation | C41: extracted | D41: 46080.559 | E41: 64.8 | F41: 1140 | G41: 0 | I41: mail - tena.medical.cs.nl@essity.com — 3505026639 ESSITY Orderbevestiging | J41: Dutch | K41: 10 | L41: 3505026639 | M41: 50 | N41: 3004524437 | O41: 50 | P41: 11/02/2026 | Q41: 50 | R41: Essity Netherlands B.V. Health & Medical | S41: 50 | T41: Hospital Logistics Nederland b.v. | U41: 50 | V41: EUR | W41: 50 | X41: 100 | Y41: 50 | Z41: 7228001 | AA41: 50 | AB41: DC Conformable wit 3,6m x 5cm - P10 | AC41: 50 | AD41: 7 | AE41: 50 | AF41: PC | AG41: 50 | AH41: 50,25 / 1 PC | AI41: 50 | AJ41: 18/02/2026 | AK41: 50
A42: 3505026639 ESSITY Orderbevestiging.pdf | B42: Purchase Order Confirmation | C42: extracted | D42: 46080.559 | E42: 64.8 | F42: 1140 | G42: 0 | I42: mail - tena.medical.cs.nl@essity.com — 3505026639 ESSITY Orderbevestiging | J42: Dutch | K42: 11 | L42: 3505026639 | M42: 50 | N42: 3004524437 | O42: 50 | P42: 11/02/2026 | Q42: 50 | R42: Essity Netherlands B.V. Health & Medical | S42: 50 | T42: Hospital Logistics Nederland b.v. | U42: 50 | V42: EUR | W42: 50 | X42: 110 | Y42: 50 | Z42: 7228002 | AA42: 50 | AB42: DC Conformable wit 3,6m x 7,5cm - P10 | AC42: 50 | AD42: 16 | AE42: 50 | AF42: PC | AG42: 50 | AH42: 61,49 / 1 PC | AI42: 50 | AJ42: 18/02/2026 | AK42: 50
A43: 3505026639 ESSITY Orderbevestiging.pdf | B43: Purchase Order Confirmation | C43: extracted | D43: 46080.559 | E43: 64.8 | F43: 1140 | G43: 0 | I43: mail - tena.medical.cs.nl@essity.com — 3505026639 ESSITY Orderbevestiging | J43: Dutch | K43: 12 | L43: 3505026639 | M43: 50 | N43: 3004524437 | O43: 50 | P43: 11/02/2026 | Q43: 50 | R43: Essity Netherlands B.V. Health & Medical | S43: 50 | T43: Hospital Logistics Nederland b.v. | U43: 50 | V43: EUR | W43: 50 | X43: 120 | Y43: 50 | Z43: 7228003 | AA43: 50 | AB43: DC Conformable wit 3,6m x 10cm - P10 | AC43: 50 | AD43: 7 | AE43: 50 | AF43: PC | AG43: 50 | AH43: 72,23 / 1 PC | AI43: 50 | AJ43: 18/02/2026 | AK43: 50
A44: 3505026639 ESSITY Orderbevestiging.pdf | B44: Purchase Order Confirmation | C44: extracted | D44: 46080.559 | E44: 64.8 | F44: 1140 | G44: 0 | I44: mail - tena.medical.cs.nl@essity.com — 3505026639 ESSITY Orderbevestiging | J44: Dutch | K44: 13 | L44: 3505026639 | M44: 50 | N44: 3004524437 | O44: 50 | P44: 11/02/2026 | Q44: 50 | R44: Essity Netherlands B.V. Health & Medical | S44: 50 | T44: Hospital Logistics Nederland b.v. | U44: 50 | V44: EUR | W44: 50 | X44: 130 | Y44: 50 | Z44: 7228004 | AA44: 50 | AB44: DC Conformable wit 3,6m x 12,5cm - P10 | AC44: 50 | AD44: 3 | AE44: 50 | AF44: PC | AG44: 50 | AH44: 79,79 / 1 PC | AI44: 50 | AJ44: 18/02/2026 | AK44: 50
A45: 3505026639 ESSITY Orderbevestiging.pdf | B45: Purchase Order Confirmation | C45: extracted | D45: 46080.559 | E45: 64.8 | F45: 1140 | G45: 0 | I45: mail - tena.medical.cs.nl@essity.com — 3505026639 ESSITY Orderbevestiging | J45: Dutch | K45: 14 | L45: 3505026639 | M45: 50 | N45: 3004524437 | O45: 50 | P45: 11/02/2026 | Q45: 50 | R45: Essity Netherlands B.V. Health & Medical | S45: 50 | T45: Hospital Logistics Nederland b.v. | U45: 50 | V45: EUR | W45: 50 | X45: 140 | Y45: 50 | Z45: 7228601 | AA45: 50 | AB45: DC Conformable paars 3,6m x 7,5cm - P10 | AC45: 50 | AD45: 2 | AE45: 50 | AF45: PC | AG45: 50 | AH45: 67,13 / 1 PC | AI45: 50 | AJ45: 18/02/2026 | AK45: 50
A46: 3505026639 ESSITY Orderbevestiging.pdf | B46: Purchase Order Confirmation | C46: extracted | D46: 46080.559 | E46: 64.8 | F46: 1140 | G46: 0 | I46: mail - tena.medical.cs.nl@essity.com — 3505026639 ESSITY Orderbevestiging | J46: Dutch | K46: 15 | L46: 3505026639 | M46: 50 | N46: 3004524437 | O46: 50 | P46: 11/02/2026 | Q46: 50 | R46: Essity Netherlands B.V. Health & Medical | S46: 50 | T46: Hospital Logistics Nederland b.v. | U46: 50 | V46: EUR | W46: 50 | X46: 150 | Y46: 50 | Z46: 7228801 | AA46: 50 | AB46: DCC zwart 3,6m x 7,5cm - P10 | AC46: 50 | AD46: 4 | AE46: 50 | AF46: PC | AG46: 50 | AH46: 62,74 / 1 PC | AI46: 50 | AJ46: 18/02/2026 | AK46: 50
... A75: 3505026639 ESSITY Orderbevestiging.pdf | B75: Purchase Order Confirmation | C75: extracted | D75: 46080.559 | E75: 64.8 | F75: 1140 | G75: 0 | I75: mail - tena.medical.cs.nl@essity.com — 3505026639 ESSITY Orderbevestiging | J75: Dutch | K75: 44 | L75: 3505026639 | M75: 50 | N75: 3004524437 | O75: 50 | P75: 11/02/2026 | Q75: 50 | R75: Essity Netherlands B.V. Health & Medical | S75: 50 | T75: Hospital Logistics Nederland b.v. | U75: 50 | V75: EUR | W75: 50 | X75: 440 | Y75: 50 | Z75: 7702800 | AA75: 50 | AB75: Comprinet pro knie groot wit 1pr | AC75: 50 | AD75: 10 | AE75: 50 | AF75: PC | AG75: 50 | AH75: 5,17 / 1 PC | AI75: 50 | AJ75: 18/02/2026 | AK75: 50
A76: 3505026639 ESSITY Orderbevestiging.pdf | B76: Purchase Order Confirmation | C76: extracted | D76: 46080.559 | E76: 64.8 | F76: 1140 | G76: 0 | I76: mail - tena.medical.cs.nl@essity.com — 3505026639 ESSITY Orderbevestiging | J76: Dutch | K76: 45 | L76: 3505026639 | M76: 50 | N76: 3004524437 | O76: 50 | P76: 11/02/2026 | Q76: 50 | R76: Essity Netherlands B.V. Health & Medical | S76: 50 | T76: Hospital Logistics Nederland b.v. | U76: 50 | V76: EUR | W76: 50 | X76: 450 | Y76: 50 | Z76: 0956600 | AA76: 50 | AB76: Leukosilk 9,2m x 1,25cm | AC76: 50 | AD76: 48 | AE76: 50 | AF76: PC | AG76: 50 | AH76: 0,71 / 1 PC | AI76: 50
A77: 3505026639 ESSITY Orderbevestiging.pdf | B77: Purchase Order Confirmation | C77: extracted | D77: 46080.559 | E77: 64.8 | F77: 1140 | G77: 0 | I77: mail - tena.medical.cs.nl@essity.com — 3505026639 ESSITY Orderbevestiging | J77: Dutch | K77: 46 | L77: 3505026639 | M77: 50 | N77: 3004524437 | O77: 50 | P77: 11/02/2026 | Q77: 50 | R77: Essity Netherlands B.V. Health & Medical | S77: 50 | T77: Hospital Logistics Nederland b.v. | U77: 50 | V77: EUR | W77: 50 | X77: 460 | Y77: 50 | Z77: 0195700 | AA77: 50 | AB77: Ideaal BSN 5m x 12cm ongecoffeleerd | AC77: 50 | AD77: 10 | AE77: 50 | AF77: PC | AG77: 50 | AH77: 1,16 / 1 PC | AI77: 50 | AJ77: 18/02/2026 | AK77: 50
A78: 3505026639 ESSITY Orderbevestiging.pdf | B78: Purchase Order Confirmation | C78: extracted | D78: 46080.559 | E78: 64.8 | F78: 1140 | G78: 0 | I78: mail - tena.medical.cs.nl@essity.com — 3505026639 ESSITY Orderbevestiging | J78: Dutch | K78: 47 | L78: 3505026639 | M78: 50 | N78: 3004524437 | O78: 50 | P78: 11/02/2026 | Q78: 50 | R78: Essity Netherlands B.V. Health & Medical | S78: 50 | T78: Hospital Logistics Nederland b.v. | U78: 50 | V78: EUR | W78: 50 | X78: 470 | Y78: 50 | Z78: 0904600 | AA78: 50 | AB78: Artiflex 10cm x 3m - P30 | AC78: 50 | AD78: 2 | AE78: 50 | AF78: PC | AG78: 50 | AH78: 25,11 / 1 PC | AI78: 50 | AJ78: 18/02/2026 | AK78: 50
A79: 3505026639 ESSITY Orderbevestiging.pdf | B79: Purchase Order Confirmation | C79: extracted | D79: 46080.559 | E79: 64.8 | F79: 1140 | G79: 0 | I79: mail - tena.medical.cs.nl@essity.com — 3505026639 ESSITY Orderbevestiging | J79: Dutch | K79: 48 | L79: 3505026639 | M79: 50 | N79: 3004524437 | O79: 50 | P79: 11/02/2026 | Q79: 50 | R79: Essity Netherlands B.V. Health & Medical | S79: 50 | T79: Hospital Logistics Nederland b.v. | U79: 50 | V79: EUR | W79: 50 | X79: 480 | Y79: 50 | Z79: 4419 | AA79: 50 | AB79: TENA ProSkin Barrier Cream 150 ml | AC79: 50 | AD79: 12 | AE79: 50 | AF79: TRP | AG79: 50 | AH79: 1,98 / 1 CON | AI79: 50 | AJ79: 18/02/2026 | AK79: 50
A80: 3505026639 ESSITY Orderbevestiging.pdf | B80: Purchase Order Confirmation | C80: extracted | D80: 46080.559 | E80: 64.8 | F80: 1140 | G80: 0 | I80: mail - tena.medical.cs.nl@essity.com — 3505026639 ESSITY Orderbevestiging | J80: Dutch | K80: 49 | L80: 3505026639 | M80: 50 | N80: 3004524437 | O80: 50 | P80: 11/02/2026 | Q80: 50 | R80: Essity Netherlands B.V. Health & Medical | S80: 50 | T80: Hospital Logistics Nederland b.v. | U80: 50 | V80: EUR | W80: 50 | X80: 490 | Y80: 50 | Z80: 774458 | AA80: 50 | AB80: TENA Hygiene Sheet 210 x 80 cm | AC80: 50 | AD80: 8 | AE80: 50 | AF80: TRP | AG80: 50 | AH80: 56,17 / 1 TRP | AI80: 50 | AJ80: 18/02/2026 | AK80: 50
A81: 3505026639 ESSITY Orderbevestiging.pdf | B81: Purchase Order Confirmation | C81: extracted | D81: 46080.559 | E81: 64.8 | F81: 1140 | G81: 0 | I81: mail - tena.medical.cs.nl@essity.com — 3505026639 ESSITY Orderbevestiging | J81: Dutch | K81: 50 | L81: 3505026639 | M81: 50 | N81: 3004524437 | O81: 50 | P81: 11/02/2026 | Q81: 50 | R81: Essity Netherlands B.V. Health & Medical | S81: 50 | T81: Hospital Logistics Nederland b.v. | U81: 50 | V81: EUR | W81: 50 | X81: 500 | Y81: 50 | Z81: 4537100 | AA81: 50 | AB81: Elastomull haft color blauw 20m x 6cm | AC81: 50 | AD81: 24 | AE81: 50 | AF81: PC | AG81: 50 | AH81: 3,03 / 1 PC | AI81: 50 | AJ81: 18/02/2026 | AK81: 50
A82: 3505026639 ESSITY Orderbevestiging.pdf | B82: Purchase Order Confirmation | C82: extracted | D82: 46080.559 | E82: 64.8 | F82: 1140 | G82: 0 | I82: mail - tena.medical.cs.nl@essity.com — 3505026639 ESSITY Orderbevestiging | J82: Dutch | K82: 51 | L82: 3505026639 | M82: 50 | N82: 3004524437 | O82: 50 | P82: 11/02/2026 | Q82: 50 | R82: Essity Netherlands B.V. Health & Medical | S82: 50 | T82: Hospital Logistics Nederland b.v. | U82: 50 | V82: EUR | W82: 50 | X82: 510 | Y82: 50 | Z82: 4537200 | AA82: 50 | AB82: Elastomull haft color blauw 20m x 8cm | AC82: 50 | AD82: 24 | AE82: 50 | AF82: PC | AG82: 50 | AH82: 3,04 / 1 PC | AI82: 50
A83: 3505026639 ESSITY Orderbevestiging.pdf | B83: Purchase Order Confirmation | C83: extracted | D83: 46080.559 | E83: 64.8 | F83: 1140 | G83: 0 | I83: mail - tena.medical.cs.nl@essity.com — 3505026639 ESSITY Orderbevestiging | J83: Dutch | K83: 52 | L83: 3505026639 | M83: 50 | N83: 3004524437 | O83: 50 | P83: 11/02/2026 | Q83: 50 | R83: Essity Netherlands B.V. Health & Medical | S83: 50 | T83: Hospital Logistics Nederland b.v. | U83: 50 | V83: EUR | W83: 50 | X83: 520 | Y83: 50 | Z83: 4547000 | AA83: 50 | AB83: Elastomull haft 4m x 4cm | AC83: 50 | AD83: 160 | AE83: 50 | AF83: PC | AG83: 50 | AH83: 0,54 / 1 PC | AI83: 50 | AJ83: 18/02/2026 | AK83: 50
A84: 3505026639 ESSITY Orderbevestiging.pdf | B84: Purchase Order Confirmation | C84: extracted | D84: 46080.559 | E84: 64.8 | F84: 1140 | G84: 0 | I84: mail - tena.medical.cs.nl@essity.com — 3505026639 ESSITY Orderbevestiging | J84: Dutch | K84: 53 | L84: 3505026639 | M84: 50 | N84: 3004524437 | O84: 50 | P84: 11/02/2026 | Q84: 50 | R84: Essity Netherlands B.V. Health & Medical | S84: 50 | T84: Hospital Logistics Nederland b.v. | U84: 50 | V84: EUR | W84: 50 | X84: 530 | Y84: 50 | Z84: 4547300 | AA84: 50 | AB84: Elastomull haft 4m x 10cm | AC84: 50 | AD84: 30 | AE84: 50 | AF84: PC | AG84: 50 | AH84: 0,74 / 1 PC | AI84: 50 | AJ84: 18/02/2026 | AK84: 50
A85: 3505026639 ESSITY Orderbevestiging.pdf | B85: Purchase Order Confirmation | C85: extracted | D85: 46080.559 | E85: 64.8 | F85: 1140 | G85: 0 | I85: mail - tena.medical.cs.nl@essity.com — 3505026639 ESSITY Orderbevestiging | J85: Dutch | K85: 54 | L85: 3505026639 | M85: 50 | N85: 3004524437 | O85: 50 | P85: 11/02/2026 | Q85: 50 | R85: Essity Netherlands B.V. Health & Medical | S85: 50 | T85: Hospital Logistics Nederland b.v. | U85: 50 | V85: EUR | W85: 50 | X85: 540 | Y85: 50 | Z85: 7151501 | AA85: 50 | AB85: Tensogrip beige D - 10m x 7,5cm | AC85: 50 | AD85: 5 | AE85: 50 | AF85: PC | AG85: 50 | AH85: 13,72 / 1 PC | AI85: 50 | AJ85: 18/02/2026 | AK85: 50
A86: 3505026639 ESSITY Orderbevestiging.pdf | B86: Purchase Order Confirmation | C86: extracted | D86: 46080.559 | E86: 64.8 | F86: 1140 | G86: 0 | I86: mail - tena.medical.cs.nl@essity.com — 3505026639 ESSITY Orderbevestiging | J86: Dutch | K86: 55 | L86: 3505026639 | M86: 50 | N86: 3004524437 | O86: 50 | P86: 11/02/2026 | Q86: 50 | R86: Essity Netherlands B.V. Health & Medical | S86: 50 | T86: Hospital Logistics Nederland b.v. | U86: 50 | V86: EUR | W86: 50 | X86: 550 | Y86: 50 | Z86: 7199358 | AA86: 50 | AB86: Gypsona S 3m x 15cm - P40 | AC86: 50 | AD86: 1 | AE86: 50 | AF86: PC | AG86: 50 | AH86: 51,45 / 1 PC | AI86: 50 | AJ86: 18/02/2026 | AK86: 50
A87: 3505026639 ESSITY Orderbevestiging.pdf | B87: Purchase Order Confirmation | C87: extracted | D87: 46080.559 | E87: 64.8 | F87: 1140 | G87: 0 | I87: mail - tena.medical.cs.nl@essity.com — 3505026639 ESSITY Orderbevestiging | J87: Dutch | K87: 56 | L87: 3505026639 | M87: 50 | N87: 3004524437 | O87: 50 | P87: 11/02/2026 | Q87: 50 | R87: Essity Netherlands B.V. Health & Medical | S87: 50 | T87: Hospital Logistics Nederland b.v. | U87: 50 | V87: EUR | W87: 50 | X87: 560 | Y87: 50 | Z87: 7221302 | AA87: 50 | AB87: Leukoplast pro LF 9,2m x 5,00cm | AC87: 50 | AD87: 6 | AE87: 50 | AF87: PC | AG87: 50 | AH87: 2,52 / 1 PC | AI87: 50 | AJ87: 18/02/2026 | AK87: 50
A88: 3505026639 ESSITY Orderbevestiging.pdf | B88: Purchase Order Confirmation | C88: extracted | D88: 46080.559 | E88: 64.8 | F88: 1140 | G88: 0 | I88: mail - tena.medical.cs.nl@essity.com — 3505026639 ESSITY Orderbevestiging | J88: Dutch | K88: 57 | L88: 3505026639 | M88: 50 | N88: 3004524437 | O88: 50 | P88: 11/02/2026 | Q88: 50 | R88: Essity Netherlands B.V. Health & Medical | S88: 50 | T88: Hospital Logistics Nederland b.v. | U88: 50 | V88: EUR | W88: 50 | X88: 570 | Y88: 50 | Z88: 7221600 | AA88: 50 | AB88: Fixomull transparent 10m x 5cm | AC88: 50 | AD88: 12 | AE88: 50 | AF88: PC | AG88: 50 | AH88: 8,89 / 1 PC | AI88: 50 | AJ88: 18/02/2026 | AK88: 50
A89: 3505026639 ESSITY Orderbevestiging.pdf | B89: Purchase Order Confirmation | C89: extracted | D89: 46080.559 | E89: 64.8 | F89: 1140 | G89: 0 | I89: mail - tena.medical.cs.nl@essity.com — 3505026639 ESSITY Orderbevestiging | J89: Dutch | K89: 58 | L89: 3505026639 | M89: 50 | N89: 3004524437 | O89: 50 | P89: 11/02/2026 | Q89: 50 | R89: Essity Netherlands B.V. Health & Medical | S89: 50 | T89: Hospital Logistics Nederland b.v. | U89: 50 | V89: EUR | W89: 50 | X89: 580 | Y89: 50 | Z89: 7508000 | AA89: 50 | AB89: Comprilan S 5m x 10cm | AC89: 50 | AD89: 160 | AE89: 50 | AF89: PC | AG89: 50 | AH89: 2,41 / 1 PC | AI89: 50 | AJ89: 18/02/2026 | AK89: 50
A90: 3505026639 ESSITY Orderbevestiging.pdf | B90: Purchase Order Confirmation | C90: extracted | D90: 46080.559 | E90: 64.8 | F90: 1140 | G90: 0 | I90: mail - tena.medical.cs.nl@essity.com — 3505026639 ESSITY Orderbevestiging | J90: Dutch | K90: 59 | L90: 3505026639 | M90: 50 | N90: 3004524437 | O90: 50 | P90: 11/02/2026 | Q90: 50 | R90: Essity Netherlands B.V. Health & Medical | S90: 50 | T90: Hospital Logistics Nederland b.v. | U90: 50 | V90: EUR | W90: 50 | X90: 590 | Y90: 50 | Z90: 7508800 | AA90: 50 | AB90: Comprinet forte 23 dij middel wit 1pr | AC90: 50 | AD90: 40 | AE90: 50 | AF90: PC | AG90: 50 | AH90: 11,04 / 1 PC | AI90: 50 | AJ90: 18/02/2026 | AK90: 50
A91: 3505026639 ESSITY Orderbevestiging.pdf | B91: Purchase Order Confirmation | C91: extracted | D91: 46080.559 | E91: 64.8 | F91: 1140 | G91: 0 | I91: mail - tena.medical.cs.nl@essity.com — 3505026639 ESSITY Orderbevestiging | J91: Dutch | K91: 60 | L91: 3505026639 | M91: 50 | N91: 3004524437 | O91: 50 | P91: 11/02/2026 | Q91: 50 | R91: Essity Netherlands B.V. Health & Medical | S91: 50 | T91: Hospital Logistics Nederland b.v. | U91: 50 | V91: EUR | W91: 50 | X91: 600 | Y91: 50 | Z91: 7128400 | AA91: 50 | AB91: LP comp absorbent protect 100x300mm - P20 | AC91: 50 | AD91: 72 | AE91: 50 | AF91: PC | AG91: 50 | AH91: 3,21 / 1 PC | AI91: 50 | AJ91: 18/02/2026 | AK91: 50
A92: 3505026639 ESSITY Orderbevestiging.pdf | B92: Purchase Order Confirmation | C92: extracted | D92: 46080.559 | E92: 64.8 | F92: 1140 | G92: 0 | I92: mail - tena.medical.cs.nl@essity.com — 3505026639 ESSITY Orderbevestiging | J92: Dutch | K92: 61 | L92: 3505026639 | M92: 50 | N92: 3004524437 | O92: 50 | P92: 11/02/2026 | Q92: 50 | R92: Essity Netherlands B.V. Health & Medical | S92: 50 | T92: Hospital Logistics Nederland b.v. | U92: 50 | V92: EUR | W92: 50 | X92: 610 | Y92: 50 | Z92: 0209900 | AA92: 50 | AB92: Elastomull 4m x 4cm | AC92: 50 | AD92: 80 | AE92: 50 | AF92: PC | AG92: 50 | AH92: 0,08 / 1 PC | AI92: 50 | AJ92: 18/02/2026 | AK92: 50
A93: 3505026639 ESSITY Orderbevestiging.pdf | B93: Purchase Order Confirmation | C93: extracted | D93: 46080.559 | E93: 64.8 | F93: 1140 | G93: 0 | I93: mail - tena.medical.cs.nl@essity.com — 3505026639 ESSITY Orderbevestiging | J93: Dutch | K93: 62 | L93: 3505026639 | M93: 50 | N93: 3004524437 | O93: 50 | P93: 11/02/2026 | Q93: 50 | R93: Essity Netherlands B.V. Health & Medical | S93: 50 | T93: Hospital Logistics Nederland b.v. | U93: 50 | V93: EUR | W93: 50 | X93: 620 | Y93: 50 | Z93: 7129100 | AA93: 50 | AB93: Leukoplast wet wipe - P100 | AC93: 50 | AD93: 8 | AE93: 50 | AF93: PC | AG93: 50 | AH93: 1,37 / 1 PC | AI93: 50 | AJ93: 18/02/2026 | AK93: 50
A94: 3505026639 ESSITY Orderbevestiging.pdf | B94: Purchase Order Confirmation | C94: extracted | D94: 46080.559 | E94: 64.8 | F94: 1140 | G94: 0 | I94: mail - tena.medical.cs.nl@essity.com — 3505026639 ESSITY Orderbevestiging | J94: Dutch | K94: 63 | L94: 3505026639 | M94: 50 | N94: 3004524437 | O94: 50 | P94: 11/02/2026 | Q94: 50 | R94: Essity Netherlands B.V. Health & Medical | S94: 50 | T94: Hospital Logistics Nederland b.v. | U94: 50 | V94: EUR | W94: 50 | X94: 630 | Y94: 50 | Z94: 4547700 | AA94: 50 | AB94: Elastomull haft 20m x 8cm | AC94: 50 | AD94: 144 | AE94: 50 | AF94: PC | AG94: 50 | AH94: 3,34 / 1 PC | AI94: 50 | AJ94: 18/02/2026 | AK94: 50
... A118: 3505026639 ESSITY Orderbevestiging.pdf | B118: Purchase Order Confirmation | C118: extracted | D118: 46080.559 | E118: 64.8 | F118: 1140 | G118: 0 | I118: mail - tena.medical.cs.nl@essity.com — 3505026639 ESSITY Orderbevestiging | J118: Dutch | K118: 87 | L118: 3505026639 | M118: 50 | N118: 3004524437 | O118: 50 | P118: 11/02/2026 | Q118: 50 | R118: Essity Netherlands B.V. Health & Medical | S118: 50 | T118: Hospital Logistics Nederland b.v. | U118: 50 | V118: EUR | W118: 50 | X118: 870 | Y118: 50 | Z118: 7627637 | AA118: 50 | AB118: Activmove Closed Shell Air Walker Hoog M | AC118: 50 | AD118: 8 | AE118: 50 | AF118: PC | AG118: 50 | AH118: 46,29 / 1 PC | AI118: 50 | AJ118: 18/02/2026 | AK118: 50
A119: 3505026639 ESSITY Orderbevestiging.pdf | B119: Purchase Order Confirmation | C119: extracted | D119: 46080.559 | E119: 64.8 | F119: 1140 | G119: 0 | I119: mail - tena.medical.cs.nl@essity.com — 3505026639 ESSITY Orderbevestiging | J119: Dutch | K119: 88 | L119: 3505026639 | M119: 50 | N119: 3004524437 | O119: 50 | P119: 11/02/2026 | Q119: 50 | R119: Essity Netherlands B.V. Health & Medical | S119: 50 | T119: Hospital Logistics Nederland b.v. | U119: 50 | V119: EUR | W119: 50 | X119: 880 | Y119: 50 | Z119: 7627638 | AA119: 50 | AB119: Activmove Closed Shell Air Walker Hoog L | AC119: 50 | AD119: 2 | AE119: 50 | AF119: PC | AG119: 50 | AH119: 46,29 / 1 PC | AI119: 50
A120: Order bevestiging 26-02818.pdf | B120: Purchase Order Confirmation | C120: extracted | D120: 46080.559 | E120: 88.03 | F120: 26 | G120: 2 | I120: mail - no.reply.customer.service@medtronic.com — Order bevestiging 26-02818 | J120: Dutch | K120: 1 | M120: 10 | N120: 26-02818 | O120: 75 | P120: 16/02/2026 | Q120: 90 | R120: Medtronic Trading NL BV | S120: 95 | T120: Canisius Wilhelmina Ziekenhuis | U120: 95 | V120: EUR | W120: 90 | X120: 1 | Y120: 95 | Z120: 00643169021563 | AA120: 80 | AB120: CAGE 6211604 PEEK ANATOMIC 16X14X4 | AC120: 90 | AD120: 3 | AE120: 95 | AF120: EA | AG120: 90 | AH120: 468,51 EUR | AI120: 90 | AJ120: 19/02/2026 | AK120: 95
A121: Order bevestiging 26-02818.pdf | B121: Purchase Order Confirmation | C121: extracted | D121: 46080.559 | E121: 88.03 | F121: 26 | G121: 2 | I121: mail - no.reply.customer.service@medtronic.com — Order bevestiging 26-02818 | J121: Dutch | K121: 2 | M121: 10 | N121: 26-02818 | O121: 75 | P121: 16/02/2026 | Q121: 90 | R121: Medtronic Trading NL BV | S121: 95 | T121: Canisius Wilhelmina Ziekenhuis | U121: 95 | V121: EUR | W121: 90 | X121: 2 | Y121: 95 | Z121: 00643169021556 | AA121: 80 | AB121: CAGE 6211605 PEEK ANATOMIC 16X14X5 | AC121: 90 | AD121: 1 | AE121: 95 | AF121: EA | AG121: 90 | AH121: 468,51 EUR | AI121: 90 | AJ121: 19/02/2026 | AK121: 95
A122: 3505026670 ESSITY Orderbevestiging.pdf | B122: Purchase Order Confirmation | C122: extracted | D122: 46080.559 | E122: 93.11 | F122: 13 | G122: 0 | I122: mail - tena.medical.cs.nl@essity.com — 3505026670 ESSITY Orderbevestiging | J122: Dutch | K122: 1 | L122: 3505026670 | M122: 96 | N122: 3004528520 | O122: 98 | P122: 12/02/2026 | Q122: 98 | R122: Essity Netherlands B.V. | S122: 95 | T122: Hospital Logistics Nederland b.v. | U122: 95 | V122: EUR | W122: 98 | X122: 20 | Y122: 98 | Z122: 729620 | AA122: 98 | AB122: TENA Flex Maxi L 3x22p. INT/NEU, NSW | AC122: 90 | AD122: 56 | AE122: 95 | AF122: TRP | AG122: 85 | AH122: 58,92 EUR / 100 PCS | AI122: 90 | AJ122: 18/02/2026 | AK122: 98
A123: Betreft_ Overzicht van nog te leveren Vygon producten.pdf | B123: Purchase Order Confirmation | C123: extracted | D123: 46080.559 | E123: 72.97 | F123: 13 | G123: 3 | I123: mail - infonl@vygon.com — Betreft: Overzicht van nog te leveren Vygon producten | J123: Dutch | K123: 1 | L123: 1507018668 | M123: 90 | N123: 0004965576 | O123: 80 | P123: 16/02/2026 | Q123: 95 | R123: VYGON NEDERLAND B.V. | S123: 95 | T123: Hospital Logistics Frisius MC Heeren | U123: 90 | W123: 10 | X123: 1 | Y123: 80 | Z123: 001361067 | AA123: 95 | AB123: NutriFit voedingssde 6Fr 50cm | AC123: 75 | AD123: 50 | AE123: 95 | AG123: 10 | AI123: 5 | AJ123: 27/02/2026 | AK123: 95
A124: 6507004827 ESSITY Order Ontvangstbevestiging.pdf | B124: Purchase Order Confirmation | C124: extracted | D124: 46080.559 | E124: 85.74 | F124: 13 | G124: 1 | I124: mail - tena.medical.cs.nl@essity.com — 6507004827 ESSITY Order Ontvangstbevestiging | J124: Dutch | K124: 1 | L124: 6507004827 | M124: 98 | N124: 3004542917 | O124: 98 | P124: 16/02/2026 | Q124: 98 | R124: Essity Netherlands B.V. | S124: 95 | T124: Hospital Logistics Nederland b.v. | U124: 95 | V124: EUR | W124: 95 | X124: 10 | Y124: 98 | Z124: 791467 | AA124: 98 | AB124: TENA Pants Normal S 4x15p, NEU, NSW, Ps | AC124: 90 | AD124: 2 | AE124: 85 | AF124: TRP | AG124: 70 | AH124: 35,46 EUR / 100 PCS | AI124: 85 | AK124: 60
A125: Order bevestiging 26-02818.pdf | B125: Purchase Order Confirmation | C125: extracted | D125: 46080.559 | E125: 83.34 | F125: 26 | G125: 2 | I125: mail - no.reply.customer.service@medtronic.com — Order bevestiging 26-02818 | J125: Dutch | K125: 1 | M125: 20 | N125: 6251707458 ZOR | O125: 95 | P125: 16/02/2026 | Q125: 92 | R125: Medtronic Trading NL BV | S125: 94 | T125: Canisius Wilhelmina Ziekenhuis | U125: 93 | V125: EUR | W125: 90 | X125: 1 | Y125: 80 | Z125: 10884521190665 / SYM2015F | AA125: 88 | AB125: SYM2015F ST EX THR 20X15CM X1 | AC125: 80 | AD125: 1 | AE125: 95 | AF125: EA | AG125: 92 | AH125: 527,77 | AI125: 92 | AJ125: 19/02/2026 | AK125: 93
A126: Order bevestiging 26-02818.pdf | B126: Purchase Order Confirmation | C126: extracted | D126: 46080.559 | E126: 83.34 | F126: 26 | G126: 2 | I126: mail - no.reply.customer.service@medtronic.com — Order bevestiging 26-02818 | J126: Dutch | K126: 2 | M126: 20 | N126: 6251707458 ZOR | O126: 95 | P126: 16/02/2026 | Q126: 92 | R126: Medtronic Trading NL BV | S126: 94 | T126: Canisius Wilhelmina Ziekenhuis | U126: 93 | V126: EUR | W126: 90 | X126: 2 | Y126: 80 | Z126: 00763000579234 / 1884012EM | AA126: 88 | AB126: BLADE 1884012EM RAD12 4MM M4 ROTATE ROHS | AC126: 85 | AD126: 1 | AE126: 95 | AF126: EA | AG126: 92 | AH126: 220,32 | AI126: 90 | AJ126: 19/02/2026 | AK126: 93
A127: Jouw Lyreco bestelling 1178683275 - 2505040761 is onderweg!.pdf | B127: Purchase Order Confirmation | C127: extracted | D127: 46080.559 | E127: 75 | F127: 0 | G127: 0 | I127: mail - customer.nl@lyreco.com — Jouw Lyreco bestelling 1178683275 - 2505040761 is onderweg! | J127: Dutch
A128: Bevestiging bestelling S09313444-1.pdf | B128: Purchase Order Confirmation | C128: extracted | D128: 46080.559 | E128: 89.62 | F128: 13 | G128: 0 | I128: mail - mail@kingbelgium.be — Bevestiging bestelling S09313444-1 | J128: Dutch | K128: 1 | L128: 6501017954 | M128: 98 | N128: S09313444-IRIS | O128: 95 | P128: 13/02/2026 | Q128: 95 | R128: King Belgium SA/NV | S128: 90 | T128: HOSPITAL LOGISTICS MAGAZIJN | U128: 92 | V128: EUR | W128: 95 | X128: 1 | Y128: 80 | Z128: 7567515450 | AA128: 92 | AB128: REFILL WRAPMASTER TOPPITS VERSHOUDOLFOLIE 45CMX300M - 6.5mu (3X1) | AC128: 90 | AD128: 1 | AE128: 95 | AF128: CS | AG128: 85 | AH128: 40,17 / CS | AI128: 90 | AJ128: 17/02/2026 | AK128: 95
A129: JAVA leveringsinformatie.pdf | B129: Purchase Order Confirmation | C129: extracted | D129: 46080.559 | E129: 78 | F129: 0 | G129: 0 | I129: mail - sligroout_noreply@sligro.nl — JAVA leveringsinformatie | J129: Dutch
A130: Verkooporder SO00454642 _ 3505026682.pdf | B130: Purchase Order Confirmation | C130: unclassified | D130: 46080.556 | E130: 65 | F130: 0 | G130: 0 | I130: mail - info@g3-medical.nl — Verkooporder SO00454642 / 3505026682
A131: Verkooporder SO00454641 _ 3505026682.pdf | B131: Purchase Order Confirmation | C131: extracted | D131: 46080.556 | E131: 81.4 | F131: 65 | G131: 0 | I131: mail - info@g3-medical.nl — Verkooporder SO00454641 / 3505026682 | J131: Dutch | K131: 1 | L131: 3505026682 | M131: 98 | N131: SO00454641 | O131: 95 | P131: 16/02/2026 | Q131: 95 | R131: G3 Medical B.V. | S131: 95 | T131: Hospital Logistics Nederland B.V./Maastricht UMC | U131: 88 | V131: EUR | W131: 95 | X131: 1 | Y131: 90 | Z131: 210057 | AA131: 96 | AB131: Grip Lok 3400L fixatiepleister, 60-13,0mm, large, steriel, 100x1st/ds | AC131: 88 | AD131: 3 | AE131: 96 | AF131: Dozen | AG131: 90 | AH131: 499,40 | AI131: 96 | AJ131: 19/02/2026 | AK131: 92
A132: Verkooporder SO00454641 _ 3505026682.pdf | B132: Purchase Order Confirmation | C132: extracted | D132: 46080.556 | E132: 81.4 | F132: 65 | G132: 0 | I132: mail - info@g3-medical.nl — Verkooporder SO00454641 / 3505026682 | J132: Dutch | K132: 2 | L132: 3505026682 | M132: 98 | N132: SO00454641 | O132: 50 | P132: 16/02/2026 | Q132: 50 | R132: G3 Medical B.V. | S132: 50 | T132: Hospital Logistics Nederland B.V./Maastricht UMC | U132: 50 | V132: EUR | W132: 50 | X132: 2 | Y132: 50 | Z132: 512028 | AA132: 96 | AB132: CuraSpon standaard, gelatine sponges, 80x50x10mm, steriel, 20x1st/ds | AC132: 87 | AD132: 2 | AE132: 95 | AF132: Dozen | AG132: 90 | AH132: 33,75 | AI132: 95 | AJ132: 19/02/2026 | AK132: 92
A133: Verkooporder SO00454641 _ 3505026682.pdf | B133: Purchase Order Confirmation | C133: extracted | D133: 46080.556 | E133: 81.4 | F133: 65 | G133: 0 | I133: mail - info@g3-medical.nl — Verkooporder SO00454641 / 3505026682 | J133: Dutch | K133: 3 | L133: 3505026682 | M133: 98 | N133: SO00454641 | O133: 50 | P133: 16/02/2026 | Q133: 50 | R133: G3 Medical B.V. | S133: 50 | T133: Hospital Logistics Nederland B.V./Maastricht UMC | U133: 50 | V133: EUR | W133: 50 | X133: 3 | Y133: 50 | Z133: 512025 | AA133: 96 | AB133: CuraSpon Cube, gelatine sponges, 10x10x10mm, steriel, 50x1st/ds | AC133: 87 | AD133: 11 | AE133: 95 | AF133: Dozen | AG133: 90 | AH133: 14,57 | AI133: 95 | AJ133: 19/02/2026 | AK133: 92
A134: Verkooporder SO00454641 _ 3505026682.pdf | B134: Purchase Order Confirmation | C134: extracted | D134: 46080.556 | E134: 81.4 | F134: 65 | G134: 0 | I134: mail - info@g3-medical.nl — Verkooporder SO00454641 / 3505026682 | J134: Dutch | K134: 4 | L134: 3505026682 | M134: 98 | N134: SO00454641 | O134: 50 | P134: 16/02/2026 | Q134: 50 | R134: G3 Medical B.V. | S134: 50 | T134: Hospital Logistics Nederland B.V./Maastricht UMC | U134: 50 | V134: EUR | W134: 50 | X134: 4 | Y134: 50 | Z134: 700167 | AA134: 96 | AB134: Ultrastop pro-med, 5ml, monodoses clinic, 30x5ml/ds | AC134: 88 | AD134: 5 | AE134: 95 | AF134: Dozen | AG134: 90 | AH134: 131,31 | AI134: 95 | AJ134: 19/02/2026 | AK134: 92
A135: Verkooporder SO00454641 _ 3505026682.pdf | B135: Purchase Order Confirmation | C135: extracted | D135: 46080.556 | E135: 81.4 | F135: 65 | G135: 0 | I135: mail - info@g3-medical.nl — Verkooporder SO00454641 / 3505026682 | J135: Dutch | K135: 5 | L135: 3505026682 | M135: 98 | N135: SO00454641 | O135: 50 | P135: 16/02/2026 | Q135: 50 | R135: G3 Medical B.V. | S135: 50 | T135: Hospital Logistics Nederland B.V./Maastricht UMC | U135: 50 | V135: EUR | W135: 50 | X135: 5 | Y135: 50 | Z135: 711038 | AA135: 96 | AB135: CMT drinkrietjes, flexibel plastic, wit, 21x0,6cm, 100x50st/zak, 5.000st/doos | AC135: 86 | AD135: 2 | AE135: 95 | AF135: Dozen | AG135: 90 | AH135: 45,74 | AI135: 95 | AJ135: 19/02/2026 | AK135: 92
A136: Verkooporder SO00454639 _ 3505026682.pdf | B136: Purchase Order Confirmation | C136: extracted | D136: 46080.556 | E136: 75.26 | F136: 65 | G136: 0 | I136: mail - info@g3-medical.nl — Verkooporder SO00454639 / 3505026682 | J136: Dutch | K136: 1 | L136: 3505026682 | M136: 50 | N136: SO00454639 | O136: 50 | P136: 16/02/2026 | Q136: 50 | R136: G3 Medical B.V. | S136: 50 | T136: Hospital Logistics Nederland B.V./Stichting | U136: 50 | V136: EUR | W136: 50 | X136: 1 | Y136: 50 | Z136: 700681 | AA136: 95 | AB136: Ultrastop flacon, 30ml, steriel, p/st | AC136: 90 | AD136: 10 | AE136: 95 | AF136: Stuks | AG136: 90 | AH136: 11,31 | AI136: 90 | AJ136: 19/02/2026 | AK136: 90
A137: Verkooporder SO00454639 _ 3505026682.pdf | B137: Purchase Order Confirmation | C137: extracted | D137: 46080.556 | E137: 75.26 | F137: 65 | G137: 0 | I137: mail - info@g3-medical.nl — Verkooporder SO00454639 / 3505026682 | J137: Dutch | K137: 2 | L137: 3505026682 | M137: 50 | N137: SO00454639 | O137: 50 | P137: 16/02/2026 | Q137: 50 | R137: G3 Medical B.V. | S137: 50 | T137: Hospital Logistics Nederland B.V./Stichting | U137: 50 | V137: EUR | W137: 50 | X137: 2 | Y137: 50 | Z137: 700658 | AA137: 95 | AB137: Wattenstok, disposable, pp, 15cm, 4mm tip, per 2 stuks, steriel, 250x2st/doos | AC137: 90 | AD137: 2 | AE137: 95 | AF137: Dozen | AG137: 90 | AH137: 69,83 | AI137: 90 | AJ137: 19/02/2026 | AK137: 90
A138: Verkooporder SO00454639 _ 3505026682.pdf | B138: Purchase Order Confirmation | C138: extracted | D138: 46080.556 | E138: 75.26 | F138: 65 | G138: 0 | I138: mail - info@g3-medical.nl — Verkooporder SO00454639 / 3505026682 | J138: Dutch | K138: 3 | L138: 3505026682 | M138: 50 | N138: SO00454639 | O138: 50 | P138: 16/02/2026 | Q138: 50 | R138: G3 Medical B.V. | S138: 50 | T138: Hospital Logistics Nederland B.V./Stichting | U138: 50 | V138: EUR | W138: 50 | X138: 3 | Y138: 50 | Z138: 410021 | AA138: 95 | AB138: Parker Signaspray 18-25 electrode solution & skin prep, 250ml, 12st/ds | AC138: 90 | AD138: 1 | AE138: 95 | AF138: Dozen | AG138: 90 | AH138: 62,49 | AI138: 90 | AJ138: 19/02/2026 | AK138: 90
A139: Verkooporder SO00454639 _ 3505026682.pdf | B139: Purchase Order Confirmation | C139: extracted | D139: 46080.556 | E139: 75.26 | F139: 65 | G139: 0 | I139: mail - info@g3-medical.nl — Verkooporder SO00454639 / 3505026682 | J139: Dutch | K139: 4 | L139: 3505026682 | M139: 50 | N139: SO00454639 | O139: 50 | P139: 16/02/2026 | Q139: 50 | R139: G3 Medical B.V. | S139: 50 | T139: Hospital Logistics Nederland B.V./Stichting | U139: 50 | V139: EUR | W139: 50 | X139: 4 | Y139: 50 | Z139: 700179 | AA139: 95 | AB139: Rolcentimeter, 150cm, p/st | AC139: 90 | AD139: 10 | AE139: 95 | AF139: Stuks | AG139: 90 | AH139: 2,74 | AI139: 90 | AJ139: 19/02/2026 | AK139: 90
A140: Verkooporder SO00454639 _ 3505026682.pdf | B140: Purchase Order Confirmation | C140: extracted | D140: 46080.556 | E140: 75.26 | F140: 65 | G140: 0 | I140: mail - info@g3-medical.nl — Verkooporder SO00454639 / 3505026682 | J140: Dutch | K140: 5 | L140: 3505026682 | M140: 50 | N140: SO00454639 | O140: 50 | P140: 16/02/2026 | Q140: 50 | R140: G3 Medical B.V. | S140: 50 | T140: Hospital Logistics Nederland B.V./Stichting | U140: 50 | V140: EUR | W140: 50 | X140: 5 | Y140: 50 | Z140: 700005 | AA140: 95 | AB140: CMT stuwband, disposable, blauw, p/st | AC140: 90 | AD140: 1 | AE140: 95 | AF140: Stuks | AG140: 90 | AH140: 3,06 | AI140: 90 | AJ140: 19/02/2026 | AK140: 90
A141: Verkooporder SO00454644 _ 3507009728.pdf | B141: Purchase Order Confirmation | C141: unclassified | D141: 46080.556 | E141: 62 | F141: 0 | G141: 0 | I141: mail - info@g3-medical.nl — Verkooporder SO00454644 / 3507009728
A142: RE_ RE_ Teleflex Orderbevestiging 1504025864 and 13995843.pdf | B142: Purchase Order Confirmation | C142: unclassified | D142: 46080.556 | E142: 68 | F142: 0 | G142: 0 | I142: mail - order.nl@teleflex.com — RE: RE: Teleflex Orderbevestiging 1504025864 and 13995843
A143: Lyreco orderbevestiging 167912161-16022026-0006.pdf | B143: Purchase Order Confirmation | C143: extracted | D143: 46080.556 | E143: 79.86 | F143: 13 | G143: 2 | I143: mail - noreply@lyreco.com — Lyreco orderbevestiging 167912161-16022026-0006 | J143: Dutch | K143: 1 | L143: 2501210303 | M143: 90 | N143: 167912161 | O143: 85 | P143: 16/02/2026 | Q143: 95 | R143: Lyreco Belgium SA/NV | S143: 95 | T143: Hospital Logistics Aarschot | U143: 90 | V143: EUR | W143: 95 | X143: 1 | Y143: 70 | Z143: 1.861.945 | AA143: 85 | AB143: Besteld door Hospital Logistics DS100 MAIL TUFF ENV 180X260 WIT | AC143: 85 | AD143: 3 | AE143: 90 | AG143: 25 | AH143: 16,92 | AI143: 90 | AK143: 20
A144: Orderbevestiging C007-S2607585-1.pdf | B144: Purchase Order Confirmation | C144: extracted | D144: 46080.538 | E144: 79.78 | F144: 156 | G144: 0 | I144: mail - orders.be@duomed.com — Orderbevestiging C007-S2607585-1 | J144: Dutch | K144: 1 | L144: 3501022495 | M144: 98 | N144: C007-S2607585-1 | O144: 95 | P144: 16/02/2026 | Q144: 96 | R144: Duomed Belgium NV/SA | S144: 90 | T144: Hospital Logistics | U144: 92 | V144: EUR | W144: 95 | X144: 1 | Y144: 90 | Z144: DCC8007 | AA144: 94 | AB144: Fairmont medical camera cover + adaptor drape | AC144: 92 | AD144: 2 | AE144: 93 | AF144: B40 | AG144: 80 | AH144: 418,26 | AI144: 94 | AJ144: 17/02/2026 | AK144: 96
A145: Orderbevestiging C007-S2607585-1.pdf | B145: Purchase Order Confirmation | C145: extracted | D145: 46080.538 | E145: 79.78 | F145: 156 | G145: 0 | I145: mail - orders.be@duomed.com — Orderbevestiging C007-S2607585-1 | J145: Dutch | K145: 2 | L145: 3501022495 | M145: 50 | N145: C007-S2607585-1 | O145: 50 | P145: 16/02/2026 | Q145: 50 | R145: Duomed Belgium NV/SA | S145: 50 | T145: Hospital Logistics | U145: 50 | V145: EUR | W145: 50 | X145: 2 | Y145: 50 | Z145: 01.3300 | AA145: 94 | AB145: Securo-Reservoir 150ml, Sterile | AC145: 92 | AD145: 4 | AE145: 92 | AF145: B5 | AG145: 80 | AH145: 141,89 | AI145: 93 | AJ145: 19/02/2026 | AK145: 95
A146: Orderbevestiging C007-S2607585-1.pdf | B146: Purchase Order Confirmation | C146: extracted | D146: 46080.538 | E146: 79.78 | F146: 156 | G146: 0 | I146: mail - orders.be@duomed.com — Orderbevestiging C007-S2607585-1 | J146: Dutch | K146: 3 | L146: 3501022495 | M146: 50 | N146: C007-S2607585-1 | O146: 50 | P146: 16/02/2026 | Q146: 50 | R146: Duomed Belgium NV/SA | S146: 50 | T146: Hospital Logistics | U146: 50 | V146: EUR | W146: 50 | X146: 3 | Y146: 50 | Z146: 0185ND | AA146: 94 | AB146: Inflation Device 30Ml/30Bar | AC146: 92 | AD146: 6 | AE146: 92 | AF146: B6 | AG146: 80 | AH146: 249,46 | AI146: 93 | AJ146: 19/02/2026 | AK146: 95
A147: Orderbevestiging C007-S2607585-1.pdf | B147: Purchase Order Confirmation | C147: extracted | D147: 46080.538 | E147: 79.78 | F147: 156 | G147: 0 | I147: mail - orders.be@duomed.com — Orderbevestiging C007-S2607585-1 | J147: Dutch | K147: 4 | L147: 3501022495 | M147: 50 | N147: C007-S2607585-1 | O147: 50 | P147: 16/02/2026 | Q147: 50 | R147: Duomed Belgium NV/SA | S147: 50 | T147: Hospital Logistics | U147: 50 | V147: EUR | W147: 50 | X147: 4 | Y147: 50 | Z147: 330048070 | AA147: 94 | AB147: Gammex Latex 7 | AC147: 92 | AD147: 2 | AE147: 92 | AF147: B200 | AG147: 80 | AH147: 148,48 | AI147: 93 | AJ147: 19/02/2026 | AK147: 95
A148: Orderbevestiging C007-S2607585-1.pdf | B148: Purchase Order Confirmation | C148: extracted | D148: 46080.538 | E148: 79.78 | F148: 156 | G148: 0 | I148: mail - orders.be@duomed.com — Orderbevestiging C007-S2607585-1 | J148: Dutch | K148: 5 | L148: 3501022495 | M148: 50 | N148: C007-S2607585-1 | O148: 50 | P148: 16/02/2026 | Q148: 50 | R148: Duomed Belgium NV/SA | S148: 50 | T148: Hospital Logistics | U148: 50 | V148: EUR | W148: 50 | X148: 5 | Y148: 50 | Z148: 330048065 | AA148: 94 | AB148: Gammex Latex 6,5 | AC148: 92 | AD148: 2 | AE148: 92 | AF148: B200 | AG148: 80 | AH148: 148,48 | AI148: 93 | AJ148: 19/02/2026 | AK148: 95
A149: Orderbevestiging C007-S2607585-1.pdf | B149: Purchase Order Confirmation | C149: extracted | D149: 46080.538 | E149: 79.78 | F149: 156 | G149: 0 | I149: mail - orders.be@duomed.com — Orderbevestiging C007-S2607585-1 | J149: Dutch | K149: 6 | L149: 3501022495 | M149: 50 | N149: C007-S2607585-1 | O149: 50 | P149: 16/02/2026 | Q149: 50 | R149: Duomed Belgium NV/SA | S149: 50 | T149: Hospital Logistics | U149: 50 | V149: EUR | W149: 50 | X149: 6 | Y149: 50 | Z149: 330048060 | AA149: 94 | AB149: Gammex Latex 6 | AC149: 92 | AD149: 1 | AE149: 92 | AF149: B200 | AG149: 80 | AH149: 148,48 | AI149: 93 | AJ149: 19/02/2026 | AK149: 95
A150: Orderbevestiging C007-S2607585-1.pdf | B150: Purchase Order Confirmation | C150: extracted | D150: 46080.538 | E150: 79.78 | F150: 156 | G150: 0 | I150: mail - orders.be@duomed.com — Orderbevestiging C007-S2607585-1 | J150: Dutch | K150: 7 | L150: 3501022495 | M150: 50 | N150: C007-S2607585-1 | O150: 50 | P150: 16/02/2026 | Q150: 50 | R150: Duomed Belgium NV/SA | S150: 50 | T150: Hospital Logistics | U150: 50 | V150: EUR | W150: 50 | X150: 7 | Y150: 50 | Z150: SOL.50.02.38 | AA150: 94 | AB150: Afsluitdop M/F Combi Rood Pvc-Vrij (Pad Verp) | AC150: 91 | AD150: 1 | AE150: 92 | AF150: B5000 | AG150: 80 | AH150: 267,92 | AI150: 94 | AJ150: 19/02/2026 | AK150: 95
A151: Orderbevestiging C007-S2607585-1.pdf | B151: Purchase Order Confirmation | C151: extracted | D151: 46080.538 | E151: 79.78 | F151: 156 | G151: 0 | I151: mail - orders.be@duomed.com — Orderbevestiging C007-S2607585-1 | J151: Dutch | K151: 8 | L151: 3501022495 | M151: 50 | N151: C007-S2607585-1 | O151: 50 | P151: 16/02/2026 | Q151: 50 | R151: Duomed Belgium NV/SA | S151: 50 | T151: Hospital Logistics | U151: 50 | V151: EUR | W151: 50 | X151: 8 | Y151: 50 | Z151: PAL-1200 | AA151: 94 | AB151: PAL Aspiration Tubing Set, 12Ft, Disposable, Sterile | AC151: 92 | AD151: 3 | AE151: 92 | AF151: B5 | AG151: 80 | AH151: 172,99 | AI151: 93 | AJ151: 19/02/2026 | AK151: 95
A152: Orderbevestiging C007-S2607585-1.pdf | B152: Purchase Order Confirmation | C152: extracted | D152: 46080.538 | E152: 79.78 | F152: 156 | G152: 0 | I152: mail - orders.be@duomed.com — Orderbevestiging C007-S2607585-1 | J152: Dutch | K152: 9 | L152: 3501022495 | M152: 50 | N152: C007-S2607585-1 | O152: 50 | P152: 16/02/2026 | Q152: 50 | R152: Duomed Belgium NV/SA | S152: 50 | T152: Hospital Logistics | U152: 50 | V152: EUR | W152: 50 | X152: 9 | Y152: 50 | Z152: 34145 | AA152: 94 | AB152: Halyard Quick Check H400 121x121cm | AC152: 92 | AD152: 30 | AE152: 92 | AF152: B48 | AG152: 80 | AH152: 51,21 | AI152: 93 | AJ152: 19/02/2026 | AK152: 95
A153: Orderbevestiging C007-S2607585-1.pdf | B153: Purchase Order Confirmation | C153: extracted | D153: 46080.538 | E153: 79.78 | F153: 156 | G153: 0 | I153: mail - orders.be@duomed.com — Orderbevestiging C007-S2607585-1 | J153: Dutch | K153: 10 | L153: 3501022495 | M153: 50 | N153: C007-S2607585-1 | O153: 50 | P153: 16/02/2026 | Q153: 50 | R153: Duomed Belgium NV/SA | S153: 50 | T153: Hospital Logistics | U153: 50 | V153: EUR | W153: 50 | X153: 10 | Y153: 50 | Z153: 553304 | AA153: 94 | AB153: Latex Onderzoekshands Mct Coated Nt.Gep. Large | AC153: 92 | AD153: 2 | AE153: 92 | AF153: B1000 | AG153: 80 | AH153: 69,59 | AI153: 93 | AJ153: 19/02/2026 | AK153: 95
A154: Orderbevestiging C007-S2607585-1.pdf | B154: Purchase Order Confirmation | C154: extracted | D154: 46080.538 | E154: 79.78 | F154: 156 | G154: 0 | I154: mail - orders.be@duomed.com — Orderbevestiging C007-S2607585-1 | J154: Dutch | K154: 11 | L154: 3501022495 | M154: 50 | N154: C007-S2607585-1 | O154: 50 | P154: 16/02/2026 | Q154: 50 | R154: Duomed Belgium NV/SA | S154: 50 | T154: Hospital Logistics | U154: 50 | V154: EUR | W154: 50 | X154: 11 | Y154: 50 | Z154: OM-1125-8 | AA154: 94 | AB154: "Oxymask With 7"" Oxygen Tubing" | AC154: 90 | AD154: 3 | AE154: 92 | AF154: B25 | AG154: 80 | AH154: 86,64 | AI154: 93 | AJ154: 19/02/2026 | AK154: 95
A155: Orderbevestiging C007-S2607585-1.pdf | B155: Purchase Order Confirmation | C155: extracted | D155: 46080.538 | E155: 79.78 | F155: 156 | G155: 0 | I155: mail - orders.be@duomed.com — Orderbevestiging C007-S2607585-1 | J155: Dutch | K155: 12 | L155: 3501022495 | M155: 50 | N155: C007-S2607585-1 | O155: 50 | P155: 16/02/2026 | Q155: 50 | R155: Duomed Belgium NV/SA | S155: 50 | T155: Hospital Logistics | U155: 50 | V155: EUR | W155: 50 | X155: 12 | Y155: 50 | Z155: 34175 | AA155: 94 | AB155: Halyard Quick Check H200 76x76cm | AC155: 92 | AD155: 3 | AE155: 92 | AF155: B144 | AG155: 80 | AH155: 55,14 | AI155: 93 | AJ155: 19/02/2026 | AK155: 95
... A158: Bevestiging bestelling S09313928-1.pdf | B158: Purchase Order Confirmation | C158: extracted | D158: 46080.537 | E158: 90.31 | F158: 26 | G158: 0 | I158: mail - mail@kingbelgium.be — Bevestiging bestelling S09313928-1 | J158: Dutch | K158: 2 | L158: 2501201307 | M158: 98 | N158: S09313928-IRIS | O158: 95 | P158: 16/02/2026 | Q158: 95 | R158: King Belgium SA/NV | S158: 90 | T158: HOSPITAL LOGISTICS MAGAZIJN | U158: 92 | V158: EUR | W158: 95 | X158: 2 | Y158: 90 | Z158: 688162220 | AA158: 90 | AB158: SLABBETJE PRIMECARE+ 2LGS MET ZAK BINNEN BLAUW 38X70CM (6X100) | AC158: 86 | AD158: 2 | AE158: 95 | AF158: CS | AG158: 90 | AH158: 56,40 / CS | AI158: 92 | AJ158: 18/02/2026 | AK158: 96
A159: RE_ order 1501037263.pdf | C159: unclassified | D159: 46080.531 | E159: 24 | F159: 0 | G159: 0 | I159: mail - vygonbe@vygon.com — RE: order 1501037263
A160: Mediq orderbevestiging_ 1507018696.pdf | B160: Purchase Order Confirmation | C160: extracted | D160: 46080.531 | E160: 91.51 | F160: 13 | G160: 0 | I160: mail - CSZiekenhuizen@mediq.com — Mediq orderbevestiging: 1507018696 | J160: Dutch | K160: 1 | L160: 1507018696 | M160: 98 | N160: 4381838 | O160: 95 | P160: 16/02/2026 | Q160: 95 | R160: Mediq Nederland B.V. | S160: 90 | T160: Hospital Logistics Nederland B.V. | U160: 90 | V160: EUR | W160: 95 | X160: 1 | Y160: 90 | Z160: 3016535 | AA160: 98 | AB160: KLINIDERM FOAM SILICONE BORDER 7,5X7,5CM STERIEL 40514828 | AC160: 95 | AD160: 22 | AE160: 90 | AF160: BD | AG160: 70 | AH160: 18,01 EUR | AI160: 95 | AJ160: 19/02/2026 | AK160: 95
...

Sheet Pivot
A3: File Name | B3: Document Type | C3: Status | D3: Count of Line Item # | E3: Count of Purchase Order Number | F3: Count of Supplier Order Number | G3: Count of Order Date | H3: Count of Supplier Name | I3: Count of Customer Name | J3: Count of Currency | K3: Count of Article Number | L3: Count of Item Description | M3: Count of Quantity | N3: Count of Unit of Measure | O3: Count of Unit Price | P3: Count of Item Planned Delivery Date | Q3: % of Purchase Order Number | R3: % of Supplier Order Number | S3: % of Order Date | T3: % of Supplier Name | U3: % of Customer Name | V3: % of Currency | W3: % of Article Number | X3: % of Item Description | Y3: % of Quantity | Z3: % of Unit of Measure | AA3: % of Unit Price | AB3: % of Item Planned Delivery Date
A4: _ Orderbevestiging 1501037327.pdf | B4: Purchase Order Confirmation | C4: extracted | D4: 1 | E4: 1 | F4: 1 | G4: 1 | H4: 1 | I4: 1 | J4: 1 | K4: 1 | L4: 1 | M4: 1 | N4: 1 | O4: 1 | P4: 1 | Q4: =GETPIVOTDATA("Count of Line Item #",$A$3,"File Name",$A4)/GETPIVOTDATA("Count of Purchase Order Number",$A$3,"File Name",$A4) -> 1 | R4: =GETPIVOTDATA("Count of Line Item #",$A$3,"File Name",$A4)/GETPIVOTDATA("Count of Supplier Order Number",$A$3,"File Name",$A4) -> 1 | S4: =GETPIVOTDATA("Count of Line Item #",$A$3,"File Name",$A4)/GETPIVOTDATA("Count of Order Date",$A$3,"File Name",$A4) -> 1 | T4: =GETPIVOTDATA("Count of Line Item #",$A$3,"File Name",$A4)/GETPIVOTDATA("Count of Supplier Name",$A$3,"File Name",$A4) -> 1 | U4: =GETPIVOTDATA("Count of Line Item #",$A$3,"File Name",$A4)/GETPIVOTDATA("Count of Customer Name",$A$3,"File Name",$A4) -> 1 | V4: =GETPIVOTDATA("Count of Line Item #",$A$3,"File Name",$A4)/GETPIVOTDATA("Count of Currency",$A$3,"File Name",$A4) -> 1 | W4: =GETPIVOTDATA("Count of Line Item #",$A$3,"File Name",$A4)/GETPIVOTDATA("Count of Article Number",$A$3,"File Name",$A4) -> 1 | X4: =GETPIVOTDATA("Count of Line Item #",$A$3,"File Name",$A4)/GETPIVOTDATA("Count of Item Description",$A$3,"File Name",$A4) -> 1 | Y4: =GETPIVOTDATA("Count of Line Item #",$A$3,"File Name",$A4)/GETPIVOTDATA("Count of Quantity",$A$3,"File Name",$A4) -> 1 | Z4: =GETPIVOTDATA("Count of Line Item #",$A$3,"File Name",$A4)/GETPIVOTDATA("Count of Unit of Measure",$A$3,"File Name",$A4) -> 1 | AA4: =GETPIVOTDATA("Count of Line Item #",$A$3,"File Name",$A4)/GETPIVOTDATA("Count of Unit Price",$A$3,"File Name",$A4) -> 1 | AB4: =GETPIVOTDATA("Count of Item Planned Delivery Date",$A$3,"File Name",$A4)/GETPIVOTDATA("Count of Line Item #",$A$3,"File Name",$A4) -> 1
A5: _ Orderbevestiging 1504026582.pdf | B5: Purchase Order Confirmation | C5: extracted | D5: 1 | E5: 1 | F5: 1 | G5: 1 | H5: 1 | I5: 1 | J5: 1 | K5: 1 | L5: 1 | M5: 1 | N5: 1 | O5: 1 | P5: 1 | Q5: =GETPIVOTDATA("Count of Line Item #",$A$3,"File Name",$A5)/GETPIVOTDATA("Count of Purchase Order Number",$A$3,"File Name",$A5) -> 1 | R5: =GETPIVOTDATA("Count of Line Item #",$A$3,"File Name",$A5)/GETPIVOTDATA("Count of Supplier Order Number",$A$3,"File Name",$A5) -> 1 | S5: =GETPIVOTDATA("Count of Line Item #",$A$3,"File Name",$A5)/GETPIVOTDATA("Count of Order Date",$A$3,"File Name",$A5) -> 1 | T5: =GETPIVOTDATA("Count of Line Item #",$A$3,"File Name",$A5)/GETPIVOTDATA("Count of Supplier Name",$A$3,"File Name",$A5) -> 1 | U5: =GETPIVOTDATA("Count of Line Item #",$A$3,"File Name",$A5)/GETPIVOTDATA("Count of Customer Name",$A$3,"File Name",$A5) -> 1 | V5: =GETPIVOTDATA("Count of Line Item #",$A$3,"File Name",$A5)/GETPIVOTDATA("Count of Currency",$A$3,"File Name",$A5) -> 1 | W5: =GETPIVOTDATA("Count of Line Item #",$A$3,"File Name",$A5)/GETPIVOTDATA("Count of Article Number",$A$3,"File Name",$A5) -> 1 | X5: =GETPIVOTDATA("Count of Line Item #",$A$3,"File Name",$A5)/GETPIVOTDATA("Count of Item Description",$A$3,"File Name",$A5) -> 1 | Y5: =GETPIVOTDATA("Count of Line Item #",$A$3,"File Name",$A5)/GETPIVOTDATA("Count of Quantity",$A$3,"File Name",$A5) -> 1 | Z5: =GETPIVOTDATA("Count of Line Item #",$A$3,"File Name",$A5)/GETPIVOTDATA("Count of Unit of Measure",$A$3,"File Name",$A5) -> 1 | AA5: =GETPIVOTDATA("Count of Line Item #",$A$3,"File Name",$A5)/GETPIVOTDATA("Count of Unit Price",$A$3,"File Name",$A5) -> 1 | AB5: =GETPIVOTDATA("Count of Item Planned Delivery Date",$A$3,"File Name",$A5)/GETPIVOTDATA("Count of Line Item #",$A$3,"File Name",$A5) -> 1
A6: _ Orderbevestiging 1505040022.pdf | B6: Purchase Order Confirmation | C6: extracted | D6: 2 | E6: 2 | F6: 2 | G6: 2 | H6: 2 | I6: 2 | J6: 2 | K6: 2 | L6: 2 | M6: 2 | N6: 2 | O6: 2 | P6: 2 | Q6: =GETPIVOTDATA("Count of Line Item #",$A$3,"File Name",$A6)/GETPIVOTDATA("Count of Purchase Order Number",$A$3,"File Name",$A6) -> 1 | R6: =GETPIVOTDATA("Count of Line Item #",$A$3,"File Name",$A6)/GETPIVOTDATA("Count of Supplier Order Number",$A$3,"File Name",$A6) -> 1 | S6: =GETPIVOTDATA("Count of Line Item #",$A$3,"File Name",$A6)/GETPIVOTDATA("Count of Order Date",$A$3,"File Name",$A6) -> 1 | T6: =GETPIVOTDATA("Count of Line Item #",$A$3,"File Name",$A6)/GETPIVOTDATA("Count of Supplier Name",$A$3,"File Name",$A6) -> 1 | U6: =GETPIVOTDATA("Count of Line Item #",$A$3,"File Name",$A6)/GETPIVOTDATA("Count of Customer Name",$A$3,"File Name",$A6) -> 1 | V6: =GETPIVOTDATA("Count of Line Item #",$A$3,"File Name",$A6)/GETPIVOTDATA("Count of Currency",$A$3,"File Name",$A6) -> 1 | W6: =GETPIVOTDATA("Count of Line Item #",$A$3,"File Name",$A6)/GETPIVOTDATA("Count of Article Number",$A$3,"File Name",$A6) -> 1 | X6: =GETPIVOTDATA("Count of Line Item #",$A$3,"File Name",$A6)/GETPIVOTDATA("Count of Item Description",$A$3,"File Name",$A6) -> 1 | Y6: =GETPIVOTDATA("Count of Line Item #",$A$3,"File Name",$A6)/GETPIVOTDATA("Count of Quantity",$A$3,"File Name",$A6) -> 1 | Z6: =GETPIVOTDATA("Count of Line Item #",$A$3,"File Name",$A6)/GETPIVOTDATA("Count of Unit of Measure",$A$3,"File Name",$A6) -> 1 | AA6: =GETPIVOTDATA("Count of Line Item #",$A$3,"File Name",$A6)/GETPIVOTDATA("Count of Unit Price",$A$3,"File Name",$A6) -> 1 | AB6: =GETPIVOTDATA("Count of Item Planned Delivery Date",$A$3,"File Name",$A6)/GETPIVOTDATA("Count of Line Item #",$A$3,"File Name",$A6) -> 1
A7: _ Orderbevestiging 3504015911.pdf | B7: Purchase Order Confirmation | C7: extracted | D7: 21 | E7: 21 | F7: 21 | G7: 21 | H7: 21 | I7: 21 | J7: 21 | K7: 21 | L7: 21 | M7: 21 | N7: 21 | O7: 21 | P7: 21 | Q7: =GETPIVOTDATA("Count of Line Item #",$A$3,"File Name",$A7)/GETPIVOTDATA("Count of Purchase Order Number",$A$3,"File Name",$A7) -> 1 | R7: =GETPIVOTDATA("Count of Line Item #",$A$3,"File Name",$A7)/GETPIVOTDATA("Count of Supplier Order Number",$A$3,"File Name",$A7) -> 1 | S7: =GETPIVOTDATA("Count of Line Item #",$A$3,"File Name",$A7)/GETPIVOTDATA("Count of Order Date",$A$3,"File Name",$A7) -> 1 | T7: =GETPIVOTDATA("Count of Line Item #",$A$3,"File Name",$A7)/GETPIVOTDATA("Count of Supplier Name",$A$3,"File Name",$A7) -> 1 | U7: =GETPIVOTDATA("Count of Line Item #",$A$3,"File Name",$A7)/GETPIVOTDATA("Count of Customer Name",$A$3,"File Name",$A7) -> 1 | V7: =GETPIVOTDATA("Count of Line Item #",$A$3,"File Name",$A7)/GETPIVOTDATA("Count of Currency",$A$3,"File Name",$A7) -> 1 | W7: =GETPIVOTDATA("Count of Line Item #",$A$3,"File Name",$A7)/GETPIVOTDATA("Count of Article Number",$A$3,"File Name",$A7) -> 1 | X7: =GETPIVOTDATA("Count of Line Item #",$A$3,"File Name",$A7)/GETPIVOTDATA("Count of Item Description",$A$3,"File Name",$A7) -> 1 | Y7: =GETPIVOTDATA("Count of Line Item #",$A$3,"File Name",$A7)/GETPIVOTDATA("Count of Quantity",$A$3,"File Name",$A7) -> 1 | Z7: =GETPIVOTDATA("Count of Line Item #",$A$3,"File Name",$A7)/GETPIVOTDATA("Count of Unit of Measure",$A$3,"File Name",$A7) -> 1 | AA7: =GETPIVOTDATA("Count of Line Item #",$A$3,"File Name",$A7)/GETPIVOTDATA("Count of Unit Price",$A$3,"File Name",$A7) -> 1 | AB7: =GETPIVOTDATA("Count of Item Planned Delivery Date",$A$3,"File Name",$A7)/GETPIVOTDATA("Count of Line Item #",$A$3,"File Name",$A7) -> 1
A8: _ Orderbevestiging 3505026677.pdf | B8: Purchase Order Confirmation | C8: extracted | D8: 2 | E8: 2 | F8: 2 | G8: 2 | H8: 2 | I8: 2 | J8: 2 | K8: 2 | L8: 2 | M8: 2 | N8: 2 | O8: 2 | P8: 2 | Q8: =GETPIVOTDATA("Count of Line Item #",$A$3,"File Name",$A8)/GETPIVOTDATA("Count of Purchase Order Number",$A$3,"File Name",$A8) -> 1 | R8: =GETPIVOTDATA("Count of Line Item #",$A$3,"File Name",$A8)/GETPIVOTDATA("Count of Supplier Order Number",$A$3,"File Name",$A8) -> 1 | S8: =GETPIVOTDATA("Count of Line Item #",$A$3,"File Name",$A8)/GETPIVOTDATA("Count of Order Date",$A$3,"File Name",$A8) -> 1 | T8: =GETPIVOTDATA("Count of Line Item #",$A$3,"File Name",$A8)/GETPIVOTDATA("Count of Supplier Name",$A$3,"File Name",$A8) -> 1 | U8: =GETPIVOTDATA("Count of Line Item #",$A$3,"File Name",$A8)/GETPIVOTDATA("Count of Customer Name",$A$3,"File Name",$A8) -> 1 | V8: =GETPIVOTDATA("Count of Line Item #",$A$3,"File Name",$A8)/GETPIVOTDATA("Count of Currency",$A$3,"File Name",$A8) -> 1 | W8: =GETPIVOTDATA("Count of Line Item #",$A$3,"File Name",$A8)/GETPIVOTDATA("Count of Article Number",$A$3,"File Name",$A8) -> 1 | X8: =GETPIVOTDATA("Count of Line Item #",$A$3,"File Name",$A8)/GETPIVOTDATA("Count of Item Description",$A$3,"File Name",$A8) -> 1 | Y8: =GETPIVOTDATA("Count of Line Item #",$A$3,"File Name",$A8)/GETPIVOTDATA("Count of Quantity",$A$3,"File Name",$A8) -> 1 | Z8: =GETPIVOTDATA("Count of Line Item #",$A$3,"File Name",$A8)/GETPIVOTDATA("Count of Unit of Measure",$A$3,"File Name",$A8) -> 1 | AA8: =GETPIVOTDATA("Count of Line Item #",$A$3,"File Name",$A8)/GETPIVOTDATA("Count of Unit Price",$A$3,"File Name",$A8) -> 1 | AB8: =GETPIVOTDATA("Count of Item Planned Delivery Date",$A$3,"File Name",$A8)/GETPIVOTDATA("Count of Line Item #",$A$3,"File Name",$A8) -> 1
A9: 100142673 HL WZC Herinnering Sligro [#KM-6720322] [#RL-144746].pdf | B9: (blank) | C9: unclassified | Q9: =GETPIVOTDATA("Count of Line Item #",$A$3,"File Name",$A9)/GETPIVOTDATA("Count of Purchase Order Number",$A$3,"File Name",$A9) -> #DIV/0! | R9: =GETPIVOTDATA("Count of Line Item #",$A$3,"File Name",$A9)/GETPIVOTDATA("Count of Supplier Order Number",$A$3,"File Name",$A9) -> #DIV/0! | S9: =GETPIVOTDATA("Count of Line Item #",$A$3,"File Name",$A9)/GETPIVOTDATA("Count of Order Date",$A$3,"File Name",$A9) -> #DIV/0! | T9: =GETPIVOTDATA("Count of Line Item #",$A$3,"File Name",$A9)/GETPIVOTDATA("Count of Supplier Name",$A$3,"File Name",$A9) -> #DIV/0! | U9: =GETPIVOTDATA("Count of Line Item #",$A$3,"File Name",$A9)/GETPIVOTDATA("Count of Customer Name",$A$3,"File Name",$A9) -> #DIV/0! | V9: =GETPIVOTDATA("Count of Line Item #",$A$3,"File Name",$A9)/GETPIVOTDATA("Count of Currency",$A$3,"File Name",$A9) -> #DIV/0! | W9: =GETPIVOTDATA("Count of Line Item #",$A$3,"File Name",$A9)/GETPIVOTDATA("Count of Article Number",$A$3,"File Name",$A9) -> #DIV/0! | X9: =GETPIVOTDATA("Count of Line Item #",$A$3,"File Name",$A9)/GETPIVOTDATA("Count of Item Description",$A$3,"File Name",$A9) -> #DIV/0! | Y9: =GETPIVOTDATA("Count of Line Item #",$A$3,"File Name",$A9)/GETPIVOTDATA("Count of Quantity",$A$3,"File Name",$A9) -> #DIV/0! | Z9: =GETPIVOTDATA("Count of Line Item #",$A$3,"File Name",$A9)/GETPIVOTDATA("Count of Unit of Measure",$A$3,"File Name",$A9) -> #DIV/0! | AA9: =GETPIVOTDATA("Count of Line Item #",$A$3,"File Name",$A9)/GETPIVOTDATA("Count of Unit Price",$A$3,"File Name",$A9) -> #DIV/0! | AB9: =GETPIVOTDATA("Count of Item Planned Delivery Date",$A$3,"File Name",$A9)/GETPIVOTDATA("Count of Line Item #",$A$3,"File Name",$A9) -> #DIV/0!
A10: 2501209992 ESSITY Orderbevestiging.pdf | B10: Purchase Order Confirmation | C10: extracted | D10: 2 | E10: 2 | F10: 2 | G10: 2 | H10: 2 | I10: 2 | J10: 2 | K10: 2 | L10: 2 | M10: 2 | N10: 2 | O10: 1 | P10: 2 | Q10: =GETPIVOTDATA("Count of Line Item #",$A$3,"File Name",$A10)/GETPIVOTDATA("Count of Purchase Order Number",$A$3,"File Name",$A10) -> 1 | R10: =GETPIVOTDATA("Count of Line Item #",$A$3,"File Name",$A10)/GETPIVOTDATA("Count of Supplier Order Number",$A$3,"File Name",$A10) -> 1 | S10: =GETPIVOTDATA("Count of Line Item #",$A$3,"File Name",$A10)/GETPIVOTDATA("Count of Order Date",$A$3,"File Name",$A10) -> 1 | T10: =GETPIVOTDATA("Count of Line Item #",$A$3,"File Name",$A10)/GETPIVOTDATA("Count of Supplier Name",$A$3,"File Name",$A10) -> 1 | U10: =GETPIVOTDATA("Count of Line Item #",$A$3,"File Name",$A10)/GETPIVOTDATA("Count of Customer Name",$A$3,"File Name",$A10) -> 1 | V10: =GETPIVOTDATA("Count of Line Item #",$A$3,"File Name",$A10)/GETPIVOTDATA("Count of Currency",$A$3,"File Name",$A10) -> 1 | W10: =GETPIVOTDATA("Count of Line Item #",$A$3,"File Name",$A10)/GETPIVOTDATA("Count of Article Number",$A$3,"File Name",$A10) -> 1 | X10: =GETPIVOTDATA("Count of Line Item #",$A$3,"File Name",$A10)/GETPIVOTDATA("Count of Item Description",$A$3,"File Name",$A10) -> 1 | Y10: =GETPIVOTDATA("Count of Line Item #",$A$3,"File Name",$A10)/GETPIVOTDATA("Count of Quantity",$A$3,"File Name",$A10) -> 1 | Z10: =GETPIVOTDATA("Count of Line Item #",$A$3,"File Name",$A10)/GETPIVOTDATA("Count of Unit of Measure",$A$3,"File Name",$A10) -> 1 | AA10: =GETPIVOTDATA("Count of Line Item #",$A$3,"File Name",$A10)/GETPIVOTDATA("Count of Unit Price",$A$3,"File Name",$A10) -> 2 | AB10: =GETPIVOTDATA("Count of Item Planned Delivery Date",$A$3,"File Name",$A10)/GETPIVOTDATA("Count of Line Item #",$A$3,"File Name",$A10) -> 1
A11: 2505040799 ESSITY Order Ontvangstbevestiging.pdf | B11: Purchase Order Confirmation | C11: extracted | D11: 1 | E11: 1 | F11: 1 | G11: 1 | H11: 1 | I11: 1 | J11: 1 | K11: 1 | L11: 1 | M11: 1 | N11: 1 | O11: 1 | Q11: =GETPIVOTDATA("Count of Line Item #",$A$3,"File Name",$A11)/GETPIVOTDATA("Count of Purchase Order Number",$A$3,"File Name",$A11) -> 1 | R11: =GETPIVOTDATA("Count of Line Item #",$A$3,"File Name",$A11)/GETPIVOTDATA("Count of Supplier Order Number",$A$3,"File Name",$A11) -> 1 | S11: =GETPIVOTDATA("Count of Line Item #",$A$3,"File Name",$A11)/GETPIVOTDATA("Count of Order Date",$A$3,"File Name",$A11) -> 1 | T11: =GETPIVOTDATA("Count of Line Item #",$A$3,"File Name",$A11)/GETPIVOTDATA("Count of Supplier Name",$A$3,"File Name",$A11) -> 1 | U11: =GETPIVOTDATA("Count of Line Item #",$A$3,"File Name",$A11)/GETPIVOTDATA("Count of Customer Name",$A$3,"File Name",$A11) -> 1 | V11: =GETPIVOTDATA("Count of Line Item #",$A$3,"File Name",$A11)/GETPIVOTDATA("Count of Currency",$A$3,"File Name",$A11) -> 1 | W11: =GETPIVOTDATA("Count of Line Item #",$A$3,"File Name",$A11)/GETPIVOTDATA("Count of Article Number",$A$3,"File Name",$A11) -> 1 | X11: =GETPIVOTDATA("Count of Line Item #",$A$3,"File Name",$A11)/GETPIVOTDATA("Count of Item Description",$A$3,"File Name",$A11) -> 1 | Y11: =GETPIVOTDATA("Count of Line Item #",$A$3,"File Name",$A11)/GETPIVOTDATA("Count of Quantity",$A$3,"File Name",$A11) -> 1 | Z11: =GETPIVOTDATA("Count of Line Item #",$A$3,"File Name",$A11)/GETPIVOTDATA("Count of Unit of Measure",$A$3,"File Name",$A11) -> 1 | AA11: =GETPIVOTDATA("Count of Line Item #",$A$3,"File Name",$A11)/GETPIVOTDATA("Count of Unit Price",$A$3,"File Name",$A11) -> 1 | AB11: =GETPIVOTDATA("Count of Item Planned Delivery Date",$A$3,"File Name",$A11)/GETPIVOTDATA("Count of Line Item #",$A$3,"File Name",$A11) -> 0
A12: 2507017044 ESSITY Order Ontvangstbevestiging.pdf | B12: Purchase Order Confirmation | C12: extracted | D12: 2 | E12: 2 | F12: 2 | G12: 2 | H12: 2 | I12: 2 | J12: 2 | K12: 2 | L12: 2 | M12: 2 | N12: 2 | O12: 2 | Q12: =GETPIVOTDATA("Count of Line Item #",$A$3,"File Name",$A12)/GETPIVOTDATA("Count of Purchase Order Number",$A$3,"File Name",$A12) -> 1 | R12: =GETPIVOTDATA("Count of Line Item #",$A$3,"File Name",$A12)/GETPIVOTDATA("Count of Supplier Order Number",$A$3,"File Name",$A12) -> 1 | S12: =GETPIVOTDATA("Count of Line Item #",$A$3,"File Name",$A12)/GETPIVOTDATA("Count of Order Date",$A$3,"File Name",$A12) -> 1 | T12: =GETPIVOTDATA("Count of Line Item #",$A$3,"File Name",$A12)/GETPIVOTDATA("Count of Supplier Name",$A$3,"File Name",$A12) -> 1 | U12: =GETPIVOTDATA("Count of Line Item #",$A$3,"File Name",$A12)/GETPIVOTDATA("Count of Customer Name",$A$3,"File Name",$A12) -> 1 | V12: =GETPIVOTDATA("Count of Line Item #",$A$3,"File Name",$A12)/GETPIVOTDATA("Count of Currency",$A$3,"File Name",$A12) -> 1 | W12: =GETPIVOTDATA("Count of Line Item #",$A$3,"File Name",$A12)/GETPIVOTDATA("Count of Article Number",$A$3,"File Name",$A12) -> 1 | X12: =GETPIVOTDATA("Count of Line Item #",$A$3,"File Name",$A12)/GETPIVOTDATA("Count of Item Description",$A$3,"File Name",$A12) -> 1 | Y12: =GETPIVOTDATA("Count of Line Item #",$A$3,"File Name",$A12)/GETPIVOTDATA("Count of Quantity",$A$3,"File Name",$A12) -> 1 | Z12: =GETPIVOTDATA("Count of Line Item #",$A$3,"File Name",$A12)/GETPIVOTDATA("Count of Unit of Measure",$A$3,"File Name",$A12) -> 1 | AA12: =GETPIVOTDATA("Count of Line Item #",$A$3,"File Name",$A12)/GETPIVOTDATA("Count of Unit Price",$A$3,"File Name",$A12) -> 1 | AB12: =GETPIVOTDATA("Count of Item Planned Delivery Date",$A$3,"File Name",$A12)/GETPIVOTDATA("Count of Line Item #",$A$3,"File Name",$A12) -> 0
A13: 2508010179 ESSITY Orderbevestiging.pdf | B13: Purchase Order Confirmation | C13: extracted | D13: 6 | E13: 6 | F13: 6 | G13: 6 | H13: 6 | I13: 6 | J13: 6 | K13: 6 | L13: 6 | M13: 6 | N13: 6 | O13: 3 | P13: 4 | Q13: =GETPIVOTDATA("Count of Line Item #",$A$3,"File Name",$A13)/GETPIVOTDATA("Count of Purchase Order Number",$A$3,"File Name",$A13) -> 1 | R13: =GETPIVOTDATA("Count of Line Item #",$A$3,"File Name",$A13)/GETPIVOTDATA("Count of Supplier Order Number",$A$3,"File Name",$A13) -> 1 | S13: =GETPIVOTDATA("Count of Line Item #",$A$3,"File Name",$A13)/GETPIVOTDATA("Count of Order Date",$A$3,"File Name",$A13) -> 1 | T13: =GETPIVOTDATA("Count of Line Item #",$A$3,"File Name",$A13)/GETPIVOTDATA("Count of Supplier Name",$A$3,"File Name",$A13) -> 1 | U13: =GETPIVOTDATA("Count of Line Item #",$A$3,"File Name",$A13)/GETPIVOTDATA("Count of Customer Name",$A$3,"File Name",$A13) -> 1 | V13: =GETPIVOTDATA("Count of Line Item #",$A$3,"File Name",$A13)/GETPIVOTDATA("Count of Currency",$A$3,"File Name",$A13) -> 1 | W13: =GETPIVOTDATA("Count of Line Item #",$A$3,"File Name",$A13)/GETPIVOTDATA("Count of Article Number",$A$3,"File Name",$A13) -> 1 | X13: =GETPIVOTDATA("Count of Line Item #",$A$3,"File Name",$A13)/GETPIVOTDATA("Count of Item Description",$A$3,"File Name",$A13) -> 1 | Y13: =GETPIVOTDATA("Count of Line Item #",$A$3,"File Name",$A13)/GETPIVOTDATA("Count of Quantity",$A$3,"File Name",$A13) -> 1 | Z13: =GETPIVOTDATA("Count of Line Item #",$A$3,"File Name",$A13)/GETPIVOTDATA("Count of Unit of Measure",$A$3,"File Name",$A13) -> 1 | AA13: =GETPIVOTDATA("Count of Line Item #",$A$3,"File Name",$A13)/GETPIVOTDATA("Count of Unit Price",$A$3,"File Name",$A13) -> 2 | AB13: =GETPIVOTDATA("Count of Item Planned Delivery Date",$A$3,"File Name",$A13)/GETPIVOTDATA("Count of Line Item #",$A$3,"File Name",$A13) -> 0.66666667
A14: 3505026639 ESSITY Orderbevestiging.pdf | B14: Purchase Order Confirmation | C14: extracted | D14: 88 | E14: 88 | F14: 88 | G14: 88 | H14: 88 | I14: 88 | J14: 88 | K14: 88 | L14: 88 | M14: 88 | N14: 88 | O14: 88 | P14: 84 | Q14: =GETPIVOTDATA("Count of Line Item #",$A$3,"File Name",$A14)/GETPIVOTDATA("Count of Purchase Order Number",$A$3,"File Name",$A14) -> 1 | R14: =GETPIVOTDATA("Count of Line Item #",$A$3,"File Name",$A14)/GETPIVOTDATA("Count of Supplier Order Number",$A$3,"File Name",$A14) -> 1 | S14: =GETPIVOTDATA("Count of Line Item #",$A$3,"File Name",$A14)/GETPIVOTDATA("Count of Order Date",$A$3,"File Name",$A14) -> 1 | T14: =GETPIVOTDATA("Count of Line Item #",$A$3,"File Name",$A14)/GETPIVOTDATA("Count of Supplier Name",$A$3,"File Name",$A14) -> 1 | U14: =GETPIVOTDATA("Count of Line Item #",$A$3,"File Name",$A14)/GETPIVOTDATA("Count of Customer Name",$A$3,"File Name",$A14) -> 1 | V14: =GETPIVOTDATA("Count of Line Item #",$A$3,"File Name",$A14)/GETPIVOTDATA("Count of Currency",$A$3,"File Name",$A14) -> 1 | W14: =GETPIVOTDATA("Count of Line Item #",$A$3,"File Name",$A14)/GETPIVOTDATA("Count of Article Number",$A$3,"File Name",$A14) -> 1 | X14: =GETPIVOTDATA("Count of Line Item #",$A$3,"File Name",$A14)/GETPIVOTDATA("Count of Item Description",$A$3,"File Name",$A14) -> 1 | Y14: =GETPIVOTDATA("Count of Line Item #",$A$3,"File Name",$A14)/GETPIVOTDATA("Count of Quantity",$A$3,"File Name",$A14) -> 1 | Z14: =GETPIVOTDATA("Count of Line Item #",$A$3,"File Name",$A14)/GETPIVOTDATA("Count of Unit of Measure",$A$3,"File Name",$A14) -> 1 | AA14: =GETPIVOTDATA("Count of Line Item #",$A$3,"File Name",$A14)/GETPIVOTDATA("Count of Unit Price",$A$3,"File Name",$A14) -> 1 | AB14: =GETPIVOTDATA("Count of Item Planned Delivery Date",$A$3,"File Name",$A14)/GETPIVOTDATA("Count of Line Item #",$A$3,"File Name",$A14) -> 0.95454545
A15: 3505026670 ESSITY Orderbevestiging.pdf | B15: Purchase Order Confirmation | C15: extracted | D15: 1 | E15: 1 | F15: 1 | G15: 1 | H15: 1 | I15: 1 | J15: 1 | K15: 1 | L15: 1 | M15: 1 | N15: 1 | O15: 1 | P15: 1 | Q15: =GETPIVOTDATA("Count of Line Item #",$A$3,"File Name",$A15)/GETPIVOTDATA("Count of Purchase Order Number",$A$3,"File Name",$A15) -> 1 | R15: =GETPIVOTDATA("Count of Line Item #",$A$3,"File Name",$A15)/GETPIVOTDATA("Count of Supplier Order Number",$A$3,"File Name",$A15) -> 1 | S15: =GETPIVOTDATA("Count of Line Item #",$A$3,"File Name",$A15)/GETPIVOTDATA("Count of Order Date",$A$3,"File Name",$A15) -> 1 | T15: =GETPIVOTDATA("Count of Line Item #",$A$3,"File Name",$A15)/GETPIVOTDATA("Count of Supplier Name",$A$3,"File Name",$A15) -> 1 | U15: =GETPIVOTDATA("Count of Line Item #",$A$3,"File Name",$A15)/GETPIVOTDATA("Count of Customer Name",$A$3,"File Name",$A15) -> 1 | V15: =GETPIVOTDATA("Count of Line Item #",$A$3,"File Name",$A15)/GETPIVOTDATA("Count of Currency",$A$3,"File Name",$A15) -> 1 | W15: =GETPIVOTDATA("Count of Line Item #",$A$3,"File Name",$A15)/GETPIVOTDATA("Count of Article Number",$A$3,"File Name",$A15) -> 1 | X15: =GETPIVOTDATA("Count of Line Item #",$A$3,"File Name",$A15)/GETPIVOTDATA("Count of Item Description",$A$3,"File Name",$A15) -> 1 | Y15: =GETPIVOTDATA("Count of Line Item #",$A$3,"File Name",$A15)/GETPIVOTDATA("Count of Quantity",$A$3,"File Name",$A15) -> 1 | Z15: =GETPIVOTDATA("Count of Line Item #",$A$3,"File Name",$A15)/GETPIVOTDATA("Count of Unit of Measure",$A$3,"File Name",$A15) -> 1 | AA15: =GETPIVOTDATA("Count of Line Item #",$A$3,"File Name",$A15)/GETPIVOTDATA("Count of Unit Price",$A$3,"File Name",$A15) -> 1 | AB15: =GETPIVOTDATA("Count of Item Planned Delivery Date",$A$3,"File Name",$A15)/GETPIVOTDATA("Count of Line Item #",$A$3,"File Name",$A15) -> 1
A16: 3505026678 ESSITY Orderbevestiging.pdf | B16: Purchase Order Confirmation | C16: extracted | D16: 2 | E16: 2 | F16: 2 | G16: 2 | H16: 2 | I16: 2 | J16: 2 | K16: 2 | L16: 2 | M16: 2 | N16: 2 | O16: 2 | P16: 2 | Q16: =GETPIVOTDATA("Count of Line Item #",$A$3,"File Name",$A16)/GETPIVOTDATA("Count of Purchase Order Number",$A$3,"File Name",$A16) -> 1 | R16: =GETPIVOTDATA("Count of Line Item #",$A$3,"File Name",$A16)/GETPIVOTDATA("Count of Supplier Order Number",$A$3,"File Name",$A16) -> 1 | S16: =GETPIVOTDATA("Count of Line Item #",$A$3,"File Name",$A16)/GETPIVOTDATA("Count of Order Date",$A$3,"File Name",$A16) -> 1 | T16: =GETPIVOTDATA("Count of Line Item #",$A$3,"File Name",$A16)/GETPIVOTDATA("Count of Supplier Name",$A$3,"File Name",$A16) -> 1 | U16: =GETPIVOTDATA("Count of Line Item #",$A$3,"File Name",$A16)/GETPIVOTDATA("Count of Customer Name",$A$3,"File Name",$A16) -> 1 | V16: =GETPIVOTDATA("Count of Line Item #",$A$3,"File Name",$A16)/GETPIVOTDATA("Count of Currency",$A$3,"File Name",$A16) -> 1 | W16: =GETPIVOTDATA("Count of Line Item #",$A$3,"File Name",$A16)/GETPIVOTDATA("Count of Article Number",$A$3,"File Name",$A16) -> 1 | X16: =GETPIVOTDATA("Count of Line Item #",$A$3,"File Name",$A16)/GETPIVOTDATA("Count of Item Description",$A$3,"File Name",$A16) -> 1 | Y16: =GETPIVOTDATA("Count of Line Item #",$A$3,"File Name",$A16)/GETPIVOTDATA("Count of Quantity",$A$3,"File Name",$A16) -> 1 | Z16: =GETPIVOTDATA("Count of Line Item #",$A$3,"File Name",$A16)/GETPIVOTDATA("Count of Unit of Measure",$A$3,"File Name",$A16) -> 1 | AA16: =GETPIVOTDATA("Count of Line Item #",$A$3,"File Name",$A16)/GETPIVOTDATA("Count of Unit Price",$A$3,"File Name",$A16) -> 1 | AB16: =GETPIVOTDATA("Count of Item Planned Delivery Date",$A$3,"File Name",$A16)/GETPIVOTDATA("Count of Line Item #",$A$3,"File Name",$A16) -> 1
A17: 6507004827 ESSITY Order Ontvangstbevestiging.pdf | B17: Purchase Order Confirmation | C17: extracted | D17: 1 | E17: 1 | F17: 1 | G17: 1 | H17: 1 | I17: 1 | J17: 1 | K17: 1 | L17: 1 | M17: 1 | N17: 1 | O17: 1 | Q17: =GETPIVOTDATA("Count of Line Item #",$A$3,"File Name",$A17)/GETPIVOTDATA("Count of Purchase Order Number",$A$3,"File Name",$A17) -> 1 | R17: =GETPIVOTDATA("Count of Line Item #",$A$3,"File Name",$A17)/GETPIVOTDATA("Count of Supplier Order Number",$A$3,"File Name",$A17) -> 1 | S17: =GETPIVOTDATA("Count of Line Item #",$A$3,"File Name",$A17)/GETPIVOTDATA("Count of Order Date",$A$3,"File Name",$A17) -> 1 | T17: =GETPIVOTDATA("Count of Line Item #",$A$3,"File Name",$A17)/GETPIVOTDATA("Count of Supplier Name",$A$3,"File Name",$A17) -> 1 | U17: =GETPIVOTDATA("Count of Line Item #",$A$3,"File Name",$A17)/GETPIVOTDATA("Count of Customer Name",$A$3,"File Name",$A17) -> 1 | V17: =GETPIVOTDATA("Count of Line Item #",$A$3,"File Name",$A17)/GETPIVOTDATA("Count of Currency",$A$3,"File Name",$A17) -> 1 | W17: =GETPIVOTDATA("Count of Line Item #",$A$3,"File Name",$A17)/GETPIVOTDATA("Count of Article Number",$A$3,"File Name",$A17) -> 1 | X17: =GETPIVOTDATA("Count of Line Item #",$A$3,"File Name",$A17)/GETPIVOTDATA("Count of Item Description",$A$3,"File Name",$A17) -> 1 | Y17: =GETPIVOTDATA("Count of Line Item #",$A$3,"File Name",$A17)/GETPIVOTDATA("Count of Quantity",$A$3,"File Name",$A17) -> 1 | Z17: =GETPIVOTDATA("Count of Line Item #",$A$3,"File Name",$A17)/GETPIVOTDATA("Count of Unit of Measure",$A$3,"File Name",$A17) -> 1 | AA17: =GETPIVOTDATA("Count of Line Item #",$A$3,"File Name",$A17)/GETPIVOTDATA("Count of Unit Price",$A$3,"File Name",$A17) -> 1 | AB17: =GETPIVOTDATA("Count of Item Planned Delivery Date",$A$3,"File Name",$A17)/GETPIVOTDATA("Count of Line Item #",$A$3,"File Name",$A17) -> 0
A18: 6507004831 ESSITY Order Ontvangstbevestiging.pdf | B18: Purchase Order Confirmation | C18: extracted | D18: 1 | E18: 1 | F18: 1 | G18: 1 | H18: 1 | I18: 1 | J18: 1 | K18: 1 | L18: 1 | M18: 1 | N18: 1 | O18: 1 | Q18: =GETPIVOTDATA("Count of Line Item #",$A$3,"File Name",$A18)/GETPIVOTDATA("Count of Purchase Order Number",$A$3,"File Name",$A18) -> 1 | R18: =GETPIVOTDATA("Count of Line Item #",$A$3,"File Name",$A18)/GETPIVOTDATA("Count of Supplier Order Number",$A$3,"File Name",$A18) -> 1 | S18: =GETPIVOTDATA("Count of Line Item #",$A$3,"File Name",$A18)/GETPIVOTDATA("Count of Order Date",$A$3,"File Name",$A18) -> 1 | T18: =GETPIVOTDATA("Count of Line Item #",$A$3,"File Name",$A18)/GETPIVOTDATA("Count of Supplier Name",$A$3,"File Name",$A18) -> 1 | U18: =GETPIVOTDATA("Count of Line Item #",$A$3,"File Name",$A18)/GETPIVOTDATA("Count of Customer Name",$A$3,"File Name",$A18) -> 1 | V18: =GETPIVOTDATA("Count of Line Item #",$A$3,"File Name",$A18)/GETPIVOTDATA("Count of Currency",$A$3,"File Name",$A18) -> 1 | W18: =GETPIVOTDATA("Count of Line Item #",$A$3,"File Name",$A18)/GETPIVOTDATA("Count of Article Number",$A$3,"File Name",$A18) -> 1 | X18: =GETPIVOTDATA("Count of Line Item #",$A$3,"File Name",$A18)/GETPIVOTDATA("Count of Item Description",$A$3,"File Name",$A18) -> 1 | Y18: =GETPIVOTDATA("Count of Line Item #",$A$3,"File Name",$A18)/GETPIVOTDATA("Count of Quantity",$A$3,"File Name",$A18) -> 1 | Z18: =GETPIVOTDATA("Count of Line Item #",$A$3,"File Name",$A18)/GETPIVOTDATA("Count of Unit of Measure",$A$3,"File Name",$A18) -> 1 | AA18: =GETPIVOTDATA("Count of Line Item #",$A$3,"File Name",$A18)/GETPIVOTDATA("Count of Unit Price",$A$3,"File Name",$A18) -> 1 | AB18: =GETPIVOTDATA("Count of Item Planned Delivery Date",$A$3,"File Name",$A18)/GETPIVOTDATA("Count of Line Item #",$A$3,"File Name",$A18) -> 0
A19: 6507004833 ESSITY Order Ontvangstbevestiging.pdf | B19: Purchase Order Confirmation | C19: extracted | D19: 1 | E19: 1 | F19: 1 | G19: 1 | H19: 1 | I19: 1 | J19: 1 | K19: 1 | L19: 1 | M19: 1 | N19: 1 | O19: 1 | Q19: =GETPIVOTDATA("Count of Line Item #",$A$3,"File Name",$A19)/GETPIVOTDATA("Count of Purchase Order Number",$A$3,"File Name",$A19) -> 1 | R19: =GETPIVOTDATA("Count of Line Item #",$A$3,"File Name",$A19)/GETPIVOTDATA("Count of Supplier Order Number",$A$3,"File Name",$A19) -> 1 | S19: =GETPIVOTDATA("Count of Line Item #",$A$3,"File Name",$A19)/GETPIVOTDATA("Count of Order Date",$A$3,"File Name",$A19) -> 1 | T19: =GETPIVOTDATA("Count of Line Item #",$A$3,"File Name",$A19)/GETPIVOTDATA("Count of Supplier Name",$A$3,"File Name",$A19) -> 1 | U19: =GETPIVOTDATA("Count of Line Item #",$A$3,"File Name",$A19)/GETPIVOTDATA("Count of Customer Name",$A$3,"File Name",$A19) -> 1 | V19: =GETPIVOTDATA("Count of Line Item #",$A$3,"File Name",$A19)/GETPIVOTDATA("Count of Currency",$A$3,"File Name",$A19) -> 1 | W19: =GETPIVOTDATA("Count of Line Item #",$A$3,"File Name",$A19)/GETPIVOTDATA("Count of Article Number",$A$3,"File Name",$A19) -> 1 | X19: =GETPIVOTDATA("Count of Line Item #",$A$3,"File Name",$A19)/GETPIVOTDATA("Count of Item Description",$A$3,"File Name",$A19) -> 1 | Y19: =GETPIVOTDATA("Count of Line Item #",$A$3,"File Name",$A19)/GETPIVOTDATA("Count of Quantity",$A$3,"File Name",$A19) -> 1 | Z19: =GETPIVOTDATA("Count of Line Item #",$A$3,"File Name",$A19)/GETPIVOTDATA("Count of Unit of Measure",$A$3,"File Name",$A19) -> 1 | AA19: =GETPIVOTDATA("Count of Line Item #",$A$3,"File Name",$A19)/GETPIVOTDATA("Count of Unit Price",$A$3,"File Name",$A19) -> 1 | AB19: =GETPIVOTDATA("Count of Item Planned Delivery Date",$A$3,"File Name",$A19)/GETPIVOTDATA("Count of Line Item #",$A$3,"File Name",$A19) -> 0
A20: BD Order Acknowledgement for your purchase order with reference 1505040027.pdf | B20: Purchase Order Confirmation | C20: extracted | D20: 2 | E20: 2 | F20: 2 | G20: 2 | H20: 2 | I20: 2 | J20: 2 | K20: 2 | L20: 2 | M20: 2 | N20: 2 | O20: 2 | P20: 2 | Q20: =GETPIVOTDATA("Count of Line Item #",$A$3,"File Name",$A20)/GETPIVOTDATA("Count of Purchase Order Number",$A$3,"File Name",$A20) -> 1 | R20: =GETPIVOTDATA("Count of Line Item #",$A$3,"File Name",$A20)/GETPIVOTDATA("Count of Supplier Order Number",$A$3,"File Name",$A20) -> 1 | S20: =GETPIVOTDATA("Count of Line Item #",$A$3,"File Name",$A20)/GETPIVOTDATA("Count of Order Date",$A$3,"File Name",$A20) -> 1 | T20: =GETPIVOTDATA("Count of Line Item #",$A$3,"File Name",$A20)/GETPIVOTDATA("Count of Supplier Name",$A$3,"File Name",$A20) -> 1 | U20: =GETPIVOTDATA("Count of Line Item #",$A$3,"File Name",$A20)/GETPIVOTDATA("Count of Customer Name",$A$3,"File Name",$A20) -> 1 | V20: =GETPIVOTDATA("Count of Line Item #",$A$3,"File Name",$A20)/GETPIVOTDATA("Count of Currency",$A$3,"File Name",$A20) -> 1 | W20: =GETPIVOTDATA("Count of Line Item #",$A$3,"File Name",$A20)/GETPIVOTDATA("Count of Article Number",$A$3,"File Name",$A20) -> 1 | X20: =GETPIVOTDATA("Count of Line Item #",$A$3,"File Name",$A20)/GETPIVOTDATA("Count of Item Description",$A$3,"File Name",$A20) -> 1 | Y20: =GETPIVOTDATA("Count of Line Item #",$A$3,"File Name",$A20)/GETPIVOTDATA("Count of Quantity",$A$3,"File Name",$A20) -> 1 | Z20: =GETPIVOTDATA("Count of Line Item #",$A$3,"File Name",$A20)/GETPIVOTDATA("Count of Unit of Measure",$A$3,"File Name",$A20) -> 1 | AA20: =GETPIVOTDATA("Count of Line Item #",$A$3,"File Name",$A20)/GETPIVOTDATA("Count of Unit Price",$A$3,"File Name",$A20) -> 1 | AB20: =GETPIVOTDATA("Count of Item Planned Delivery Date",$A$3,"File Name",$A20)/GETPIVOTDATA("Count of Line Item #",$A$3,"File Name",$A20) -> 1
A21: BD Order Acknowledgement for your purchase order with reference 3504015923.pdf | B21: Purchase Order Confirmation | C21: extracted | D21: 29 | E21: 29 | F21: 29 | G21: 29 | H21: 29 | I21: 29 | J21: 29 | K21: 29 | L21: 29 | M21: 29 | O21: 29 | P21: 29 | Q21: =GETPIVOTDATA("Count of Line Item #",$A$3,"File Name",$A21)/GETPIVOTDATA("Count of Purchase Order Number",$A$3,"File Name",$A21) -> 1 | R21: =GETPIVOTDATA("Count of Line Item #",$A$3,"File Name",$A21)/GETPIVOTDATA("Count of Supplier Order Number",$A$3,"File Name",$A21) -> 1 | S21: =GETPIVOTDATA("Count of Line Item #",$A$3,"File Name",$A21)/GETPIVOTDATA("Count of Order Date",$A$3,"File Name",$A21) -> 1 | T21: =GETPIVOTDATA("Count of Line Item #",$A$3,"File Name",$A21)/GETPIVOTDATA("Count of Supplier Name",$A$3,"File Name",$A21) -> 1 | U21: =GETPIVOTDATA("Count of Line Item #",$A$3,"File Name",$A21)/GETPIVOTDATA("Count of Customer Name",$A$3,"File Name",$A21) -> 1 | V21: =GETPIVOTDATA("Count of Line Item #",$A$3,"File Name",$A21)/GETPIVOTDATA("Count of Currency",$A$3,"File Name",$A21) -> 1 | W21: =GETPIVOTDATA("Count of Line Item #",$A$3,"File Name",$A21)/GETPIVOTDATA("Count of Article Number",$A$3,"File Name",$A21) -> 1 | X21: =GETPIVOTDATA("Count of Line Item #",$A$3,"File Name",$A21)/GETPIVOTDATA("Count of Item Description",$A$3,"File Name",$A21) -> 1 | Y21: =GETPIVOTDATA("Count of Line Item #",$A$3,"File Name",$A21)/GETPIVOTDATA("Count of Quantity",$A$3,"File Name",$A21) -> 1 | Z21: =GETPIVOTDATA("Count of Line Item #",$A$3,"File Name",$A21)/GETPIVOTDATA("Count of Unit of Measure",$A$3,"File Name",$A21) -> #DIV/0! | AA21: =GETPIVOTDATA("Count of Line Item #",$A$3,"File Name",$A21)/GETPIVOTDATA("Count of Unit Price",$A$3,"File Name",$A21) -> 1 | AB21: =GETPIVOTDATA("Count of Item Planned Delivery Date",$A$3,"File Name",$A21)/GETPIVOTDATA("Count of Line Item #",$A$3,"File Name",$A21) -> 1
A22: BD Order Acknowledgement for your purchase order with reference 3507009726.pdf | B22: Purchase Order Confirmation | C22: extracted | D22: 11 | E22: 11 | F22: 11 | G22: 11 | H22: 11 | I22: 11 | J22: 11 | K22: 11 | L22: 11 | M22: 11 | O22: 11 | P22: 11 | Q22: =GETPIVOTDATA("Count of Line Item #",$A$3,"File Name",$A22)/GETPIVOTDATA("Count of Purchase Order Number",$A$3,"File Name",$A22) -> 1 | R22: =GETPIVOTDATA("Count of Line Item #",$A$3,"File Name",$A22)/GETPIVOTDATA("Count of Supplier Order Number",$A$3,"File Name",$A22) -> 1 | S22: =GETPIVOTDATA("Count of Line Item #",$A$3,"File Name",$A22)/GETPIVOTDATA("Count of Order Date",$A$3,"File Name",$A22) -> 1 | T22: =GETPIVOTDATA("Count of Line Item #",$A$3,"File Name",$A22)/GETPIVOTDATA("Count of Supplier Name",$A$3,"File Name",$A22) -> 1 | U22: =GETPIVOTDATA("Count of Line Item #",$A$3,"File Name",$A22)/GETPIVOTDATA("Count of Customer Name",$A$3,"File Name",$A22) -> 1 | V22: =GETPIVOTDATA("Count of Line Item #",$A$3,"File Name",$A22)/GETPIVOTDATA("Count of Currency",$A$3,"File Name",$A22) -> 1 | W22: =GETPIVOTDATA("Count of Line Item #",$A$3,"File Name",$A22)/GETPIVOTDATA("Count of Article Number",$A$3,"File Name",$A22) -> 1 | X22: =GETPIVOTDATA("Count of Line Item #",$A$3,"File Name",$A22)/GETPIVOTDATA("Count of Item Description",$A$3,"File Name",$A22) -> 1 | Y22: =GETPIVOTDATA("Count of Line Item #",$A$3,"File Name",$A22)/GETPIVOTDATA("Count of Quantity",$A$3,"File Name",$A22) -> 1 | Z22: =GETPIVOTDATA("Count of Line Item #",$A$3,"File Name",$A22)/GETPIVOTDATA("Count of Unit of Measure",$A$3,"File Name",$A22) -> #DIV/0! | AA22: =GETPIVOTDATA("Count of Line Item #",$A$3,"File Name",$A22)/GETPIVOTDATA("Count of Unit Price",$A$3,"File Name",$A22) -> 1 | AB22: =GETPIVOTDATA("Count of Item Planned Delivery Date",$A$3,"File Name",$A22)/GETPIVOTDATA("Count of Line Item #",$A$3,"File Name",$A22) -> 1
A23: BE356233 Order Hospital Logistics 1501037350.pdf | B23: Purchase Order Confirmation | C23: extracted | D23: 1 | E23: 1 | F23: 1 | G23: 1 | H23: 1 | I23: 1 | J23: 1 | K23: 1 | M23: 1 | O23: 1 | P23: 1 | Q23: =GETPIVOTDATA("Count of Line Item #",$A$3,"File Name",$A23)/GETPIVOTDATA("Count of Purchase Order Number",$A$3,"File Name",$A23) -> 1 | R23: =GETPIVOTDATA("Count of Line Item #",$A$3,"File Name",$A23)/GETPIVOTDATA("Count of Supplier Order Number",$A$3,"File Name",$A23) -> 1 | S23: =GETPIVOTDATA("Count of Line Item #",$A$3,"File Name",$A23)/GETPIVOTDATA("Count of Order Date",$A$3,"File Name",$A23) -> 1 | T23: =GETPIVOTDATA("Count of Line Item #",$A$3,"File Name",$A23)/GETPIVOTDATA("Count of Supplier Name",$A$3,"File Name",$A23) -> 1 | U23: =GETPIVOTDATA("Count of Line Item #",$A$3,"File Name",$A23)/GETPIVOTDATA("Count of Customer Name",$A$3,"File Name",$A23) -> 1 | V23: =GETPIVOTDATA("Count of Line Item #",$A$3,"File Name",$A23)/GETPIVOTDATA("Count of Currency",$A$3,"File Name",$A23) -> 1 | W23: =GETPIVOTDATA("Count of Line Item #",$A$3,"File Name",$A23)/GETPIVOTDATA("Count of Article Number",$A$3,"File Name",$A23) -> 1 | X23: =GETPIVOTDATA("Count of Line Item #",$A$3,"File Name",$A23)/GETPIVOTDATA("Count of Item Description",$A$3,"File Name",$A23) -> #DIV/0! | Y23: =GETPIVOTDATA("Count of Line Item #",$A$3,"File Name",$A23)/GETPIVOTDATA("Count of Quantity",$A$3,"File Name",$A23) -> 1 | Z23: =GETPIVOTDATA("Count of Line Item #",$A$3,"File Name",$A23)/GETPIVOTDATA("Count of Unit of Measure",$A$3,"File Name",$A23) -> #DIV/0! | AA23: =GETPIVOTDATA("Count of Line Item #",$A$3,"File Name",$A23)/GETPIVOTDATA("Count of Unit Price",$A$3,"File Name",$A23) -> 1 | AB23: =GETPIVOTDATA("Count of Item Planned Delivery Date",$A$3,"File Name",$A23)/GETPIVOTDATA("Count of Line Item #",$A$3,"File Name",$A23) -> 1
A24: Betreft_ Overzicht van nog te leveren Vygon producten.pdf | B24: Purchase Order Confirmation | C24: extracted | D24: 1 | E24: 1 | F24: 1 | G24: 1 | H24: 1 | I24: 1 | K24: 1 | L24: 1 | M24: 1 | P24: 1 | Q24: =GETPIVOTDATA("Count of Line Item #",$A$3,"File Name",$A24)/GETPIVOTDATA("Count of Purchase Order Number",$A$3,"File Name",$A24) -> #REF! | R24: =GETPIVOTDATA("Count of Line Item #",$A$3,"File Name",$A24)/GETPIVOTDATA("Count of Supplier Order Number",$A$3,"File Name",$A24) -> #REF! | S24: =GETPIVOTDATA("Count of Line Item #",$A$3,"File Name",$A24)/GETPIVOTDATA("Count of Order Date",$A$3,"File Name",$A24) -> #REF! | T24: =GETPIVOTDATA("Count of Line Item #",$A$3,"File Name",$A24)/GETPIVOTDATA("Count of Supplier Name",$A$3,"File Name",$A24) -> #REF! | U24: =GETPIVOTDATA("Count of Line Item #",$A$3,"File Name",$A24)/GETPIVOTDATA("Count of Customer Name",$A$3,"File Name",$A24) -> #REF! | V24: =GETPIVOTDATA("Count of Line Item #",$A$3,"File Name",$A24)/GETPIVOTDATA("Count of Currency",$A$3,"File Name",$A24) -> #REF! | W24: =GETPIVOTDATA("Count of Line Item #",$A$3,"File Name",$A24)/GETPIVOTDATA("Count of Article Number",$A$3,"File Name",$A24) -> #REF! | X24: =GETPIVOTDATA("Count of Line Item #",$A$3,"File Name",$A24)/GETPIVOTDATA("Count of Item Description",$A$3,"File Name",$A24) -> #REF! | Y24: =GETPIVOTDATA("Count of Line Item #",$A$3,"File Name",$A24)/GETPIVOTDATA("Count of Quantity",$A$3,"File Name",$A24) -> #REF! | Z24: =GETPIVOTDATA("Count of Line Item #",$A$3,"File Name",$A24)/GETPIVOTDATA("Count of Unit of Measure",$A$3,"File Name",$A24) -> #REF! | AA24: =GETPIVOTDATA("Count of Line Item #",$A$3,"File Name",$A24)/GETPIVOTDATA("Count of Unit Price",$A$3,"File Name",$A24) -> #REF! | AB24: =GETPIVOTDATA("Count of Item Planned Delivery Date",$A$3,"File Name",$A24)/GETPIVOTDATA("Count of Line Item #",$A$3,"File Name",$A24) -> #REF!
A25: Betreft_ Overzicht van nog te leveren Vygon producten.pdf | B25: Purchase Order Confirmation | C25: unclassified | Q25: =GETPIVOTDATA("Count of Line Item #",$A$3,"File Name",$A25)/GETPIVOTDATA("Count of Purchase Order Number",$A$3,"File Name",$A25) -> #REF! | R25: =GETPIVOTDATA("Count of Line Item #",$A$3,"File Name",$A25)/GETPIVOTDATA("Count of Supplier Order Number",$A$3,"File Name",$A25) -> #REF! | S25: =GETPIVOTDATA("Count of Line Item #",$A$3,"File Name",$A25)/GETPIVOTDATA("Count of Order Date",$A$3,"File Name",$A25) -> #REF! | T25: =GETPIVOTDATA("Count of Line Item #",$A$3,"File Name",$A25)/GETPIVOTDATA("Count of Supplier Name",$A$3,"File Name",$A25) -> #REF! | U25: =GETPIVOTDATA("Count of Line Item #",$A$3,"File Name",$A25)/GETPIVOTDATA("Count of Customer Name",$A$3,"File Name",$A25) -> #REF! | V25: =GETPIVOTDATA("Count of Line Item #",$A$3,"File Name",$A25)/GETPIVOTDATA("Count of Currency",$A$3,"File Name",$A25) -> #REF! | W25: =GETPIVOTDATA("Count of Line Item #",$A$3,"File Name",$A25)/GETPIVOTDATA("Count of Article Number",$A$3,"File Name",$A25) -> #REF! | X25: =GETPIVOTDATA("Count of Line Item #",$A$3,"File Name",$A25)/GETPIVOTDATA("Count of Item Description",$A$3,"File Name",$A25) -> #REF! | Y25: =GETPIVOTDATA("Count of Line Item #",$A$3,"File Name",$A25)/GETPIVOTDATA("Count of Quantity",$A$3,"File Name",$A25) -> #REF! | Z25: =GETPIVOTDATA("Count of Line Item #",$A$3,"File Name",$A25)/GETPIVOTDATA("Count of Unit of Measure",$A$3,"File Name",$A25) -> #REF! | AA25: =GETPIVOTDATA("Count of Line Item #",$A$3,"File Name",$A25)/GETPIVOTDATA("Count of Unit Price",$A$3,"File Name",$A25) -> #REF! | AB25: =GETPIVOTDATA("Count of Item Planned Delivery Date",$A$3,"File Name",$A25)/GETPIVOTDATA("Count of Line Item #",$A$3,"File Name",$A25) -> #REF!
A26: Betreft_ Overzicht van nog te leveren Vygon producten.pdf | B26: (blank) | C26: unclassified | Q26: =GETPIVOTDATA("Count of Line Item #",$A$3,"File Name",$A26)/GETPIVOTDATA("Count of Purchase Order Number",$A$3,"File Name",$A26) -> #REF! | R26: =GETPIVOTDATA("Count of Line Item #",$A$3,"File Name",$A26)/GETPIVOTDATA("Count of Supplier Order Number",$A$3,"File Name",$A26) -> #REF! | S26: =GETPIVOTDATA("Count of Line Item #",$A$3,"File Name",$A26)/GETPIVOTDATA("Count of Order Date",$A$3,"File Name",$A26) -> #REF! | T26: =GETPIVOTDATA("Count of Line Item #",$A$3,"File Name",$A26)/GETPIVOTDATA("Count of Supplier Name",$A$3,"File Name",$A26) -> #REF! | U26: =GETPIVOTDATA("Count of Line Item #",$A$3,"File Name",$A26)/GETPIVOTDATA("Count of Customer Name",$A$3,"File Name",$A26) -> #REF! | V26: =GETPIVOTDATA("Count of Line Item #",$A$3,"File Name",$A26)/GETPIVOTDATA("Count of Currency",$A$3,"File Name",$A26) -> #REF! | W26: =GETPIVOTDATA("Count of Line Item #",$A$3,"File Name",$A26)/GETPIVOTDATA("Count of Article Number",$A$3,"File Name",$A26) -> #REF! | X26: =GETPIVOTDATA("Count of Line Item #",$A$3,"File Name",$A26)/GETPIVOTDATA("Count of Item Description",$A$3,"File Name",$A26) -> #REF! | Y26: =GETPIVOTDATA("Count of Line Item #",$A$3,"File Name",$A26)/GETPIVOTDATA("Count of Quantity",$A$3,"File Name",$A26) -> #REF! | Z26: =GETPIVOTDATA("Count of Line Item #",$A$3,"File Name",$A26)/GETPIVOTDATA("Count of Unit of Measure",$A$3,"File Name",$A26) -> #REF! | AA26: =GETPIVOTDATA("Count of Line Item #",$A$3,"File Name",$A26)/GETPIVOTDATA("Count of Unit Price",$A$3,"File Name",$A26) -> #REF! | AB26: =GETPIVOTDATA("Count of Item Planned Delivery Date",$A$3,"File Name",$A26)/GETPIVOTDATA("Count of Line Item #",$A$3,"File Name",$A26) -> #REF!
A27: Bevestiging bestelling S09313425-1.pdf | B27: Purchase Order Confirmation | C27: extracted | D27: 1 | E27: 1 | F27: 1 | G27: 1 | H27: 1 | I27: 1 | J27: 1 | K27: 1 | L27: 1 | M27: 1 | N27: 1 | O27: 1 | P27: 1 | Q27: =GETPIVOTDATA("Count of Line Item #",$A$3,"File Name",$A27)/GETPIVOTDATA("Count of Purchase Order Number",$A$3,"File Name",$A27) -> 1 | R27: =GETPIVOTDATA("Count of Line Item #",$A$3,"File Name",$A27)/GETPIVOTDATA("Count of Supplier Order Number",$A$3,"File Name",$A27) -> 1 | S27: =GETPIVOTDATA("Count of Line Item #",$A$3,"File Name",$A27)/GETPIVOTDATA("Count of Order Date",$A$3,"File Name",$A27) -> 1 | T27: =GETPIVOTDATA("Count of Line Item #",$A$3,"File Name",$A27)/GETPIVOTDATA("Count of Supplier Name",$A$3,"File Name",$A27) -> 1 | U27: =GETPIVOTDATA("Count of Line Item #",$A$3,"File Name",$A27)/GETPIVOTDATA("Count of Customer Name",$A$3,"File Name",$A27) -> 1 | V27: =GETPIVOTDATA("Count of Line Item #",$A$3,"File Name",$A27)/GETPIVOTDATA("Count of Currency",$A$3,"File Name",$A27) -> 1 | W27: =GETPIVOTDATA("Count of Line Item #",$A$3,"File Name",$A27)/GETPIVOTDATA("Count of Article Number",$A$3,"File Name",$A27) -> 1 | X27: =GETPIVOTDATA("Count of Line Item #",$A$3,"File Name",$A27)/GETPIVOTDATA("Count of Item Description",$A$3,"File Name",$A27) -> 1 | Y27: =GETPIVOTDATA("Count of Line Item #",$A$3,"File Name",$A27)/GETPIVOTDATA("Count of Quantity",$A$3,"File Name",$A27) -> 1 | Z27: =GETPIVOTDATA("Count of Line Item #",$A$3,"File Name",$A27)/GETPIVOTDATA("Count of Unit of Measure",$A$3,"File Name",$A27) -> 1 | AA27: =GETPIVOTDATA("Count of Line Item #",$A$3,"File Name",$A27)/GETPIVOTDATA("Count of Unit Price",$A$3,"File Name",$A27) -> 1 | AB27: =GETPIVOTDATA("Count of Item Planned Delivery Date",$A$3,"File Name",$A27)/GETPIVOTDATA("Count of Line Item #",$A$3,"File Name",$A27) -> 1
A28: Bevestiging bestelling S09313437-1.pdf | B28: Purchase Order Confirmation | C28: extracted | D28: 1 | E28: 1 | F28: 1 | G28: 1 | H28: 1 | I28: 1 | J28: 1 | K28: 1 | L28: 1 | M28: 1 | N28: 1 | O28: 1 | P28: 1 | Q28: =GETPIVOTDATA("Count of Line Item #",$A$3,"File Name",$A28)/GETPIVOTDATA("Count of Purchase Order Number",$A$3,"File Name",$A28) -> 1 | R28: =GETPIVOTDATA("Count of Line Item #",$A$3,"File Name",$A28)/GETPIVOTDATA("Count of Supplier Order Number",$A$3,"File Name",$A28) -> 1 | S28: =GETPIVOTDATA("Count of Line Item #",$A$3,"File Name",$A28)/GETPIVOTDATA("Count of Order Date",$A$3,"File Name",$A28) -> 1 | T28: =GETPIVOTDATA("Count of Line Item #",$A$3,"File Name",$A28)/GETPIVOTDATA("Count of Supplier Name",$A$3,"File Name",$A28) -> 1 | U28: =GETPIVOTDATA("Count of Line Item #",$A$3,"File Name",$A28)/GETPIVOTDATA("Count of Customer Name",$A$3,"File Name",$A28) -> 1 | V28: =GETPIVOTDATA("Count of Line Item #",$A$3,"File Name",$A28)/GETPIVOTDATA("Count of Currency",$A$3,"File Name",$A28) -> 1 | W28: =GETPIVOTDATA("Count of Line Item #",$A$3,"File Name",$A28)/GETPIVOTDATA("Count of Article Number",$A$3,"File Name",$A28) -> 1 | X28: =GETPIVOTDATA("Count of Line Item #",$A$3,"File Name",$A28)/GETPIVOTDATA("Count of Item Description",$A$3,"File Name",$A28) -> 1 | Y28: =GETPIVOTDATA("Count of Line Item #",$A$3,"File Name",$A28)/GETPIVOTDATA("Count of Quantity",$A$3,"File Name",$A28) -> 1 | Z28: =GETPIVOTDATA("Count of Line Item #",$A$3,"File Name",$A28)/GETPIVOTDATA("Count of Unit of Measure",$A$3,"File Name",$A28) -> 1 | AA28: =GETPIVOTDATA("Count of Line Item #",$A$3,"File Name",$A28)/GETPIVOTDATA("Count of Unit Price",$A$3,"File Name",$A28) -> 1 | AB28: =GETPIVOTDATA("Count of Item Planned Delivery Date",$A$3,"File Name",$A28)/GETPIVOTDATA("Count of Line Item #",$A$3,"File Name",$A28) -> 1
A29: Bevestiging bestelling S09313444-1.pdf | B29: Purchase Order Confirmation | C29: extracted | D29: 1 | E29: 1 | F29: 1 | G29: 1 | H29: 1 | I29: 1 | J29: 1 | K29: 1 | L29: 1 | M29: 1 | N29: 1 | O29: 1 | P29: 1 | Q29: =GETPIVOTDATA("Count of Line Item #",$A$3,"File Name",$A29)/GETPIVOTDATA("Count of Purchase Order Number",$A$3,"File Name",$A29) -> 1 | R29: =GETPIVOTDATA("Count of Line Item #",$A$3,"File Name",$A29)/GETPIVOTDATA("Count of Supplier Order Number",$A$3,"File Name",$A29) -> 1 | S29: =GETPIVOTDATA("Count of Line Item #",$A$3,"File Name",$A29)/GETPIVOTDATA("Count of Order Date",$A$3,"File Name",$A29) -> 1 | T29: =GETPIVOTDATA("Count of Line Item #",$A$3,"File Name",$A29)/GETPIVOTDATA("Count of Supplier Name",$A$3,"File Name",$A29) -> 1 | U29: =GETPIVOTDATA("Count of Line Item #",$A$3,"File Name",$A29)/GETPIVOTDATA("Count of Customer Name",$A$3,"File Name",$A29) -> 1 | V29: =GETPIVOTDATA("Count of Line Item #",$A$3,"File Name",$A29)/GETPIVOTDATA("Count of Currency",$A$3,"File Name",$A29) -> 1 | W29: =GETPIVOTDATA("Count of Line Item #",$A$3,"File Name",$A29)/GETPIVOTDATA("Count of Article Number",$A$3,"File Name",$A29) -> 1 | X29: =GETPIVOTDATA("Count of Line Item #",$A$3,"File Name",$A29)/GETPIVOTDATA("Count of Item Description",$A$3,"File Name",$A29) -> 1 | Y29: =GETPIVOTDATA("Count of Line Item #",$A$3,"File Name",$A29)/GETPIVOTDATA("Count of Quantity",$A$3,"File Name",$A29) -> 1 | Z29: =GETPIVOTDATA("Count of Line Item #",$A$3,"File Name",$A29)/GETPIVOTDATA("Count of Unit of Measure",$A$3,"File Name",$A29) -> 1 | AA29: =GETPIVOTDATA("Count of Line Item #",$A$3,"File Name",$A29)/GETPIVOTDATA("Count of Unit Price",$A$3,"File Name",$A29) -> 1 | AB29: =GETPIVOTDATA("Count of Item Planned Delivery Date",$A$3,"File Name",$A29)/GETPIVOTDATA("Count of Line Item #",$A$3,"File Name",$A29) -> 1
A30: Bevestiging bestelling S09313481-1.pdf | B30: Purchase Order Confirmation | C30: extracted | D30: 1 | E30: 1 | F30: 1 | G30: 1 | H30: 1 | I30: 1 | J30: 1 | K30: 1 | L30: 1 | M30: 1 | N30: 1 | O30: 1 | P30: 1 | Q30: =GETPIVOTDATA("Count of Line Item #",$A$3,"File Name",$A30)/GETPIVOTDATA("Count of Purchase Order Number",$A$3,"File Name",$A30) -> 1 | R30: =GETPIVOTDATA("Count of Line Item #",$A$3,"File Name",$A30)/GETPIVOTDATA("Count of Supplier Order Number",$A$3,"File Name",$A30) -> 1 | S30: =GETPIVOTDATA("Count of Line Item #",$A$3,"File Name",$A30)/GETPIVOTDATA("Count of Order Date",$A$3,"File Name",$A30) -> 1 | T30: =GETPIVOTDATA("Count of Line Item #",$A$3,"File Name",$A30)/GETPIVOTDATA("Count of Supplier Name",$A$3,"File Name",$A30) -> 1 | U30: =GETPIVOTDATA("Count of Line Item #",$A$3,"File Name",$A30)/GETPIVOTDATA("Count of Customer Name",$A$3,"File Name",$A30) -> 1 | V30: =GETPIVOTDATA("Count of Line Item #",$A$3,"File Name",$A30)/GETPIVOTDATA("Count of Currency",$A$3,"File Name",$A30) -> 1 | W30: =GETPIVOTDATA("Count of Line Item #",$A$3,"File Name",$A30)/GETPIVOTDATA("Count of Article Number",$A$3,"File Name",$A30) -> 1 | X30: =GETPIVOTDATA("Count of Line Item #",$A$3,"File Name",$A30)/GETPIVOTDATA("Count of Item Description",$A$3,"File Name",$A30) -> 1 | Y30: =GETPIVOTDATA("Count of Line Item #",$A$3,"File Name",$A30)/GETPIVOTDATA("Count of Quantity",$A$3,"File Name",$A30) -> 1 | Z30: =GETPIVOTDATA("Count of Line Item #",$A$3,"File Name",$A30)/GETPIVOTDATA("Count of Unit of Measure",$A$3,"File Name",$A30) -> 1 | AA30: =GETPIVOTDATA("Count of Line Item #",$A$3,"File Name",$A30)/GETPIVOTDATA("Count of Unit Price",$A$3,"File Name",$A30) -> 1 | AB30: =GETPIVOTDATA("Count of Item Planned Delivery Date",$A$3,"File Name",$A30)/GETPIVOTDATA("Count of Line Item #",$A$3,"File Name",$A30) -> 1
A31: Bevestiging bestelling S09313926-1.pdf | B31: Purchase Order Confirmation | C31: extracted | D31: 1 | E31: 1 | F31: 1 | G31: 1 | H31: 1 | I31: 1 | J31: 1 | K31: 1 | L31: 1 | M31: 1 | N31: 1 | O31: 1 | P31: 1 | Q31: =GETPIVOTDATA("Count of Line Item #",$A$3,"File Name",$A31)/GETPIVOTDATA("Count of Purchase Order Number",$A$3,"File Name",$A31) -> 1 | R31: =GETPIVOTDATA("Count of Line Item #",$A$3,"File Name",$A31)/GETPIVOTDATA("Count of Supplier Order Number",$A$3,"File Name",$A31) -> 1 | S31: =GETPIVOTDATA("Count of Line Item #",$A$3,"File Name",$A31)/GETPIVOTDATA("Count of Order Date",$A$3,"File Name",$A31) -> 1 | T31: =GETPIVOTDATA("Count of Line Item #",$A$3,"File Name",$A31)/GETPIVOTDATA("Count of Supplier Name",$A$3,"File Name",$A31) -> 1 | U31: =GETPIVOTDATA("Count of Line Item #",$A$3,"File Name",$A31)/GETPIVOTDATA("Count of Customer Name",$A$3,"File Name",$A31) -> 1 | V31: =GETPIVOTDATA("Count of Line Item #",$A$3,"File Name",$A31)/GETPIVOTDATA("Count of Currency",$A$3,"File Name",$A31) -> 1 | W31: =GETPIVOTDATA("Count of Line Item #",$A$3,"File Name",$A31)/GETPIVOTDATA("Count of Article Number",$A$3,"File Name",$A31) -> 1 | X31: =GETPIVOTDATA("Count of Line Item #",$A$3,"File Name",$A31)/GETPIVOTDATA("Count of Item Description",$A$3,"File Name",$A31) -> 1 | Y31: =GETPIVOTDATA("Count of Line Item #",$A$3,"File Name",$A31)/GETPIVOTDATA("Count of Quantity",$A$3,"File Name",$A31) -> 1 | Z31: =GETPIVOTDATA("Count of Line Item #",$A$3,"File Name",$A31)/GETPIVOTDATA("Count of Unit of Measure",$A$3,"File Name",$A31) -> 1 | AA31: =GETPIVOTDATA("Count of Line Item #",$A$3,"File Name",$A31)/GETPIVOTDATA("Count of Unit Price",$A$3,"File Name",$A31) -> 1 | AB31: =GETPIVOTDATA("Count of Item Planned Delivery Date",$A$3,"File Name",$A31)/GETPIVOTDATA("Count of Line Item #",$A$3,"File Name",$A31) -> 1
A32: Bevestiging bestelling S09313928-1.pdf | B32: Purchase Order Confirmation | C32: extracted | D32: 2 | E32: 2 | F32: 2 | G32: 2 | H32: 2 | I32: 2 | J32: 2 | K32: 2 | L32: 2 | M32: 2 | N32: 2 | O32: 2 | P32: 2 | Q32: =GETPIVOTDATA("Count of Line Item #",$A$3,"File Name",$A32)/GETPIVOTDATA("Count of Purchase Order Number",$A$3,"File Name",$A32) -> 1 | R32: =GETPIVOTDATA("Count of Line Item #",$A$3,"File Name",$A32)/GETPIVOTDATA("Count of Supplier Order Number",$A$3,"File Name",$A32) -> 1 | S32: =GETPIVOTDATA("Count of Line Item #",$A$3,"File Name",$A32)/GETPIVOTDATA("Count of Order Date",$A$3,"File Name",$A32) -> 1 | T32: =GETPIVOTDATA("Count of Line Item #",$A$3,"File Name",$A32)/GETPIVOTDATA("Count of Supplier Name",$A$3,"File Name",$A32) -> 1 | U32: =GETPIVOTDATA("Count of Line Item #",$A$3,"File Name",$A32)/GETPIVOTDATA("Count of Customer Name",$A$3,"File Name",$A32) -> 1 | V32: =GETPIVOTDATA("Count of Line Item #",$A$3,"File Name",$A32)/GETPIVOTDATA("Count of Currency",$A$3,"File Name",$A32) -> 1 | W32: =GETPIVOTDATA("Count of Line Item #",$A$3,"File Name",$A32)/GETPIVOTDATA("Count of Article Number",$A$3,"File Name",$A32) -> 1 | X32: =GETPIVOTDATA("Count of Line Item #",$A$3,"File Name",$A32)/GETPIVOTDATA("Count of Item Description",$A$3,"File Name",$A32) -> 1 | Y32: =GETPIVOTDATA("Count of Line Item #",$A$3,"File Name",$A32)/GETPIVOTDATA("Count of Quantity",$A$3,"File Name",$A32) -> 1 | Z32: =GETPIVOTDATA("Count of Line Item #",$A$3,"File Name",$A32)/GETPIVOTDATA("Count of Unit of Measure",$A$3,"File Name",$A32) -> 1 | AA32: =GETPIVOTDATA("Count of Line Item #",$A$3,"File Name",$A32)/GETPIVOTDATA("Count of Unit Price",$A$3,"File Name",$A32) -> 1 | AB32: =GETPIVOTDATA("Count of Item Planned Delivery Date",$A$3,"File Name",$A32)/GETPIVOTDATA("Count of Line Item #",$A$3,"File Name",$A32) -> 1
A33: Confirmation C007-S2607613-1.pdf | B33: Purchase Order Confirmation | C33: extracted | D33: 11 | E33: 11 | F33: 11 | G33: 11 | H33: 11 | I33: 11 | J33: 11 | K33: 11 | L33: 11 | M33: 11 | N33: 11 | O33: 11 | P33: 11 | Q33: =GETPIVOTDATA("Count of Line Item #",$A$3,"File Name",$A33)/GETPIVOTDATA("Count of Purchase Order Number",$A$3,"File Name",$A33) -> 1 | R33: =GETPIVOTDATA("Count of Line Item #",$A$3,"File Name",$A33)/GETPIVOTDATA("Count of Supplier Order Number",$A$3,"File Name",$A33) -> 1 | S33: =GETPIVOTDATA("Count of Line Item #",$A$3,"File Name",$A33)/GETPIVOTDATA("Count of Order Date",$A$3,"File Name",$A33) -> 1 | T33: =GETPIVOTDATA("Count of Line Item #",$A$3,"File Name",$A33)/GETPIVOTDATA("Count of Supplier Name",$A$3,"File Name",$A33) -> 1 | U33: =GETPIVOTDATA("Count of Line Item #",$A$3,"File Name",$A33)/GETPIVOTDATA("Count of Customer Name",$A$3,"File Name",$A33) -> 1 | V33: =GETPIVOTDATA("Count of Line Item #",$A$3,"File Name",$A33)/GETPIVOTDATA("Count of Currency",$A$3,"File Name",$A33) -> 1 | W33: =GETPIVOTDATA("Count of Line Item #",$A$3,"File Name",$A33)/GETPIVOTDATA("Count of Article Number",$A$3,"File Name",$A33) -> 1 | X33: =GETPIVOTDATA("Count of Line Item #",$A$3,"File Name",$A33)/GETPIVOTDATA("Count of Item Description",$A$3,"File Name",$A33) -> 1 | Y33: =GETPIVOTDATA("Count of Line Item #",$A$3,"File Name",$A33)/GETPIVOTDATA("Count of Quantity",$A$3,"File Name",$A33) -> 1 | Z33: =GETPIVOTDATA("Count of Line Item #",$A$3,"File Name",$A33)/GETPIVOTDATA("Count of Unit of Measure",$A$3,"File Name",$A33) -> 1 | AA33: =GETPIVOTDATA("Count of Line Item #",$A$3,"File Name",$A33)/GETPIVOTDATA("Count of Unit Price",$A$3,"File Name",$A33) -> 1 | AB33: =GETPIVOTDATA("Count of Item Planned Delivery Date",$A$3,"File Name",$A33)/GETPIVOTDATA("Count of Line Item #",$A$3,"File Name",$A33) -> 1
A34: Confirmation Commande S09313483-1.pdf | B34: Purchase Order Confirmation | C34: extracted | D34: 2 | E34: 2 | F34: 2 | G34: 2 | H34: 2 | I34: 2 | J34: 2 | K34: 2 | L34: 2 | M34: 2 | N34: 2 | O34: 2 | P34: 2 | Q34: =GETPIVOTDATA("Count of Line Item #",$A$3,"File Name",$A34)/GETPIVOTDATA("Count of Purchase Order Number",$A$3,"File Name",$A34) -> 1 | R34: =GETPIVOTDATA("Count of Line Item #",$A$3,"File Name",$A34)/GETPIVOTDATA("Count of Supplier Order Number",$A$3,"File Name",$A34) -> 1 | S34: =GETPIVOTDATA("Count of Line Item #",$A$3,"File Name",$A34)/GETPIVOTDATA("Count of Order Date",$A$3,"File Name",$A34) -> 1 | T34: =GETPIVOTDATA("Count of Line Item #",$A$3,"File Name",$A34)/GETPIVOTDATA("Count of Supplier Name",$A$3,"File Name",$A34) -> 1 | U34: =GETPIVOTDATA("Count of Line Item #",$A$3,"File Name",$A34)/GETPIVOTDATA("Count of Customer Name",$A$3,"File Name",$A34) -> 1 | V34: =GETPIVOTDATA("Count of Line Item #",$A$3,"File Name",$A34)/GETPIVOTDATA("Count of Currency",$A$3,"File Name",$A34) -> 1 | W34: =GETPIVOTDATA("Count of Line Item #",$A$3,"File Name",$A34)/GETPIVOTDATA("Count of Article Number",$A$3,"File Name",$A34) -> 1 | X34: =GETPIVOTDATA("Count of Line Item #",$A$3,"File Name",$A34)/GETPIVOTDATA("Count of Item Description",$A$3,"File Name",$A34) -> 1 | Y34: =GETPIVOTDATA("Count of Line Item #",$A$3,"File Name",$A34)/GETPIVOTDATA("Count of Quantity",$A$3,"File Name",$A34) -> 1 | Z34: =GETPIVOTDATA("Count of Line Item #",$A$3,"File Name",$A34)/GETPIVOTDATA("Count of Unit of Measure",$A$3,"File Name",$A34) -> 1 | AA34: =GETPIVOTDATA("Count of Line Item #",$A$3,"File Name",$A34)/GETPIVOTDATA("Count of Unit Price",$A$3,"File Name",$A34) -> 1 | AB34: =GETPIVOTDATA("Count of Item Planned Delivery Date",$A$3,"File Name",$A34)/GETPIVOTDATA("Count of Line Item #",$A$3,"File Name",$A34) -> 1
A35: Embal.bon_100726_Sligro_5061_klant_000142470.pdf | B35: Purchase Order Confirmation | C35: unclassified | Q35: =GETPIVOTDATA("Count of Line Item #",$A$3,"File Name",$A35)/GETPIVOTDATA("Count of Purchase Order Number",$A$3,"File Name",$A35) -> #DIV/0! | R35: =GETPIVOTDATA("Count of Line Item #",$A$3,"File Name",$A35)/GETPIVOTDATA("Count of Supplier Order Number",$A$3,"File Name",$A35) -> #DIV/0! | S35: =GETPIVOTDATA("Count of Line Item #",$A$3,"File Name",$A35)/GETPIVOTDATA("Count of Order Date",$A$3,"File Name",$A35) -> #DIV/0! | T35: =GETPIVOTDATA("Count of Line Item #",$A$3,"File Name",$A35)/GETPIVOTDATA("Count of Supplier Name",$A$3,"File Name",$A35) -> #DIV/0! | U35: =GETPIVOTDATA("Count of Line Item #",$A$3,"File Name",$A35)/GETPIVOTDATA("Count of Customer Name",$A$3,"File Name",$A35) -> #DIV/0! | V35: =GETPIVOTDATA("Count of Line Item #",$A$3,"File Name",$A35)/GETPIVOTDATA("Count of Currency",$A$3,"File Name",$A35) -> #DIV/0! | W35: =GETPIVOTDATA("Count of Line Item #",$A$3,"File Name",$A35)/GETPIVOTDATA("Count of Article Number",$A$3,"File Name",$A35) -> #DIV/0! | X35: =GETPIVOTDATA("Count of Line Item #",$A$3,"File Name",$A35)/GETPIVOTDATA("Count of Item Description",$A$3,"File Name",$A35) -> #DIV/0! | Y35: =GETPIVOTDATA("Count of Line Item #",$A$3,"File Name",$A35)/GETPIVOTDATA("Count of Quantity",$A$3,"File Name",$A35) -> #DIV/0! | Z35: =GETPIVOTDATA("Count of Line Item #",$A$3,"File Name",$A35)/GETPIVOTDATA("Count of Unit of Measure",$A$3,"File Name",$A35) -> #DIV/0! | AA35: =GETPIVOTDATA("Count of Line Item #",$A$3,"File Name",$A35)/GETPIVOTDATA("Count of Unit Price",$A$3,"File Name",$A35) -> #DIV/0! | AB35: =GETPIVOTDATA("Count of Item Planned Delivery Date",$A$3,"File Name",$A35)/GETPIVOTDATA("Count of Line Item #",$A$3,"File Name",$A35) -> #DIV/0!
A36: FW_ ORDERBEVESTIGING NL327171, Deb.nr. 110890HE, Uw order_ 3507009725.pdf | B36: Purchase Order Confirmation | C36: extracted | D36: 30 | E36: 30 | F36: 30 | G36: 30 | H36: 30 | I36: 30 | J36: 30 | K36: 30 | L36: 30 | M36: 30 | N36: 30 | O36: 30 | P36: 30 | Q36: =GETPIVOTDATA("Count of Line Item #",$A$3,"File Name",$A36)/GETPIVOTDATA("Count of Purchase Order Number",$A$3,"File Name",$A36) -> 1 | R36: =GETPIVOTDATA("Count of Line Item #",$A$3,"File Name",$A36)/GETPIVOTDATA("Count of Supplier Order Number",$A$3,"File Name",$A36) -> 1 | S36: =GETPIVOTDATA("Count of Line Item #",$A$3,"File Name",$A36)/GETPIVOTDATA("Count of Order Date",$A$3,"File Name",$A36) -> 1 | T36: =GETPIVOTDATA("Count of Line Item #",$A$3,"File Name",$A36)/GETPIVOTDATA("Count of Supplier Name",$A$3,"File Name",$A36) -> 1 | U36: =GETPIVOTDATA("Count of Line Item #",$A$3,"File Name",$A36)/GETPIVOTDATA("Count of Customer Name",$A$3,"File Name",$A36) -> 1 | V36: =GETPIVOTDATA("Count of Line Item #",$A$3,"File Name",$A36)/GETPIVOTDATA("Count of Currency",$A$3,"File Name",$A36) -> 1 | W36: =GETPIVOTDATA("Count of Line Item #",$A$3,"File Name",$A36)/GETPIVOTDATA("Count of Article Number",$A$3,"File Name",$A36) -> 1 | X36: =GETPIVOTDATA("Count of Line Item #",$A$3,"File Name",$A36)/GETPIVOTDATA("Count of Item Description",$A$3,"File Name",$A36) -> 1 | Y36: =GETPIVOTDATA("Count of Line Item #",$A$3,"File Name",$A36)/GETPIVOTDATA("Count of Quantity",$A$3,"File Name",$A36) -> 1 | Z36: =GETPIVOTDATA("Count of Line Item #",$A$3,"File Name",$A36)/GETPIVOTDATA("Count of Unit of Measure",$A$3,"File Name",$A36) -> 1 | AA36: =GETPIVOTDATA("Count of Line Item #",$A$3,"File Name",$A36)/GETPIVOTDATA("Count of Unit Price",$A$3,"File Name",$A36) -> 1 | AB36: =GETPIVOTDATA("Count of Item Planned Delivery Date",$A$3,"File Name",$A36)/GETPIVOTDATA("Count of Line Item #",$A$3,"File Name",$A36) -> 1
A37: Hartmann _ Order bevestiging.pdf | B37: Purchase Order Confirmation | C37: extracted | D37: 27 | E37: 27 | F37: 27 | G37: 27 | H37: 27 | I37: 27 | J37: 27 | K37: 27 | L37: 27 | M37: 27 | N37: 27 | O37: 27 | P37: 27 | Q37: =GETPIVOTDATA("Count of Line Item #",$A$3,"File Name",$A37)/GETPIVOTDATA("Count of Purchase Order Number",$A$3,"File Name",$A37) -> 1 | R37: =GETPIVOTDATA("Count of Line Item #",$A$3,"File Name",$A37)/GETPIVOTDATA("Count of Supplier Order Number",$A$3,"File Name",$A37) -> 1 | S37: =GETPIVOTDATA("Count of Line Item #",$A$3,"File Name",$A37)/GETPIVOTDATA("Count of Order Date",$A$3,"File Name",$A37) -> 1 | T37: =GETPIVOTDATA("Count of Line Item #",$A$3,"File Name",$A37)/GETPIVOTDATA("Count of Supplier Name",$A$3,"File Name",$A37) -> 1 | U37: =GETPIVOTDATA("Count of Line Item #",$A$3,"File Name",$A37)/GETPIVOTDATA("Count of Customer Name",$A$3,"File Name",$A37) -> 1 | V37: =GETPIVOTDATA("Count of Line Item #",$A$3,"File Name",$A37)/GETPIVOTDATA("Count of Currency",$A$3,"File Name",$A37) -> 1 | W37: =GETPIVOTDATA("Count of Line Item #",$A$3,"File Name",$A37)/GETPIVOTDATA("Count of Article Number",$A$3,"File Name",$A37) -> 1 | X37: =GETPIVOTDATA("Count of Line Item #",$A$3,"File Name",$A37)/GETPIVOTDATA("Count of Item Description",$A$3,"File Name",$A37) -> 1 | Y37: =GETPIVOTDATA("Count of Line Item #",$A$3,"File Name",$A37)/GETPIVOTDATA("Count of Quantity",$A$3,"File Name",$A37) -> 1 | Z37: =GETPIVOTDATA("Count of Line Item #",$A$3,"File Name",$A37)/GETPIVOTDATA("Count of Unit of Measure",$A$3,"File Name",$A37) -> 1 | AA37: =GETPIVOTDATA("Count of Line Item #",$A$3,"File Name",$A37)/GETPIVOTDATA("Count of Unit Price",$A$3,"File Name",$A37) -> 1 | AB37: =GETPIVOTDATA("Count of Item Planned Delivery Date",$A$3,"File Name",$A37)/GETPIVOTDATA("Count of Line Item #",$A$3,"File Name",$A37) -> 1
A38: HARTMANN_ ORDERBEVESTIGING0021752283.pdf | B38: Purchase Order Confirmation | C38: extracted | D38: 4 | E38: 4 | F38: 4 | G38: 4 | H38: 4 | I38: 4 | J38: 4 | K38: 4 | L38: 4 | M38: 4 | N38: 4 | O38: 4 | P38: 4 | Q38: =GETPIVOTDATA("Count of Line Item #",$A$3,"File Name",$A38)/GETPIVOTDATA("Count of Purchase Order Number",$A$3,"File Name",$A38) -> 1 | R38: =GETPIVOTDATA("Count of Line Item #",$A$3,"File Name",$A38)/GETPIVOTDATA("Count of Supplier Order Number",$A$3,"File Name",$A38) -> 1 | S38: =GETPIVOTDATA("Count of Line Item #",$A$3,"File Name",$A38)/GETPIVOTDATA("Count of Order Date",$A$3,"File Name",$A38) -> 1 | T38: =GETPIVOTDATA("Count of Line Item #",$A$3,"File Name",$A38)/GETPIVOTDATA("Count of Supplier Name",$A$3,"File Name",$A38) -> 1 | U38: =GETPIVOTDATA("Count of Line Item #",$A$3,"File Name",$A38)/GETPIVOTDATA("Count of Customer Name",$A$3,"File Name",$A38) -> 1 | V38: =GETPIVOTDATA("Count of Line Item #",$A$3,"File Name",$A38)/GETPIVOTDATA("Count of Currency",$A$3,"File Name",$A38) -> 1 | W38: =GETPIVOTDATA("Count of Line Item #",$A$3,"File Name",$A38)/GETPIVOTDATA("Count of Article Number",$A$3,"File Name",$A38) -> 1 | X38: =GETPIVOTDATA("Count of Line Item #",$A$3,"File Name",$A38)/GETPIVOTDATA("Count of Item Description",$A$3,"File Name",$A38) -> 1 | Y38: =GETPIVOTDATA("Count of Line Item #",$A$3,"File Name",$A38)/GETPIVOTDATA("Count of Quantity",$A$3,"File Name",$A38) -> 1 | Z38: =GETPIVOTDATA("Count of Line Item #",$A$3,"File Name",$A38)/GETPIVOTDATA("Count of Unit of Measure",$A$3,"File Name",$A38) -> 1 | AA38: =GETPIVOTDATA("Count of Line Item #",$A$3,"File Name",$A38)/GETPIVOTDATA("Count of Unit Price",$A$3,"File Name",$A38) -> 1 | AB38: =GETPIVOTDATA("Count of Item Planned Delivery Date",$A$3,"File Name",$A38)/GETPIVOTDATA("Count of Line Item #",$A$3,"File Name",$A38) -> 1
A39: HARTMANN_ ORDERBEVESTIGING0021752292.pdf | B39: Purchase Order Confirmation | C39: extracted | D39: 42 | E39: 42 | F39: 42 | G39: 42 | H39: 42 | I39: 42 | J39: 42 | K39: 42 | L39: 42 | M39: 42 | N39: 42 | O39: 42 | P39: 42 | Q39: =GETPIVOTDATA("Count of Line Item #",$A$3,"File Name",$A39)/GETPIVOTDATA("Count of Purchase Order Number",$A$3,"File Name",$A39) -> 1 | R39: =GETPIVOTDATA("Count of Line Item #",$A$3,"File Name",$A39)/GETPIVOTDATA("Count of Supplier Order Number",$A$3,"File Name",$A39) -> 1 | S39: =GETPIVOTDATA("Count of Line Item #",$A$3,"File Name",$A39)/GETPIVOTDATA("Count of Order Date",$A$3,"File Name",$A39) -> 1 | T39: =GETPIVOTDATA("Count of Line Item #",$A$3,"File Name",$A39)/GETPIVOTDATA("Count of Supplier Name",$A$3,"File Name",$A39) -> 1 | U39: =GETPIVOTDATA("Count of Line Item #",$A$3,"File Name",$A39)/GETPIVOTDATA("Count of Customer Name",$A$3,"File Name",$A39) -> 1 | V39: =GETPIVOTDATA("Count of Line Item #",$A$3,"File Name",$A39)/GETPIVOTDATA("Count of Currency",$A$3,"File Name",$A39) -> 1 | W39: =GETPIVOTDATA("Count of Line Item #",$A$3,"File Name",$A39)/GETPIVOTDATA("Count of Article Number",$A$3,"File Name",$A39) -> 1 | X39: =GETPIVOTDATA("Count of Line Item #",$A$3,"File Name",$A39)/GETPIVOTDATA("Count of Item Description",$A$3,"File Name",$A39) -> 1 | Y39: =GETPIVOTDATA("Count of Line Item #",$A$3,"File Name",$A39)/GETPIVOTDATA("Count of Quantity",$A$3,"File Name",$A39) -> 1 | Z39: =GETPIVOTDATA("Count of Line Item #",$A$3,"File Name",$A39)/GETPIVOTDATA("Count of Unit of Measure",$A$3,"File Name",$A39) -> 1 | AA39: =GETPIVOTDATA("Count of Line Item #",$A$3,"File Name",$A39)/GETPIVOTDATA("Count of Unit Price",$A$3,"File Name",$A39) -> 1 | AB39: =GETPIVOTDATA("Count of Item Planned Delivery Date",$A$3,"File Name",$A39)/GETPIVOTDATA("Count of Line Item #",$A$3,"File Name",$A39) -> 1
A40: HARTMANN_ ORDERBEVESTIGING0021752293.pdf | B40: Purchase Order Confirmation | C40: extracted | D40: 13 | E40: 13 | F40: 13 | G40: 13 | H40: 13 | I40: 13 | J40: 13 | K40: 13 | L40: 13 | M40: 13 | N40: 13 | O40: 13 | P40: 13 | Q40: =GETPIVOTDATA("Count of Line Item #",$A$3,"File Name",$A40)/GETPIVOTDATA("Count of Purchase Order Number",$A$3,"File Name",$A40) -> 1 | R40: =GETPIVOTDATA("Count of Line Item #",$A$3,"File Name",$A40)/GETPIVOTDATA("Count of Supplier Order Number",$A$3,"File Name",$A40) -> 1 | S40: =GETPIVOTDATA("Count of Line Item #",$A$3,"File Name",$A40)/GETPIVOTDATA("Count of Order Date",$A$3,"File Name",$A40) -> 1 | T40: =GETPIVOTDATA("Count of Line Item #",$A$3,"File Name",$A40)/GETPIVOTDATA("Count of Supplier Name",$A$3,"File Name",$A40) -> 1 | U40: =GETPIVOTDATA("Count of Line Item #",$A$3,"File Name",$A40)/GETPIVOTDATA("Count of Customer Name",$A$3,"File Name",$A40) -> 1 | V40: =GETPIVOTDATA("Count of Line Item #",$A$3,"File Name",$A40)/GETPIVOTDATA("Count of Currency",$A$3,"File Name",$A40) -> 1 | W40: =GETPIVOTDATA("Count of Line Item #",$A$3,"File Name",$A40)/GETPIVOTDATA("Count of Article Number",$A$3,"File Name",$A40) -> 1 | X40: =GETPIVOTDATA("Count of Line Item #",$A$3,"File Name",$A40)/GETPIVOTDATA("Count of Item Description",$A$3,"File Name",$A40) -> 1 | Y40: =GETPIVOTDATA("Count of Line Item #",$A$3,"File Name",$A40)/GETPIVOTDATA("Count of Quantity",$A$3,"File Name",$A40) -> 1 | Z40: =GETPIVOTDATA("Count of Line Item #",$A$3,"File Name",$A40)/GETPIVOTDATA("Count of Unit of Measure",$A$3,"File Name",$A40) -> 1 | AA40: =GETPIVOTDATA("Count of Line Item #",$A$3,"File Name",$A40)/GETPIVOTDATA("Count of Unit Price",$A$3,"File Name",$A40) -> 1 | AB40: =GETPIVOTDATA("Count of Item Planned Delivery Date",$A$3,"File Name",$A40)/GETPIVOTDATA("Count of Line Item #",$A$3,"File Name",$A40) -> 1
A41: Informatie betreffende een JAVA levering.pdf | B41: Purchase Order Confirmation | C41: unclassified | Q41: =GETPIVOTDATA("Count of Line Item #",$A$3,"File Name",$A41)/GETPIVOTDATA("Count of Purchase Order Number",$A$3,"File Name",$A41) -> #REF! | R41: =GETPIVOTDATA("Count of Line Item #",$A$3,"File Name",$A41)/GETPIVOTDATA("Count of Supplier Order Number",$A$3,"File Name",$A41) -> #REF! | S41: =GETPIVOTDATA("Count of Line Item #",$A$3,"File Name",$A41)/GETPIVOTDATA("Count of Order Date",$A$3,"File Name",$A41) -> #REF! | T41: =GETPIVOTDATA("Count of Line Item #",$A$3,"File Name",$A41)/GETPIVOTDATA("Count of Supplier Name",$A$3,"File Name",$A41) -> #REF! | U41: =GETPIVOTDATA("Count of Line Item #",$A$3,"File Name",$A41)/GETPIVOTDATA("Count of Customer Name",$A$3,"File Name",$A41) -> #REF! | V41: =GETPIVOTDATA("Count of Line Item #",$A$3,"File Name",$A41)/GETPIVOTDATA("Count of Currency",$A$3,"File Name",$A41) -> #REF! | W41: =GETPIVOTDATA("Count of Line Item #",$A$3,"File Name",$A41)/GETPIVOTDATA("Count of Article Number",$A$3,"File Name",$A41) -> #REF! | X41: =GETPIVOTDATA("Count of Line Item #",$A$3,"File Name",$A41)/GETPIVOTDATA("Count of Item Description",$A$3,"File Name",$A41) -> #REF! | Y41: =GETPIVOTDATA("Count of Line Item #",$A$3,"File Name",$A41)/GETPIVOTDATA("Count of Quantity",$A$3,"File Name",$A41) -> #REF! | Z41: =GETPIVOTDATA("Count of Line Item #",$A$3,"File Name",$A41)/GETPIVOTDATA("Count of Unit of Measure",$A$3,"File Name",$A41) -> #REF! | AA41: =GETPIVOTDATA("Count of Line Item #",$A$3,"File Name",$A41)/GETPIVOTDATA("Count of Unit Price",$A$3,"File Name",$A41) -> #REF! | AB41: =GETPIVOTDATA("Count of Item Planned Delivery Date",$A$3,"File Name",$A41)/GETPIVOTDATA("Count of Line Item #",$A$3,"File Name",$A41) -> #REF!
A42: Informatie betreffende een JAVA levering.pdf | B42: (blank) | C42: unclassified | Q42: =GETPIVOTDATA("Count of Line Item #",$A$3,"File Name",$A42)/GETPIVOTDATA("Count of Purchase Order Number",$A$3,"File Name",$A42) -> #REF! | R42: =GETPIVOTDATA("Count of Line Item #",$A$3,"File Name",$A42)/GETPIVOTDATA("Count of Supplier Order Number",$A$3,"File Name",$A42) -> #REF! | S42: =GETPIVOTDATA("Count of Line Item #",$A$3,"File Name",$A42)/GETPIVOTDATA("Count of Order Date",$A$3,"File Name",$A42) -> #REF! | T42: =GETPIVOTDATA("Count of Line Item #",$A$3,"File Name",$A42)/GETPIVOTDATA("Count of Supplier Name",$A$3,"File Name",$A42) -> #REF! | U42: =GETPIVOTDATA("Count of Line Item #",$A$3,"File Name",$A42)/GETPIVOTDATA("Count of Customer Name",$A$3,"File Name",$A42) -> #REF! | V42: =GETPIVOTDATA("Count of Line Item #",$A$3,"File Name",$A42)/GETPIVOTDATA("Count of Currency",$A$3,"File Name",$A42) -> #REF! | W42: =GETPIVOTDATA("Count of Line Item #",$A$3,"File Name",$A42)/GETPIVOTDATA("Count of Article Number",$A$3,"File Name",$A42) -> #REF! | X42: =GETPIVOTDATA("Count of Line Item #",$A$3,"File Name",$A42)/GETPIVOTDATA("Count of Item Description",$A$3,"File Name",$A42) -> #REF! | Y42: =GETPIVOTDATA("Count of Line Item #",$A$3,"File Name",$A42)/GETPIVOTDATA("Count of Quantity",$A$3,"File Name",$A42) -> #REF! | Z42: =GETPIVOTDATA("Count of Line Item #",$A$3,"File Name",$A42)/GETPIVOTDATA("Count of Unit of Measure",$A$3,"File Name",$A42) -> #REF! | AA42: =GETPIVOTDATA("Count of Line Item #",$A$3,"File Name",$A42)/GETPIVOTDATA("Count of Unit Price",$A$3,"File Name",$A42) -> #REF! | AB42: =GETPIVOTDATA("Count of Item Planned Delivery Date",$A$3,"File Name",$A42)/GETPIVOTDATA("Count of Line Item #",$A$3,"File Name",$A42) -> #REF!
A43: JAVA leveringsinformatie.pdf | B43: Purchase Order Confirmation | C43: extracted | Q43: =GETPIVOTDATA("Count of Line Item #",$A$3,"File Name",$A43)/GETPIVOTDATA("Count of Purchase Order Number",$A$3,"File Name",$A43) -> #REF! | R43: =GETPIVOTDATA("Count of Line Item #",$A$3,"File Name",$A43)/GETPIVOTDATA("Count of Supplier Order Number",$A$3,"File Name",$A43) -> #REF! | S43: =GETPIVOTDATA("Count of Line Item #",$A$3,"File Name",$A43)/GETPIVOTDATA("Count of Order Date",$A$3,"File Name",$A43) -> #REF! | T43: =GETPIVOTDATA("Count of Line Item #",$A$3,"File Name",$A43)/GETPIVOTDATA("Count of Supplier Name",$A$3,"File Name",$A43) -> #REF! | U43: =GETPIVOTDATA("Count of Line Item #",$A$3,"File Name",$A43)/GETPIVOTDATA("Count of Customer Name",$A$3,"File Name",$A43) -> #REF! | V43: =GETPIVOTDATA("Count of Line Item #",$A$3,"File Name",$A43)/GETPIVOTDATA("Count of Currency",$A$3,"File Name",$A43) -> #REF! | W43: =GETPIVOTDATA("Count of Line Item #",$A$3,"File Name",$A43)/GETPIVOTDATA("Count of Article Number",$A$3,"File Name",$A43) -> #REF! | X43: =GETPIVOTDATA("Count of Line Item #",$A$3,"File Name",$A43)/GETPIVOTDATA("Count of Item Description",$A$3,"File Name",$A43) -> #REF! | Y43: =GETPIVOTDATA("Count of Line Item #",$A$3,"File Name",$A43)/GETPIVOTDATA("Count of Quantity",$A$3,"File Name",$A43) -> #REF! | Z43: =GETPIVOTDATA("Count of Line Item #",$A$3,"File Name",$A43)/GETPIVOTDATA("Count of Unit of Measure",$A$3,"File Name",$A43) -> #REF! | AA43: =GETPIVOTDATA("Count of Line Item #",$A$3,"File Name",$A43)/GETPIVOTDATA("Count of Unit Price",$A$3,"File Name",$A43) -> #REF! | AB43: =GETPIVOTDATA("Count of Item Planned Delivery Date",$A$3,"File Name",$A43)/GETPIVOTDATA("Count of Line Item #",$A$3,"File Name",$A43) -> #REF!
A44: JAVA leveringsinformatie.pdf | B44: Purchase Order Confirmation | C44: unclassified | Q44: =GETPIVOTDATA("Count of Line Item #",$A$3,"File Name",$A44)/GETPIVOTDATA("Count of Purchase Order Number",$A$3,"File Name",$A44) -> #REF! | R44: =GETPIVOTDATA("Count of Line Item #",$A$3,"File Name",$A44)/GETPIVOTDATA("Count of Supplier Order Number",$A$3,"File Name",$A44) -> #REF! | S44: =GETPIVOTDATA("Count of Line Item #",$A$3,"File Name",$A44)/GETPIVOTDATA("Count of Order Date",$A$3,"File Name",$A44) -> #REF! | T44: =GETPIVOTDATA("Count of Line Item #",$A$3,"File Name",$A44)/GETPIVOTDATA("Count of Supplier Name",$A$3,"File Name",$A44) -> #REF! | U44: =GETPIVOTDATA("Count of Line Item #",$A$3,"File Name",$A44)/GETPIVOTDATA("Count of Customer Name",$A$3,"File Name",$A44) -> #REF! | V44: =GETPIVOTDATA("Count of Line Item #",$A$3,"File Name",$A44)/GETPIVOTDATA("Count of Currency",$A$3,"File Name",$A44) -> #REF! | W44: =GETPIVOTDATA("Count of Line Item #",$A$3,"File Name",$A44)/GETPIVOTDATA("Count of Article Number",$A$3,"File Name",$A44) -> #REF! | X44: =GETPIVOTDATA("Count of Line Item #",$A$3,"File Name",$A44)/GETPIVOTDATA("Count of Item Description",$A$3,"File Name",$A44) -> #REF! | Y44: =GETPIVOTDATA("Count of Line Item #",$A$3,"File Name",$A44)/GETPIVOTDATA("Count of Quantity",$A$3,"File Name",$A44) -> #REF! | Z44: =GETPIVOTDATA("Count of Line Item #",$A$3,"File Name",$A44)/GETPIVOTDATA("Count of Unit of Measure",$A$3,"File Name",$A44) -> #REF! | AA44: =GETPIVOTDATA("Count of Line Item #",$A$3,"File Name",$A44)/GETPIVOTDATA("Count of Unit Price",$A$3,"File Name",$A44) -> #REF! | AB44: =GETPIVOTDATA("Count of Item Planned Delivery Date",$A$3,"File Name",$A44)/GETPIVOTDATA("Count of Line Item #",$A$3,"File Name",$A44) -> #REF!
A45: Jouw Lyreco bestelling 1178683275 - 2505040761 is onderweg!.pdf | B45: Purchase Order Confirmation | C45: extracted | Q45: =GETPIVOTDATA("Count of Line Item #",$A$3,"File Name",$A45)/GETPIVOTDATA("Count of Purchase Order Number",$A$3,"File Name",$A45) -> #DIV/0! | R45: =GETPIVOTDATA("Count of Line Item #",$A$3,"File Name",$A45)/GETPIVOTDATA("Count of Supplier Order Number",$A$3,"File Name",$A45) -> #DIV/0! | S45: =GETPIVOTDATA("Count of Line Item #",$A$3,"File Name",$A45)/GETPIVOTDATA("Count of Order Date",$A$3,"File Name",$A45) -> #DIV/0! | T45: =GETPIVOTDATA("Count of Line Item #",$A$3,"File Name",$A45)/GETPIVOTDATA("Count of Supplier Name",$A$3,"File Name",$A45) -> #DIV/0! | U45: =GETPIVOTDATA("Count of Line Item #",$A$3,"File Name",$A45)/GETPIVOTDATA("Count of Customer Name",$A$3,"File Name",$A45) -> #DIV/0! | V45: =GETPIVOTDATA("Count of Line Item #",$A$3,"File Name",$A45)/GETPIVOTDATA("Count of Currency",$A$3,"File Name",$A45) -> #DIV/0! | W45: =GETPIVOTDATA("Count of Line Item #",$A$3,"File Name",$A45)/GETPIVOTDATA("Count of Article Number",$A$3,"File Name",$A45) -> #DIV/0! | X45: =GETPIVOTDATA("Count of Line Item #",$A$3,"File Name",$A45)/GETPIVOTDATA("Count of Item Description",$A$3,"File Name",$A45) -> #DIV/0! | Y45: =GETPIVOTDATA("Count of Line Item #",$A$3,"File Name",$A45)/GETPIVOTDATA("Count of Quantity",$A$3,"File Name",$A45) -> #DIV/0! | Z45: =GETPIVOTDATA("Count of Line Item #",$A$3,"File Name",$A45)/GETPIVOTDATA("Count of Unit of Measure",$A$3,"File Name",$A45) -> #DIV/0! | AA45: =GETPIVOTDATA("Count of Line Item #",$A$3,"File Name",$A45)/GETPIVOTDATA("Count of Unit Price",$A$3,"File Name",$A45) -> #DIV/0! | AB45: =GETPIVOTDATA("Count of Item Planned Delivery Date",$A$3,"File Name",$A45)/GETPIVOTDATA("Count of Line Item #",$A$3,"File Name",$A45) -> #DIV/0!
